Workbook
Name t_7092566280593B3BB2C1334FFD87BB75: 'Dropdown Lists'!$C$1:$N$1
Name t_EBE942180826316599849DBDC67BC840: 'Dropdown Lists'!$C$2:$D$2
Name t_B57E8C7A770F35A0BB7753EC0D5DEE56: 'Dropdown Lists'!$C$3:$D$3
Name t_14F2526269293CCF896C9AED8757E81A: 'Dropdown Lists'!$C$4:$G$4
Name t_12506A60C0C93D84978C908BCC35B3F8: 'Dropdown Lists'!$C$5:$H$5
Name t_8A82F0D250A131CB9678F7CD269E83CC: 'Dropdown Lists'!$C$6:$F$6
Name t_CAFFECC57A233C6B8496E27E94BD00CB: 'Dropdown Lists'!$C$7:$P$7
Name t_D6AB99606DBC3456B889DB0B1F4983B5: 'Dropdown Lists'!$C$8:$V$8
Name t_1E1124B7FC7B3954A750E25A69DB0658: 'Dropdown Lists'!$C$9:$L$9
Name t_051693175F4C3966A32680C3E926669D: 'Dropdown Lists'!$C$10:$F$10
Name t_8D7DCDFB1275340BB941677042807F6D: 'Dropdown Lists'!$C$11:$K$11
Name t_918E40D3EBF332149A0D44DF1196300A: 'Dropdown Lists'!$C$12:$K$12
Name t_B828B691B56D3478B51C1F1C2D71B611: 'Dropdown Lists'!$C$13:$S$13
Name t_967ABFFF1F2A3DF9AD8906E53C9D7D59: 'Dropdown Lists'!$C$14:$G$14
Name t_D959B5776CF4385C84E15E547C8B411C: 'Dropdown Lists'!$C$15:$H$15
Name t_96546FBB0668356C839991263B8C6D21: 'Dropdown Lists'!$C$16:$E$16
Name t_DA27226285E53EEF9D162B1EF4365EE2: 'Dropdown Lists'!$C$17:$C$17
Name t_A27F3AA7885C3505852C3B301309B57B: 'Dropdown Lists'!$C$18:$C$18
Name t_3773E4160E40388BA98ED300101B52CD: 'Dropdown Lists'!$C$19:$BY$19
Name t_8814DB9E78153D73A2DE4EFFFCEF1256: 'Dropdown Lists'!$C$20:$BU$20
Name t_D166DE0F832B3D4689BF54F4F9DD5454: 'Dropdown Lists'!$C$21:$BY$21
Name t_A20C14220EF237158FD9CCA8C686F5B6: 'Dropdown Lists'!$C$22:$BY$22
Name t_F98DCB3AE762307DA38D7F30833DF73F: 'Dropdown Lists'!$C$23:$H$23
Name t_C01086A5CDC33871996916645423B4C8: 'Dropdown Lists'!$C$24:$H$24
Name t_1DEB50D24B7633DEB568D46CD0DEE18A: 'Dropdown Lists'!$C$25:$H$25
Name t_10B93B27AE6432F7A309E668D2CC9EDD: 'Dropdown Lists'!$C$26:$H$26
Name t_7BF920BAC1E832CBA736C384387E7A64: 'Dropdown Lists'!$C$27:$D$27
Name t_1A4E538CD7F63317BF625E62EEEBBC3D: 'Dropdown Lists'!$C$28:$D$28
Name t_D8E40E3C11163CDE8776515BCDB9008B: 'Dropdown Lists'!$C$29:$D$29
Name t_E18D138B932938D2B244867CB5CA5F8D: 'Dropdown Lists'!$C$30:$D$30
Name t_2641CB45323E330DA4A86DBF28925232: 'Dropdown Lists'!$C$31:$D$31
Name t_5902DC47A34934A6B275A7ABB0F18706: 'Dropdown Lists'!$C$32:$D$32
Name t_A8996EFB19463551AD2FD78E6CFFFA06: 'Dropdown Lists'!$C$33:$D$33
Name t_E412CE876AE93AD5AC0D5C1480E444C3: 'Dropdown Lists'!$C$34:$D$34
Name t_8ED06C1BC7523579B7FCB86101DC9F37: 'Dropdown Lists'!$C$35:$D$35
Name t_261CDA0339713BDD94255721F6AC1E98: 'Dropdown Lists'!$C$36:$D$36
Name t_5A6FEE3097733D8EBA56B406A1BFEBF3: 'Dropdown Lists'!$C$37:$D$37
Name t_8CB41F7CB92D3DE09250B594F82216BC: 'Dropdown Lists'!$C$38:$D$38
Name t_AF77F406BC7B38739E6D8F1879B1781C: 'Dropdown Lists'!$C$39:$D$39
Name t_EB77710FD03D3CB2B57FFC7E3A2B0A38: 'Dropdown Lists'!$C$40:$D$40
Name t_BFF2A9A99B043547BCF1A7250E072E9C: 'Dropdown Lists'!$C$41:$D$41
Name t_76884B4ABFE53376A65A72677CABCE3D: 'Dropdown Lists'!$C$42:$D$42
Name t_BBF50BEADA7C326398209A43F6AD8F09: 'Dropdown Lists'!$C$43:$D$43
Name t_B49ECF871E0F3408BE31D0994F96041B: 'Dropdown Lists'!$C$44:$D$44
Name t_93A7B5EFF15F3A8F92108126979F2A18: 'Dropdown Lists'!$C$45:$D$45
Name t_2513B871335C3DAB8A733A8C3D70AE77: 'Dropdown Lists'!$C$46:$D$46
Name t_F672583C87EE37CFB0B56C16306BA3CB: 'Dropdown Lists'!$C$47:$D$47
Name t_C8FE43FD1F7F35CAB2C15938EDAD956E: 'Dropdown Lists'!$C$48:$D$48
Name t_A0E4AD6831313900AD961B58EF1C1A77: 'Dropdown Lists'!$C$49:$D$49
Name t_0B2F388CB16F3B18B7491E916140F8B3: 'Dropdown Lists'!$C$50:$D$50
Name t_6433030A9FF83D298602F400E71A99A4: 'Dropdown Lists'!$C$51:$D$51
Name t_438EBE297B01396A97D96656A124EC12: 'Dropdown Lists'!$C$52:$D$52
Name t_76FB370A4ADA3369938705E3B396C3DB: 'Dropdown Lists'!$C$53:$D$53
Name t_F3F0BCE81CAE3DA08E421109EEFE4D3E: 'Dropdown Lists'!$C$54:$D$54
Name t_0B6A9C9F1908395D95B606E715119DED: 'Dropdown Lists'!$C$55:$BS$55
Name t_0815AE15C0663BAE95DDDC17B942AA0E: 'Dropdown Lists'!$C$56:$BS$56
Name t_2176EB6E9ECC38E99443FCEA3B6EAFFB: 'Dropdown Lists'!$C$57:$BS$57
Name t_56720A2F7E653636BA1E4305A9628763: 'Dropdown Lists'!$C$58:$BS$58
Name t_D097CE9D29693045AE3A663CF490EEC0: 'Dropdown Lists'!$C$59:$BS$59
Name t_77B205B7C3DD3B1BBEF38D3B352A8D84: 'Dropdown Lists'!$C$60:$BS$60

Sheet Anleitung
A1: Anwendungsleitfaden für Vorlagen
A2: Diese Seite drucken
A3: Auf dieser Seite finden Sie die notwendigen Informationen, um Ihre Tabellenvorlage zu erstellen, zu überprüfen und an Temu zu übermitteln. Wir empfehlen Ihnen, diese Seite auszudrucken, damit Sie die Informationen während des gesamten Prozesses leicht nachschlagen können.
A4: Speichern Sie eine Version dieser Datei im Excel-Format auf Ihrer Festplatte. Geben Sie anschließend Ihre Produktinformationen gemäß den folgenden Anweisungen in die Registerkarte „Vorlage“ ein.
A6: Registerkarte „Bilder“
A7: Auf der Registerkarte „Bilder“ können Sie sich mit den Leitlinien von Temu für visuelle Inhalte vertraut machen. Stellen Sie sicher, dass die Bilder, die Sie zu Temu beisteuern, diesen festgelegten Standards entsprechen, um Einheitlichkeit und eine hohe Qualität zu gewährleisten.
A8: Für jedes Produkt muss unbedingt ein Bild bereitgestellt werden. Laden Sie Bilder hoch, indem Sie die Bild-URL angeben.
A10: Registerkarte „Beispiel“
A11: Auf der Registerkarte „Beispiel“ finden Sie ein Beispiel für die Eingabe von Produktdaten. Dies dient nur zu Ihrer Orientierung. Denken Sie daran: Um zu verhindern, dass falsche Produktinformationen in Ihre Bestandsdatei aufgenommen werden, sollten Sie ihre eigenen Produkte nicht direkt im Beispielblatt bearbeiten.
A13: Template Tab
A14: 1. Empfohlene Software: Aufgrund von Überlegungen zur Dateikompatibilität wird Office Excel empfohlen, um die Vorlagendatei zu nutzen und zu bearbeiten. 2. Integrität der Vorlage: Ändern oder löschen Sie in der Vorlagendatei keine Arbeitsblattnamen, Spaltenüberschriften oder deren Reihenfolge. Wählen Sie für Zellen mit Dropdown-Aufzählungen Werte aus der Dropdown-Liste aus, und geben Sie sie ein. 3. Maßeinheiten: Die Einheiten in der Vorlagendatei beziehen sich auf die Veröffentlichungswebsite a. Der Verkaufsort USA verwendet das angloamerikanische (imperiale) System: Die Längeneinheit ist Zoll, die Gewichtseinheit ist Pfund und die Währungseinheit ist USD 1. Der Längenbereich liegt zwischen 0,1 Zoll und 999,9 Zoll mit maximal 1 Dezimalstelle und wird aufgerundet. 2. Der Gewichtsbereich liegt zwischen 0,1 lb und 9999,9 lb mit maximal 1 Dezimalstelle und wird aufgerundet. 3. Der Preisbereich liegt zwischen 0,01 $ und 99999999,99 $ mit maximal 2 Dezimalstellen und wird aufgerundet. a. Der Verkaufsort Mexiko verwendet das metrische System: Die Längeneinheit ist Zentimeter, die Gewichtseinheit ist Gramm und die Währungseinheit ist MXN Der Längenbereich liegt zwischen 0,1 cm und 9999999,9 cm mit maximal 1 Dezimalstelle und wird aufgerundet. ii. Der Gewichtsbereich liegt zwischen 0,1 g und 9999,9 g mit maximal 1 Dezimalstelle und wird aufgerundet. iii. Der Preisbereich liegt zwischen 0,01 MX$ und 99999999,99 MX$ mit maximal 2 Dezimalstellen und wird aufgerundet. c. Die deutschen, italienischen, französischen und spanischen Verkaufsorte verwenden alle das metrische System: Die Längeneinheit ist Zentimeter, die Gewichtseinheit ist Gramm und die Währungseinheit ist EUR 1. Der Längenbereich liegt zwischen 0,1 cm und 9999999,9 cm mit maximal 1 Dezimalstelle und wird aufgerundet. 2. Der Gewichtsbereich liegt zwischen 0,1 g und 9999,9 g mit maximal 1 Dezimalstelle und wird aufgerundet. 3. Der Preisbereich liegt zwischen 0,01 € und 99999999,99 € mit maximal 2 Dezimalstellen und wird aufgerundet. d. Der Verkaufsort Vereinigtes Königreich verwendet das metrische System: Die Längeneinheit ist Zentimeter, die Gewichtseinheit ist Gramm und die Währungseinheit ist GBP 1. Der Längenbereich liegt zwischen 0,1 cm und 9999999,9 cm mit maximal 1 Dezimalstelle und wird aufgerundet. 2. Der Gewichtsbereich liegt zwischen 0,1 g und 9999,9 g mit maximal 1 Dezimalstelle und wird aufgerundet. 3. Der Preisbereich liegt zwischen 0,01 £ und 99999999,99 £ mit maximal 2 Dezimalstellen und wird aufgerundet. 4. Qualifikationen und Fotos: Excel unterstützt derzeit nicht das Hochladen von Qualifizierungsdokumenten oder Fotos. Wenn für Produkte diese Materialien erforderlich sind, stellen Sie diese nach der Einreichung der Produkte auf der Seite „Produkt-Compliance“ bereit. 5. Pflichtfelder: Die Excel-Datei enthält integrierte Formeln. Nach der Auswahl der Kategorie führt Excel Folgendes aus: a. Kennzeichnet Pflichtfelder mit roten Umrandungen. b. Verwendet graue Felder zur Kennzeichnung von Feldern, die leer bleiben sollen. c. Verwendet weiße Felder zur Kennzeichnung von optionalen Feldern. d. Bitte stellen Sie sicher, dass in jeder Zeile alle erforderlichen Informationen korrekt und vollständig ausgefüllt sind. Stellen Sie sicher, dass alle Pflichtfelder korrekt ausgefüllt sind. e. Optionale Felder müssen zwar nicht ausgefüllt werden, doch wenn Sie so viele Informationen wie möglich angeben, kann dies beim Verkauf von Produkten hilfreich sein. 6. Mengenbegrenzung: In jeder Datei sind bis zu 200 Zeilen Inhalt zulässig, andernfalls können Produkte nicht zur Datei hinzugefügt werden. 7. Doppelte Spalten: Die Excel-Datei ist standardmäßig zugeklappt. Sie können oben in der Excel-Datei auf 1 und 2 klicken. 8. Verwenden Sie die neueste Vorlage, da Temu gültige Werte, Datenvalidierungsregeln, einen erläuternden Text oder Anforderungen in der Vorlage von Zeit zu Zeit aktualisiert.
A17: Tabelle einreichen
... A23: Von Zeit zu Zeit aktualisiert Temu Dinge wie Aktivitätsanforderungen, Datenvalidierungsregeln und erläuternden Text. Bitte verwende die zuletzt generierte Vorlage, wenn eine neue Vorlage angezeigt wird.

Sheet Bilder
A1: Bildstandards
A2: Für jedes Produkt auf Temu muss mindestens ein Produktbild bereitgestellt werden. Wählen Sie klare, unkomplizierte und leicht verständliche Bilder. Sie müssen das Produkt genau darstellen, informativ sein und ansprechend präsentiert werden. Zeigen Sie nur das Produkt, das zum Verkauf angeboten wird. Stellen Sie nach Möglichkeit mehrere Bilder zur Verfügung, die jeweils verschiedene Blickwinkel und Details des Produkts zeigen. Dies ist Ihre Gelegenheit, Ihrem Kunden Ihr Produkt zu präsentieren, also ist Qualität wichtig.
A3: Wir behalten uns das Recht vor, Bilder abzulehnen, die nicht unseren Bildstandards entsprechen.
A4: Es liegt in Ihrer Verantwortung, sicherzustellen, dass Sie alle erforderlichen Rechte an den von Ihnen eingereichten Bildern besitzen.
A6: SKU-Bilder
A7: Die SKU-Bilder werden oben auf der Produktseite angezeigt. Verschiedene SKU-Bilder bilden ein Karussell des Produkts.
A8: Bei Bekleidungsprodukten sollten die hochgeladenen Bilder eine maximale Größe von 3 MB, ein Seitenverhältnis von 3:4, eine Breite von ≥ 1340 px und eine Höhe von ≥ 1785 px haben. Die SKUs mit derselben Farbe teilen sich einen Satz von Karussellbildern.
A9: Bei anderen Produkten als Bekleidungsprodukten sollten die hochgeladenen Bilder eine maximale Größe von 3 MB, ein Seitenverhältnis von 1:1 und eine Breite und Höhe von ≥ 800 px aufweisen.
A10: Du kannst bis zu zehn Bilder hochladen, wobei jede Zelle eine Bild-URL enthält.
A12: Produktvideo
A13: Das Produktvideo wird oben auf der Produktseite angezeigt.
A14: Das hochgeladene Video sollte eine maximale Größe von 100 MB, eine Länge von maximal 180 Sekunden und eine Mindestauflösung von 720 p haben.
... A23: Laden Sie das Video mit einer maximalen Größe von 300 MB, einer Länge von maximal 180 Sekunden, einem Seitenverhältnis von 1:1, 4:3 oder 16:9 und einer Mindestauflösung von 720p hoch.

Sheet Beispiel
A1: 1. Bitte schauen Sie sich nicht nur den Inhalt der Registerkarte „Beispiel“ an, sondern auch die Registerkarte „Anleitungen“ in diesem Dokument.
A2: 2. Beachten Sie, dass die angeführten Beispiele lediglich der Veranschaulichung dienen. Die in Ihrer angepassten Vorlage angezeigten Spalten variieren je nach der ausgewählten Kategorie. Verwenden Sie die Registerkarte „Vorlage“, um die Tabellenvorlage zu erstellen.
A3: 3. Einige der optionalen Spalten sind eingeklappt, um eine bessere Darstellung zu ermöglichen. Lassen Sie diese ausgeblendeten Bereiche anzeigen, indem Sie in der entsprechenden Spalte oder im entsprechenden Abschnitt auf die Schaltfläche „+“ klicken
A4: 4. Fehler beim Senden eines Produkteintrags können durch Anzeigen der Verarbeitungsergebnisse oder durch Kontaktaufnahme mit dem Verkäufersupport behoben werden.
A5: Einige Felder sind Pflichtfelder. Andere sind optional. | B5: Product Identity | H5: Product Description | BN5: Product Detail | GT5: Sale Property (At Least One, At Most Two) | HL5: Size Chart | IE5: Variations | IY5: Offer | JC5: Qualifications
B6: Category | C6: Product Name | D6: Contribution Goods | E6: Contribution SKU | F6: Brand | G6: Trademark | H6: Product Description | I6: Bullet Point | J6: Bullet Point | K6: Bullet Point | L6: Bullet Point | M6: Bullet Point | N6: Bullet Point | O6: Detail Images URL | P6: Detail Images URL | Q6: Detail Images URL | R6: Detail Images URL | S6: Detail Images URL | T6: Detail Images URL | U6: Detail Images URL | V6: Detail Images URL | W6: Detail Images URL | X6: Detail Images URL | Y6: Detail Images URL | Z6: Detail Images URL | AA6: Detail Images URL | AB6: Detail Images URL | AC6: Detail Images URL | AD6: Detail Images URL | AE6: Detail Images URL | AF6: Detail Images URL | AG6: Detail Images URL | AH6: Detail Images URL | AI6: Detail Images URL | AJ6: Detail Images URL | AK6: Detail Images URL | AL6: Detail Images URL | AM6: Detail Images URL | AN6: Detail Images URL | AO6: Detail Images URL | AP6: Detail Images URL | AQ6: Detail Images URL | AR6: Detail Images URL | AS6: Detail Images URL | AT6: Detail Images URL | AU6: Detail Images URL | AV6: Detail Images URL | AW6: Detail Images URL | AX6: Detail Images URL | AY6: Detail Images URL | AZ6: Detail Images URL | BA6: Detail Images URL | BB6: Detail Images URL | BC6: Detail Images URL | BD6: Detail Images URL | BE6: Detail Images URL | BF6: Detail Images URL | BG6: Detail Images URL | BH6: Detail Images URL | BI6: Detail Images URL | BJ6: Detail Images URL | BK6: Detail Images URL | BL6: Detail Images URL | BM6: Detail Video URL | BN6: 4115 - Shelf Life - value | BO6: 4115 - Shelf Life - unit | BP6: 4118 - Speciality | BQ6: 4118 - Speciality | BR6: 4118 - Speciality | BS6: 4119 - Item Weight - value | BT6: 4119 - Item Weight - unit | BU6: 4120 - Package Weight - value | BV6: 4120 - Package Weight - unit | BW6: 4121 - Allergen Information | BX6: 4121 - Allergen Information | BY6: 4121 - Allergen Information | BZ6: 4121 - Allergen Information | CA6: 4121 - Allergen Information | CB6: 4121 - Allergen Information | CC6: 4121 - Allergen Information | CD6: 4121 - Allergen Information | CE6: 4121 - Allergen Information | CF6: 4121 - Allergen Information | CG6: 195 - Diet Type | CH6: 195 - Diet Type | CI6: 195 - Diet Type | CJ6: 6160 - Brand Name | CK6: 6210 - USDA certified | CL6: 4110 - Production Date | CM6: 6440 - best before | CN6: 361 - Package Quantity | CO6: 12 - Material | CP6: 12 - Material | CQ6: 12 - Material | CR6: 12 - Material | CS6: 12 - Material | CT6: 4134 - Publisher | CU6: 4130 - Country/Region Of Origin | CV6: 4137 - Author | CW6: 1120 - Set or not | CX6: 4133 - Binding Type | CY6: 4123 - Languages | CZ6: 4123 - Languages | DA6: 4123 - Languages | DB6: 4142 - Year Of Publication | DC6: 4124 - Number Of Pages (pages) - value | DD6: 4124 - Number Of Pages (pages) - unit | DE6: 4131 - Number Of Words (10,000 Words) | DF6: 4127 - Product Weight (g) - value | DG6: 4127 - Product Weight (g) - unit | DH6: 4128 - Maximum Reading Age (years) - value | DI6: 4128 - Maximum Reading Age (years) - unit | DJ6: 4129 - Minimum Reading Age (years) - value | DK6: 4129 - Minimum Reading Age (years) - unit | DL6: 121 - Material | DM6: 121 - Material | DN6: 121 - Material | DO6: 121 - Material | DP6: 121 - Material | DQ6: 132 - Finish Type | DR6: 210 - Furniture Finish | DS6: 19 - Style | DT6: 1561 - Power Supply | DU6: 1132 - Operating Voltage | DV6: 1485 - Plug Type | DW6: 1485 - Plug Type | DX6: 1485 - Plug Type | DY6: 1571 - Acceptable Voltage Range | DZ6: 4102 - Contain Wooden Materials | EA6: 4097 - Tree Species | EB6: 4097 - Tree Species | EC6: 4098 - Wood Formation Type | ED6: 4098 - Wood Formation Type | EE6: 4098 - Wood Formation Type | EF6: 4099 - Fiberboard Density | EG6: 6171 - Wether Independent | EH6: 6172 - Closed Storage Capacity | EI6: 6173 - Height After Assembly | EJ6: 6174 - Physical Weight | EK6: 2153 - Battery Properties | EL6: 2147 - Rechargeable Battery | EM6: 2154 - Solar Battery Type | EN6: 3740 - Non-rechargeable Battery | EO6: 2028 - Battery Capacity (mAh) - value | EP6: 2028 - Battery Capacity (mAh) - unit | EQ6: 63 - Color | ER6: 15 - Composition:Nylon | ES6: 15 - Composition:Polyester | ET6: 15 - Composition:Polyamide | EU6: 15 - Composition:Elastane | EV6: 15 - Composition:Spandex | EW6: 15 - Composition:Acrylic | EX6: 15 - Composition:Cotton | EY6: 15 - Composition:Silk | EZ6: 15 - Composition:Linen | FA6: 15 - Composition:Modal | FB6: 15 - Composition:Viscose | FC6: 15 - Composition:Rayon | FD6: 15 - Composition:Carbon | FE6: 15 - Composition:Metal | FF6: 15 - Composition:Wool | FG6: 15 - Composition:Cashmere | FH6: 15 - Composition:Mohair | FI6: 15 - Composition:Rabbit Hair | FJ6: 15 - Composition:Bovine Leather | FK6: 15 - Composition:Sheep Leather | FL6: 15 - Composition:Pig Leather | FM6: 15 - Composition:Polyurethane | FN6: 15 - Composition:Polyvinyl Chloride | FO6: 15 - Composition:Cupro | FP6: 15 - Composition:Lyocell | FQ6: 15 - Composition:Acetate | FR6: 15 - Composition:Down | FS6: 15 - Composition:Feather | FT6: 15 - Composition:Duck Down | FU6: 15 - Composition:Alpaca | FV6: 15 - Composition:Metallized Fibres | FW6: 15 - Composition:Polypropylene fibers | FX6: 15 - Composition:Other Fibers | FY6: 28 - Length | FZ6: 74 - Belt | GA6: 29 - Sleeve Length | GB6: 27 - Sleeve Type | GC6: 94 - Chest Pad | GD6: 83 - Details | GE6: 26 - Pattern | GF6: 24 - Sheer | GG6: 22 - Fabric | GH6: 86 - Placket Type | GI6: 78 - Lining | GJ6: 113 - Contour | GK6: 76 - Season | GL6: 20 - Operation Instruction | GM6: 114 - Fit Type | GN6: 1352 - Fabric Elasticity | GO6: 1919 - Printing Type | GP6: 2103 - Style source | GQ6: 1192 - Weaving Method | GR6: 21 - Collar Style | GS6: 6227 - Collection | GT6: Variation Theme | GU6: Size Family | GV6: Sub-Size Family | GW6: Size | GX6: Color | GY6: Color | GZ6: Size | HA6: Style | HB6: Material | HC6: Flavors | HD6: Applicable People | HE6: Capacity | HF6: Composition | HG6: Weight | HH6: Items | HI6: Quantity | HJ6: Model | HK6: Hair Length | HL6: Unit | HM6: US Size | HN6: Tops - Product - Shoulder width | HO6: Tops - Product - Bust size | HP6: Tops - Product - Clothes length | HQ6: Tops - Product - Sleeve length | HR6: Tops - Product - Waist size | HS6: Tops - Product - Underbust | HT6: Tops - Product - Neck | HU6: Tops - Product - Hem | HV6: Tops - Product - Cuffs | HW6: Tops - Body - Bust - min | HX6: Tops - Body - Bust - max | HY6: Tops - Body - Waist - min | HZ6: Tops - Body - Waist - max | IA6: Tops - Body - Hips - min | IB6: Tops - Body - Hips - max | IC6: Tops - Body - Height - min | ID6: Tops - Body - Height - max | IE6: SKU Images URL | IF6: SKU Images URL | IG6: SKU Images URL | IH6: SKU Images URL | II6: SKU Images URL | IJ6: SKU Images URL | IK6: SKU Images URL | IL6: SKU Images URL | IM6: SKU Images URL | IN6: SKU Images URL | IO6: Quantity | IP6: Base Price - EUP | IQ6: List Price - EUP | IR6: Not available for List price | IS6: Weight - g | IT6: Length - cm | IU6: Width - cm | IV6: Height - cm | IW6: External Product ID Type | IX6: External Product ID | IY6: Handling Time | IZ6: Shipping Template | JA6: Import Designation | JB6: Item Tax Code | JC6: Product Guide
A7: Beispiel 1: Dies ist ein Beispiel für die Bereitstellung eines neuen Angebots. Dieses Beispiel hat keine Variation und wird als einzelne Detailseite aufgeführt. | B7: 29069 | C7: Example Women T-shirt, 156 Black T-shirt | D7: EXAMPLE-156-US-Black-one-size | E7: EXAMPLE-156-US-Black-one-size | H7: Unleash your personal style with our classic fit tee. Crafted from 100% cotton, it offers unmatched comfort and durability. The tee features a unique, eye-catching graphic that embodies modern chic. Perfect for casual outings or layering under a jacket, this T-shirt is versatile for any occasion. With a breathable fabric that holds its shape, it's a wardrobe staple you'll reach for time and again. Make a statement and stay cozy in a shirt designed to express who you are. (Character count: 493) | I7: 100% premium cotton for ultimate comfort. | J7: Timeless design meets modern style. | K7: Durable fabric, perfect for daily wear | L7: Machine washable and easy to care for. | M7: Versatile fit for every body type. | O7: http://www.companyname.com/images/1250.main.jpg | P7: http://www.companyname.com/images/1250.main.jpg | Q7: http://www.companyname.com/images/1250.main.jpg | R7: http://www.companyname.com/images/1250.main.jpg | CO7: Recycle Polyester | DS7: Y2K | ER7: 32 | ES7: 28 | ET7: 40 | FY7: Short Length | FZ7: Yes | GA7: Long Sleeve | GB7: Raglan sleeve | GC7: No Padding | GD7: Fake Pockets | GE7: Mushroom | GF7: No | GG7: Non-Stretch | GH7: Half Placket | GI7: Cashmere | GJ7: H | GK7: Fall | GL7: Do not wash | GM7: Regular | GN7: No Elasticity | GO7: Positioning Printing | GP7: Buyer provides | GQ7: Woven | GR7: Off the Shoulder | GS7: Middle East | GT7: Size × Color | GU7: US/EU size | GV7: One Size | GW7: one-size | GX7: Black | HL7: cm | HM7: one-size | HO7: 36 | HP7: 28 | HW7: 33.9 | HX7: 35.5 | HY7: 26 | HZ7: 27.6 | IA7: 35.9 | IB7: 37.4 | IE7: http://www.companyname.com/images/1250.main.jpg | IF7: http://www.companyname.com/images/1250.main.jpg | IG7: http://www.companyname.com/images/1250.main.jpg | IO7: 5 | IP7: 2.99 | IQ7: 5.99 | IS7: 9.2 | IT7: 2 | IU7: 3 | IV7: 4 | IY7: 1 Day | IZ7: test1 | JA7: Imported | JB7: GEN STANDARD
B8: 12408 | C8: Example reclaimed Cabinet Solid Wood with 4 Drawers | D8: EXAMPLE-576-Brown | E8: EXAMPLE-576-Brown | DL8: Wood | DQ8: Painted | DR8: Cedar | DS8: Vintage | DT8: Plug Powered | DU8: 110V (included)-240V (included) | DV8: US Plug | DZ8: Yes | EA8: Hardwood | EC8: Block Board (large Core Board) | EG8: Yes | EH8: <3.2 Cubic Feet | EI8: <27 Inches | EJ8: <30 Lbs | EK8: Without Battery | EQ8: Red | GT8: Color × Style | GY8: Red | HA8: Vintage | IE8: http://www.companyname.com/images/1250.main.jpg | IF8: http://www.companyname.com/images/1250.main.jpg | IG8: http://www.companyname.com/images/1250.main.jpg | IO8: 0 | IP8: 2.99 | IQ8: 5.99 | IS8: 9.2 | IT8: 2 | IU8: 3 | IV8: 4 | IY8: 1 Day | IZ8: test1 | JA8: Imported | JB8: GEN STANDARD | JC8: http://www.companyname.com/images/productguide.pdf
B9: 44936 | C9: Example book for US with isbn | D9: EXAMPLEISBN9787040205190 | E9: EXAMPLEISBN9787040205190 | CT9: Example publisher | CU9: USA | CV9: Example author | CW9: No | CX9: Paperback | CY9: English | DB9: 44604 | DC9: 300 | DD9: Page | DE9: 1000 | DF9: 200 | DG9: g | DH9: 99 | DI9: years old | DJ9: 1 | DK9: years old | GT9: Items | HH9: Example book for US with isbn | IE9: http://www.companyname.com/images/1250.main.jpg | IF9: http://www.companyname.com/images/1250.main.jpg | IG9: http://www.companyname.com/images/1250.main.jpg | IO9: 20 | IP9: 7.82 | IQ9: 10.23 | IS9: 9.2 | IT9: 2 | IU9: 3 | IV9: 4 | IW9: ISBN | IX9: 920000021 | IY9: 1 Day | IZ9: test1 | JA9: Imported | JB9: BOOKS GEN
B10: 42550 | C10: Example food Potato Chips Pack of 6 - 80g per bag | D10: EXAMPLE-Pack6 - 80g | E10: EXAMPLE-Pack6 - 80g | BN10: 30 | BO10: Day | BP10: Wild-Caught | BQ10: Certified-Humane-Raised-And-Handled | BS10: 90 | BT10: g | BU10: 106 | BV10: g | BW10: Contains cow's milk | BX10: Contains Peanuts | CG10: Plant Based | CJ10: Example brand name | CK10: less than 70% organic ingredients | CL10: 45550 | CM10: 45641 | GT10: Weight | HG10: 90g | IE10: http://www.companyname.com/images/1250.main.jpg | IF10: http://www.companyname.com/images/1250.main.jpg | IG10: http://www.companyname.com/images/1250.main.jpg | IO10: 20 | IP10: 5.39 | IR10: N/A | IS10: 9.2 | IT10: 2 | IU10: 3 | IV10: 4 | IY10: 1 Day | IZ10: test1 | JA10: Imported | JB10: FOOD GEN
A12: Beispiel 2: Dies ist ein Beispiel für ein Produkt mit 1 Variationsdesign (Größe) mit 3 Variationen. Dabei handelt es sich um 3 „untergeordnete“ SKUs in einer „übergeordneten“ Ware. Hinweis: Stelln Sie bei Informationen auf Produktebene, wie z. B. Produktname, Produktbeschreibung, Produktdetails, Angebot, Qualifikationen, sicher, dass jede Zeile korrekt ausgefüllt ist und die Informationen einheitlich eingegeben werden. | B12: 29069 | C12: Example Women T-shirt, 156 Black T-shirt | D12: EXAMPLE-156-US-Black | E12: EXAMPLE-156-US-Black-S | H12: Unleash your personal style with our classic fit tee. Crafted from 100% cotton, it offers unmatched comfort and durability. The tee features a unique, eye-catching graphic that embodies modern chic. Perfect for casual outings or layering under a jacket, this T-shirt is versatile for any occasion. With a breathable fabric that holds its shape, it's a wardrobe staple you'll reach for time and again. Make a statement and stay cozy in a shirt designed to express who you are. (Character count: 493) | I12: 100% premium cotton for ultimate comfort. | J12: Timeless design meets modern style. | K12: Durable fabric, perfect for daily wear | L12: Machine washable and easy to care for. | M12: Versatile fit for every body type. | O12: http://www.companyname.com/images/1250.main.jpg | P12: http://www.companyname.com/images/1250.main.jpg | Q12: http://www.companyname.com/images/1250.main.jpg | R12: http://www.companyname.com/images/1250.main.jpg | CO12: Recycle Polyester | DS12: Y2K | ER12: 32 | ES12: 28 | ET12: 40 | FY12: Short Length | FZ12: Yes | GA12: Long Sleeve | GB12: Raglan sleeve | GC12: No Padding | GD12: Fake Pockets | GE12: Mushroom | GF12: No | GG12: Non-Stretch | GH12: Half Placket | GI12: Cashmere | GJ12: H | GK12: Fall | GL12: Do not wash | GM12: Regular | GN12: No Elasticity | GO12: Positioning Printing | GP12: Buyer provides | GQ12: Woven | GR12: Off the Shoulder | GS12: Middle East | GT12: Size × Color | GU12: US/EU size | GV12: Alpha | GW12: S | GX12: Black | HL12: cm | HM12: 0 | HO12: 36 | HP12: 28 | HW12: 33.9 | HX12: 35.5 | HY12: 26 | HZ12: 27.6 | IA12: 35.9 | IB12: 37.4 | IE12: http://www.companyname.com/images/1250.main.jpg | IF12: http://www.companyname.com/images/1250.main.jpg | IG12: http://www.companyname.com/images/1250.main.jpg | IO12: 5 | IP12: 2.99 | IQ12: 5.99 | IS12: 9.2 | IT12: 2 | IU12: 3 | IV12: 4 | IY12: 1 Day | IZ12: test1 | JA12: Imported | JB12: GEN STANDARD
B13: 29069 | C13: Example Women T-shirt, 156 Black T-shirt | D13: EXAMPLE-156-US-Black | E13: EXAMPLE-156-US-Black-M | H13: Unleash your personal style with our classic fit tee. Crafted from 100% cotton, it offers unmatched comfort and durability. The tee features a unique, eye-catching graphic that embodies modern chic. Perfect for casual outings or layering under a jacket, this T-shirt is versatile for any occasion. With a breathable fabric that holds its shape, it's a wardrobe staple you'll reach for time and again. Make a statement and stay cozy in a shirt designed to express who you are. (Character count: 493) | I13: 100% premium cotton for ultimate comfort. | J13: Timeless design meets modern style. | K13: Durable fabric, perfect for daily wear | L13: Machine washable and easy to care for. | M13: Versatile fit for every body type. | O13: http://www.companyname.com/images/1250.main.jpg | P13: http://www.companyname.com/images/1250.main.jpg | Q13: http://www.companyname.com/images/1250.main.jpg | R13: http://www.companyname.com/images/1250.main.jpg | CO13: Recycle Polyester | DS13: Y2K | ER13: 32 | ES13: 28 | ET13: 40 | FY13: Short Length | FZ13: Yes | GA13: Long Sleeve | GB13: Raglan sleeve | GC13: No Padding | GD13: Fake Pockets | GE13: Mushroom | GF13: No | GG13: Non-Stretch | GH13: Half Placket | GI13: Cashmere | GJ13: H | GK13: Fall | GL13: Do not wash | GM13: Regular | GN13: No Elasticity | GO13: Positioning Printing | GP13: Buyer provides | GQ13: Woven | GR13: Off the Shoulder | GS13: Middle East | GT13: Size × Color | GU13: US/EU size | GV13: Alpha | GW13: M | GX13: Black | HL13: cm | HM13: 2 | HO13: 40 | HP13: 29 | HW13: 35.5 | HX13: 37 | HY13: 27.6 | HZ13: 29.2 | IA13: 27.4 | IB13: 39 | IE13: http://www.companyname.com/images/1250.main.jpg | IF13: http://www.companyname.com/images/1250.main.jpg | IG13: http://www.companyname.com/images/1250.main.jpg | IO13: 5 | IP13: 2.99 | IQ13: 5.99 | IS13: 9.2 | IT13: 2 | IU13: 3 | IV13: 4 | IY13: 1 Day | IZ13: test1 | JA13: Imported | JB13: GEN STANDARD
B14: 29069 | C14: Example Women T-shirt, 156 Black T-shirt | D14: EXAMPLE-156-US-Black | E14: EXAMPLE-156-US-Black-L | H14: Unleash your personal style with our classic fit tee. Crafted from 100% cotton, it offers unmatched comfort and durability. The tee features a unique, eye-catching graphic that embodies modern chic. Perfect for casual outings or layering under a jacket, this T-shirt is versatile for any occasion. With a breathable fabric that holds its shape, it's a wardrobe staple you'll reach for time and again. Make a statement and stay cozy in a shirt designed to express who you are. (Character count: 493) | I14: 100% premium cotton for ultimate comfort. | J14: Timeless design meets modern style. | K14: Durable fabric, perfect for daily wear | L14: Machine washable and easy to care for. | M14: Versatile fit for every body type. | O14: http://www.companyname.com/images/1250.main.jpg | P14: http://www.companyname.com/images/1250.main.jpg | Q14: http://www.companyname.com/images/1250.main.jpg | R14: http://www.companyname.com/images/1250.main.jpg | CO14: Recycle Polyester | DS14: Y2K | ER14: 32 | ES14: 28 | ET14: 40 | FY14: Short Length | FZ14: Yes | GA14: Long Sleeve | GB14: Raglan sleeve | GC14: No Padding | GD14: Fake Pockets | GE14: Mushroom | GF14: No | GG14: Non-Stretch | GH14: Half Placket | GI14: Cashmere | GJ14: H | GK14: Fall | GL14: Do not wash | GM14: Regular | GN14: No Elasticity | GO14: Positioning Printing | GP14: Buyer provides | GQ14: Woven | GR14: Off the Shoulder | GS14: Middle East | GT14: Size × Color | GU14: US/EU size | GV14: Alpha | GW14: L | GX14: Black | HL14: cm | HM14: 4 | HO14: 44 | HP14: 30 | HW14: 37.4 | HX14: 39.8 | HY14: 29.6 | HZ14: 31.9 | IA14: 39.4 | IB14: 41.8 | IE14: http://www.companyname.com/images/1250.main.jpg | IF14: http://www.companyname.com/images/1250.main.jpg | IG14: http://www.companyname.com/images/1250.main.jpg | IO14: 5 | IP14: 2.99 | IQ14: 5.99 | IS14: 9.2 | IT14: 2 | IU14: 3 | IV14: 4 | IY14: 1 Day | IZ14: test1 | JA14: Imported | JB14: GEN STANDARD
B15: 12408 | C15: Example reclaimed Cabinet Solid Wood with 4 Drawers | D15: EXAMPLE-576 | E15: EXAMPLE-576-Brown | DL15: Wood | DQ15: Painted | DR15: Cedar | DS15: Vintage | DT15: Plug Powered | DU15: 110V (included)-240V (included) | DV15: US Plug | DZ15: Yes | EA15: Hardwood | EC15: Block Board (large Core Board) | EG15: Yes | EH15: <3.2 Cubic Feet | EI15: <27 Inches | EJ15: <30 Lbs | EK15: Without Battery | EQ15: Red | GT15: Color | GY15: Brown | IE15: http://www.companyname.com/images/1250.main.jpg | IF15: http://www.companyname.com/images/1250.main.jpg | IG15: http://www.companyname.com/images/1250.main.jpg | IO15: 5 | IP15: 2.99 | IQ15: 5.99 | IS15: 9.2 | IT15: 2 | IU15: 3 | IV15: 4 | IY15: 1 Day | IZ15: test1 | JA15: Imported | JB15: GEN STANDARD
B16: 12408 | C16: Example reclaimed Cabinet Solid Wood with 4 Drawers | D16: EXAMPLE-576 | E16: EXAMPLE-576-white | DL16: Wood | DQ16: Painted | DR16: Cedar | DS16: Vintage | DT16: Plug Powered | DU16: 110V (included)-240V (included) | DV16: US Plug | DZ16: Yes | EA16: Hardwood | EC16: Block Board (large Core Board) | EG16: Yes | EH16: <3.2 Cubic Feet | EI16: <27 Inches | EJ16: <30 Lbs | EK16: Without Battery | EQ16: Red | GT16: Color | GY16: white | IE16: http://www.companyname.com/images/1250.main.jpg | IF16: http://www.companyname.com/images/1250.main.jpg | IG16: http://www.companyname.com/images/1250.main.jpg | IO16: 5 | IP16: 2.99 | IQ16: 5.99 | IS16: 9.2 | IT16: 2 | IU16: 3 | IV16: 4 | IY16: 1 Day | IZ16: test1 | JA16: Imported | JB16: GEN STANDARD
B17: 12408 | C17: Example reclaimed Cabinet Solid Wood with 4 Drawers | D17: EXAMPLE-576 | E17: EXAMPLE-576-red | DL17: Wood | DQ17: Painted | DR17: Cedar | DS17: Vintage | DT17: Plug Powered | DU17: 110V (included)-240V (included) | DV17: US Plug | DZ17: Yes | EA17: Hardwood | EC17: Block Board (large Core Board) | EG17: Yes | EH17: <3.2 Cubic Feet | EI17: <27 Inches | EJ17: <30 Lbs | EK17: Without Battery | EQ17: Red | GT17: Color | GY17: red | IE17: http://www.companyname.com/images/1250.main.jpg | IF17: http://www.companyname.com/images/1250.main.jpg | IG17: http://www.companyname.com/images/1250.main.jpg | IO17: 5 | IP17: 2.99 | IQ17: 5.99 | IS17: 9.2 | IT17: 2 | IU17: 3 | IV17: 4 | IY17: 1 Day | IZ17: test1 | JA17: Imported | JB17: GEN STANDARD
A19: Beispiel 3: Dies ist ein Beispiel für ein Produkt mit 2 Variationsdesigns (Größe und Farbe) mit 4 Variationen. Dabei handelt es sich um 4 „untergeordnete“ SKUs in einer „übergeordneten“ Ware. Hinweis: Stellen Sie bei Informationen auf Produktebene, wie z. B. Produktname, Produktbeschreibung, Produktdetails, Angebot, Qualifikationen, sicher, dass jede Zeile korrekt ausgefüllt ist und die Informationen einheitlich eingegeben werden. | B19: 29069 | C19: Example Women T-shirt, 156 Black T-shirt | D19: EXAMPLE-156-US | E19: EXAMPLE-156-US-Black-S | H19: Unleash your personal style with our classic fit tee. Crafted from 100% cotton, it offers unmatched comfort and durability. The tee features a unique, eye-catching graphic that embodies modern chic. Perfect for casual outings or layering under a jacket, this T-shirt is versatile for any occasion. With a breathable fabric that holds its shape, it's a wardrobe staple you'll reach for time and again. Make a statement and stay cozy in a shirt designed to express who you are. (Character count: 493) | I19: 100% premium cotton for ultimate comfort. | J19: Timeless design meets modern style. | K19: Durable fabric, perfect for daily wear | L19: Machine washable and easy to care for. | M19: Versatile fit for every body type. | O19: http://www.companyname.com/images/1250.main.jpg | P19: http://www.companyname.com/images/1250.main.jpg | Q19: http://www.companyname.com/images/1250.main.jpg | R19: http://www.companyname.com/images/1250.main.jpg | CO19: Recycle Polyester | DS19: Y2K | ER19: 32 | ES19: 28 | ET19: 40 | FY19: Short Length | FZ19: Yes | GA19: Long Sleeve | GB19: Raglan sleeve | GC19: No Padding | GD19: Fake Pockets | GE19: Mushroom | GF19: No | GG19: Non-Stretch | GH19: Half Placket | GI19: Cashmere | GJ19: H | GK19: Fall | GL19: Do not wash | GM19: Regular | GN19: No Elasticity | GO19: Positioning Printing | GP19: Buyer provides | GQ19: Woven | GR19: Off the Shoulder | GS19: Middle East | GT19: Size × Color | GU19: US/EU size | GV19: Alpha | GW19: S | GX19: Black | HL19: cm | HM19: 0 | HO19: 36 | HP19: 28 | HW19: 33.9 | HX19: 35.5 | HY19: 26 | HZ19: 27.6 | IA19: 35.9 | IB19: 37.4 | IE19: http://www.companyname.com/images/1250.main.jpg | IF19: http://www.companyname.com/images/1250.main.jpg | IG19: http://www.companyname.com/images/1250.main.jpg | IO19: 5 | IP19: 2.99 | IQ19: 5.99 | IS19: 9.2 | IT19: 2 | IU19: 3 | IV19: 4 | IY19: 1 Day | IZ19: test1 | JA19: Imported | JB19: GEN STANDARD
B20: 29069 | C20: Example Women T-shirt, 156 Black T-shirt | D20: EXAMPLE-156-US | E20: EXAMPLE-156-US-Black-M | H20: Unleash your personal style with our classic fit tee. Crafted from 100% cotton, it offers unmatched comfort and durability. The tee features a unique, eye-catching graphic that embodies modern chic. Perfect for casual outings or layering under a jacket, this T-shirt is versatile for any occasion. With a breathable fabric that holds its shape, it's a wardrobe staple you'll reach for time and again. Make a statement and stay cozy in a shirt designed to express who you are. (Character count: 493) | I20: 100% premium cotton for ultimate comfort. | J20: Timeless design meets modern style. | K20: Durable fabric, perfect for daily wear | L20: Machine washable and easy to care for. | M20: Versatile fit for every body type. | O20: http://www.companyname.com/images/1250.main.jpg | P20: http://www.companyname.com/images/1250.main.jpg | Q20: http://www.companyname.com/images/1250.main.jpg | R20: http://www.companyname.com/images/1250.main.jpg | CO20: Recycle Polyester | DS20: Y2K | ER20: 32 | ES20: 28 | ET20: 40 | FY20: Short Length | FZ20: Yes | GA20: Long Sleeve | GB20: Raglan sleeve | GC20: No Padding | GD20: Fake Pockets | GE20: Mushroom | GF20: No | GG20: Non-Stretch | GH20: Half Placket | GI20: Cashmere | GJ20: H | GK20: Fall | GL20: Do not wash | GM20: Regular | GN20: No Elasticity | GO20: Positioning Printing | GP20: Buyer provides | GQ20: Woven | GR20: Off the Shoulder | GS20: Middle East | GT20: Size × Color | GU20: US/EU size | GV20: Alpha | GW20: M | GX20: Black | HL20: cm | HM20: 2 | HO20: 40 | HP20: 29 | HW20: 35.5 | HX20: 37 | HY20: 27.6 | HZ20: 29.2 | IA20: 27.4 | IB20: 39 | IE20: http://www.companyname.com/images/1250.main.jpg | IF20: http://www.companyname.com/images/1250.main.jpg | IG20: http://www.companyname.com/images/1250.main.jpg | IO20: 5 | IP20: 2.99 | IQ20: 5.99 | IS20: 9.2 | IT20: 2 | IU20: 3 | IV20: 4 | IY20: 1 Day | IZ20: test1 | JA20: Imported | JB20: GEN STANDARD
B21: 29069 | C21: Example Women T-shirt, 156 Black T-shirt | D21: EXAMPLE-156-US | E21: EXAMPLE-156-US-red-S | H21: Unleash your personal style with our classic fit tee. Crafted from 100% cotton, it offers unmatched comfort and durability. The tee features a unique, eye-catching graphic that embodies modern chic. Perfect for casual outings or layering under a jacket, this T-shirt is versatile for any occasion. With a breathable fabric that holds its shape, it's a wardrobe staple you'll reach for time and again. Make a statement and stay cozy in a shirt designed to express who you are. (Character count: 493) | I21: 100% premium cotton for ultimate comfort. | J21: Timeless design meets modern style. | K21: Durable fabric, perfect for daily wear | L21: Machine washable and easy to care for. | M21: Versatile fit for every body type. | O21: http://www.companyname.com/images/1250.main.jpg | P21: http://www.companyname.com/images/1250.main.jpg | Q21: http://www.companyname.com/images/1250.main.jpg | R21: http://www.companyname.com/images/1250.main.jpg | CO21: Recycle Polyester | DS21: Y2K | ER21: 32 | ES21: 28 | ET21: 40 | FY21: Short Length | FZ21: Yes | GA21: Long Sleeve | GB21: Raglan sleeve | GC21: No Padding | GD21: Fake Pockets | GE21: Mushroom | GF21: No | GG21: Non-Stretch | GH21: Half Placket | GI21: Cashmere | GJ21: H | GK21: Fall | GL21: Do not wash | GM21: Regular | GN21: No Elasticity | GO21: Positioning Printing | GP21: Buyer provides | GQ21: Woven | GR21: Off the Shoulder | GS21: Middle East | GT21: Size × Color | GU21: US/EU size | GV21: Alpha | GW21: S | GX21: Red | HL21: cm | HM21: 0 | HO21: 36 | HP21: 28 | HW21: 33.9 | HX21: 35.5 | HY21: 26 | HZ21: 27.6 | IA21: 35.9 | IB21: 37.4 | IE21: http://www.companyname.com/images/1250.main.jpg | IF21: http://www.companyname.com/images/1250.main.jpg | IG21: http://www.companyname.com/images/1250.main.jpg | IO21: 5 | IP21: 3.99 | IQ21: 7.99 | IS21: 9.2 | IT21: 2 | IU21: 3 | IV21: 4 | IY21: 1 Day | IZ21: test1 | JA21: Imported | JB21: GEN STANDARD
B22: 29069 | C22: Example Women T-shirt, 156 Black T-shirt | D22: EXAMPLE-156-US | E22: EXAMPLE-156-US-red-M | H22: Unleash your personal style with our classic fit tee. Crafted from 100% cotton, it offers unmatched comfort and durability. The tee features a unique, eye-catching graphic that embodies modern chic. Perfect for casual outings or layering under a jacket, this T-shirt is versatile for any occasion. With a breathable fabric that holds its shape, it's a wardrobe staple you'll reach for time and again. Make a statement and stay cozy in a shirt designed to express who you are. (Character count: 493) | I22: 100% premium cotton for ultimate comfort. | J22: Timeless design meets modern style. | K22: Durable fabric, perfect for daily wear | L22: Machine washable and easy to care for. | M22: Versatile fit for every body type. | O22: http://www.companyname.com/images/1250.main.jpg | P22: http://www.companyname.com/images/1250.main.jpg | Q22: http://www.companyname.com/images/1250.main.jpg | R22: http://www.companyname.com/images/1250.main.jpg | CO22: Recycle Polyester | DS22: Y2K | ER22: 32 | ES22: 28 | ET22: 40 | FY22: Short Length | FZ22: Yes | GA22: Long Sleeve | GB22: Raglan sleeve | GC22: No Padding | GD22: Fake Pockets | GE22: Mushroom | GF22: No | GG22: Non-Stretch | GH22: Half Placket | GI22: Cashmere | GJ22: H | GK22: Fall | GL22: Do not wash | GM22: Regular | GN22: No Elasticity | GO22: Positioning Printing | GP22: Buyer provides | GQ22: Woven | GR22: Off the Shoulder | GS22: Middle East | GT22: Size × Color | GU22: US/EU size | GV22: Alpha | GW22: M | GX22: Red | HL22: cm | HM22: 2 | HO22: 40 | HP22: 29 | HW22: 35.5 | HX22: 37 | HY22: 27.6 | HZ22: 29.2 | IA22: 27.4 | IB22: 39 | IE22: http://www.companyname.com/images/1250.main.jpg | IF22: http://www.companyname.com/images/1250.main.jpg | IG22: http://www.companyname.com/images/1250.main.jpg | IO22: 5 | IP22: 3.99 | IQ22: 7.99 | IS22: 9.2 | IT22: 2 | IU22: 3 | IV22: 4 | IY22: 1 Day | IZ22: test1 | JA22: Imported | JB22: GEN STANDARD
B23: 12408 | C23: Example reclaimed Cabinet Solid Wood with 4 Drawers | D23: EXAMPLE-576 | E23: Example_Brand Night Stand with 4 Drawers (White, 21 inch) | DL23: Wood | DQ23: Painted | DR23: Cedar | DS23: Vintage | DT23: Plug Powered | DU23: 110V (included)-240V (included) | DV23: US Plug | DZ23: Yes | EA23: Hardwood | EC23: Block Board (large Core Board) | EG23: Yes | EH23: <3.2 Cubic Feet | EI23: <27 Inches | EJ23: <30 Lbs | EK23: Without Battery | EQ23: Red | GT23: Color × Size | GY23: White | GZ23: 21 inch | IE23: http://www.companyname.com/images/1250.main.jpg | IF23: http://www.companyname.com/images/1250.main.jpg | IG23: http://www.companyname.com/images/1250.main.jpg | IO23: 5 | IP23: 2.99 | IQ23: 5.99 | IS23: 9.2 | IT23: 2 | IU23: 3 | IV23: 4 | IY23: 1 Day | IZ23: test1 | JA23: Imported | JB23: GEN STANDARD
B24: 12408 | C24: Example reclaimed Cabinet Solid Wood with 4 Drawers | D24: EXAMPLE-576 | E24: Example_Brand Night Stand with 2 Drawers (White, 24 inch) | DL24: Wood | DQ24: Painted | DR24: Cedar | DS24: Vintage | DT24: Plug Powered | DU24: 110V (included)-240V (included) | DV24: US Plug | DZ24: Yes | EA24: Hardwood | EC24: Block Board (large Core Board) | EG24: Yes | EH24: <3.2 Cubic Feet | EI24: <27 Inches | EJ24: <30 Lbs | EK24: Without Battery | EQ24: Red | GT24: Color × Size | GY24: White | GZ24: 24 inch | IE24: http://www.companyname.com/images/1250.main.jpg | IF24: http://www.companyname.com/images/1250.main.jpg | IG24: http://www.companyname.com/images/1250.main.jpg | IO24: 5 | IP24: 2.99 | IQ24: 5.99 | IS24: 9.2 | IT24: 2 | IU24: 3 | IV24: 4 | IY24: 1 Day | IZ24: test1 | JA24: Imported | JB24: GEN STANDARD
B25: 12408 | C25: Example reclaimed Cabinet Solid Wood with 4 Drawers | D25: EXAMPLE-576 | E25: Example_Brand Night Stand with 2 Drawers (Grey, 21 inch) | DL25: Wood | DQ25: Painted | DR25: Cedar | DS25: Vintage | DT25: Plug Powered | DU25: 110V (included)-240V (included) | DV25: US Plug | DZ25: Yes | EA25: Hardwood | EC25: Block Board (large Core Board) | EG25: Yes | EH25: <3.2 Cubic Feet | EI25: <27 Inches | EJ25: <30 Lbs | EK25: Without Battery | EQ25: Red | GT25: Color × Size | GY25: Grey | GZ25: 21 inch | IE25: http://www.companyname.com/images/1250.main.jpg | IF25: http://www.companyname.com/images/1250.main.jpg | IG25: http://www.companyname.com/images/1250.main.jpg | IO25: 5 | IP25: 2.99 | IQ25: 5.99 | IS25: 9.2 | IT25: 2 | IU25: 3 | IV25: 4 | IY25: 1 Day | IZ25: test1 | JA25: Imported | JB25: GEN STANDARD
B26: 12408 | C26: Example reclaimed Cabinet Solid Wood with 4 Drawers | D26: EXAMPLE-576 | E26: Example_Brand Night Stand with 2 Drawers (Grey, 24 inch) | DL26: Wood | DQ26: Painted | DR26: Cedar | DS26: Vintage | DT26: Plug Powered | DU26: 110V (included)-240V (included) | DV26: US Plug | DZ26: Yes | EA26: Hardwood | EC26: Block Board (large Core Board) | EG26: Yes | EH26: <3.2 Cubic Feet | EI26: <27 Inches | EJ26: <30 Lbs | EK26: Without Battery | EQ26: Red | GT26: Color × Size | GY26: Grey | GZ26: 24 inch | IE26: http://www.companyname.com/images/1250.main.jpg | IF26: http://www.companyname.com/images/1250.main.jpg | IG26: http://www.companyname.com/images/1250.main.jpg | IO26: 5 | IP26: 2.99 | IQ26: 5.99 | IS26: 9.2 | IT26: 2 | IU26: 3 | IV26: 4 | IY26: 1 Day | IZ26: test1 | JA26: Imported | JB26: GEN STANDARD

Sheet Datendefinitionen
A1: So füllen Sie Ihre Vorlage aus
A2: Gruppenname | B2: Namensfeld | C2: Lokale Bezeichnung des Etiketts | D2: Definition und Verwendung | E2: Akzeptierte Werte | F2: Beispiel | G2: Erforderlich oder nicht erforderlich
A3: Produktidentität: Dies sind Attribute, die für Käufer wichtig sind und für alle Ihre Artikel ausgefüllt werden müssen. Einige sind erforderlich, um ein Angebot zu erstellen.
B4: t_1_category | C4: Kategorie | D4: Unterstützt nur das Hochladen einer einzelnen Warenkategorie. Kategorie-ID wurde in der Dropdown-Liste voreingestellt. | E4: Geben Sie eine geeignete Kategorie ein. | F4: 13788 | G4: Erforderlich
B5: t_1_productname | C5: Produktname | D5: Gemäß den Richtlinien des Verkäufercenters: Maximal 500 Zeichen, darf keine leeren Zeilen oder mehr als zwei aufeinander folgende Leerzeichen enthalten. | E5: Der Produktname darf nicht länger als 500 Zeichen sein, einschließlich Leerzeichen. Zulässige Zeichen sind Buchstaben, Zahlen und Symbole. Emojis oder andere Sonderzeichen können nicht verwendet werden. Es wird empfohlen, maximal 80 Zeichen zu verwenden, da lange Produktnamen auf Mobilgeräten abgeschnitten werden können. | F5: Robert Graham Herrenhemd „Maya Bay“, Kurzarm, Classic Fit, Cranberry, Größe XL | G5: Erforderlich
B6: t_1_contributiongoods | C6: Verkäufer Goods | D6: Der Code, der Anbietern zur Kennzeichnung und Verwaltung von übergeordneten Produktlinks bereitgestellt wird; wird vom Händler eingegeben. Muss innerhalb des Stores eindeutig sein. Zeilen mit demselben Beitragswarenwert werden vom System als unterschiedliche untergeordnete SKUs desselben übergeordneten Produkts behandelt. Verwenden Sie in SKUs keine voran- oder nachgestellten Leerzeichen. | E6: Dieses Attribut gibt die Produktnummer an, die vom Beitragenden zugewiesen wurde | F6: ABC123 | G6: Erforderlich
B7: t_1_contributionsku | C7: Verkäufer SKU | D7: Der Code, der Anbietern zur Kennzeichnung und Verwaltung von Unterproduktlinks bereitgestellt wird; wird vom Händler eingegeben. Muss innerhalb des Stores eindeutig sein. Verwenden Sie in SKUs keine voran- oder nachgestellten Leerzeichen. | E7: Dieses Attribut gibt die SKU-Nummer an, die vom Beitragenden zugewiesen wurde | F7: ABC123 | G7: Erforderlich
B8: t_1_Update or Add | C8: Aktualisieren oder hinzufügen | D8: Geben Sie die Art des Vorgangs an („Update“: Update; „Partial Update“: partielles Update) an, der mit den angegebenen Daten durchgeführt werden soll. Wenn Sie das Feld leer lassen, lautet die Standardoption „Update“. Verwenden Sie „Update“, wenn Sie vorhandene Produktinformationen bearbeiten oder ein neues Produkt erstellen, und geben Sie „Partial Update“ ein, wenn nur die eingegebenen Produktinformationsfelder aktualisiert werden. | E8: Wählen Sie eine der folgenden Optionen aus: Update, PartialUpdate. | F8: Aktualisieren | G8: Optional
B9: t_1_Goods Id | C9: Warennummer | D9: Geben Sie nur bei der Bearbeitung bestehender Produktinformationen die von Temu generierte Waren-ID ein. | G9: Optional
B10: t_1_Sku Id | C10: SKU-ID | D10: Geben Sie nur bei der Bearbeitung bestehender Produktinformationen die von Temu generierte SKU-ID ein. | G10: Optional
B11: t_1_brand | C11: Marke | D11: Wenn für das Produkt Markeninformationen erforderlich sind, wählen Sie bitte sowohl die Marke als auch das Markenzeichen des Produkts aus. | E11: Wählen Sie den Markennamen des Produkts aus https://seller-eu.temu.com/performance/account-health.html?tab=compliance&opType=register | F11: Nike | G11: Optional
B12: t_1_trademark | C12: Markenzeichen | D12: Wenn für das Produkt Markeninformationen erforderlich sind, wählen Sie bitte sowohl die Marke als auch das Markenzeichen des Produkts aus. Bitte gehen Sie bei der Auswahl der Marke und des Markenzeichens, die du zuordnen möchtest, umsichtig vor. | E12: Wählen Sie den Markenzeichennamen des Produkts aus | F12: Nike | G12: Optional
A13: Produktbeschreibung: Diese Attribute wirken sich darauf aus, wie Kunden Ihr Produkt auf der Website durch Blättern oder Suchen finden können
B14: t_2_productdescription | C14: Produktbeschreibung | D14: Eine Textbeschreibung des Produkts. | E14: Entsprechend den MMS-Leitlinien: Maximal 2000 Zeichen, die Rich Text-Formatierung wird nicht unterstützt. | F14: Langärmlige Strickjacke mit V-Ausschnitt, gerippter Taille und Taschen mit Schleifendetails | G14: Optional
B15: t_2_bulletpoint | C15: Aufzählungspunkt | D15: Kurzer beschreibender Text in Form von Aufzählungspunkten zu jeweils einem bestimmten Aspekt des Produkts. Diese werden direkt unter oder neben Ihrem Produktfoto angezeigt. Es ist sinnvoll, in diese Felder interessante Informationen einzugeben. Aufzählungspunkte werden automatisch eingefügt. | E15: Entsprechend den MMS-Leitlinien: Maximal 700 Zeichen, die Rich Text-Formatierung wird nicht unterstützt. Sie können pro Zelle einen Aufzählungspunkt hochladen | F15: Hergestellt mit pflegendem, reinem Aloe-Vera-Gel | G15: Optional
B16: t_2_detailimagesurl | C16: URL für Detailbilder | D16: Rufen Sie die URLs von einer beliebigen Bildhosting-Website ab und geben Sie sie in die entsprechenden Zellen ein. i. Seitenverhältnis: 1:1, 4:3, 16:9 ii. Auflösung: min. 720 p iii. Dauer: max. 180 Sek. iv. Dateigröße: max. 300 MB v. Dateitypen: WMV, AVI, 3GP, MOV, MP4, FLV, RMVB, MKV, M4V, X-FLV | E16: Rufen Sie die URLs von einer beliebigen Bildhosting-Website ab und geben Sie sie in die entsprechenden Zellen ein. i. Seitenverhältnis: min. 1:3; ii. Breite oder Höhe: min. 480 px; iii. Dateigröße: max. 3 MB; iv. Dateitypen: JPEG, JPG, PNG | F16: http://www.companyname.com/images/1250.main.jpg | G16: Optional
B17: t_2_detailvideourl | C17: Detail-Video-URL | D17: Die URL für das Detailvideo zu deinem Produkt. Das Detailvideo wird oben im Abschnitt mit den Produktdetails angezeigt. | E17: Rufen Sie die URLs von einer beliebigen Bildhosting-Website ab und geben Sie sie in die entsprechenden Zellen ein. i. Seitenverhältnis: 1:1, 4:3, 16:9 ii. Auflösung: min. 720 p iii. Dauer: max. 180 Sek. iv. Dateigröße: max. 300 MB v. Dateitypen: WMV, AVI, 3GP, MOV, MP4, FLV, RMVB, MKV, M4V, X-FLV | F17: http://www.companyname.com/videos/1250..mp4 | G17: Optional
A18: Verkaufseigenschaft (mindestens eine, höchstens zwei): Diese Attribute für das Produkt werden für verschiedene Variationen bereitgestellt
B19: t_4_variationtheme | C19: Variationsdesign | D19: Beschreibt die Parameter, um die das übergeordnete Produkt variieren kann. Der eingegebene Wert für dieses Feld muss für alle SKUs desselben Produkts identisch sein. Beispiel: Wenn das Produkt je nach Größe variiert, geben Sie den Wert „Größe“ ein. Wenn das Produkt je nach Farbe variiert, geben Sie den Wert „Farbe“ ein. Begriffe, die für Variationsdesigns verwendet werden, werden von Ihnen, also vom Händler erstellt. (Beispiel: „Menge“ kann eine beliebige Zahl sein) | E19: Wählen Sie ein zutreffendes Variationsdesign aus. | F19: Color × Size | G19: Erforderlich
A20: Variationen: Diese Attribute sind für die Käufer wichtig und sollten für die SKU des Produkts eingetragen werden
B21: t_5_skuimagesurl | C21: URL für SKU-Bilder | D21: SKU-Bilder werden oben auf der Produktseite angezeigt, wenn der Kunde durchklickt, um andere mit dem Produkt verknüpfte Ansichten anzuzeigen. Verschiedene SKU-Bilder bilden ein Produktkarussell. Sie können dieses Feld beispielsweise verwenden, um die Informationen auf dem Etikett oder die Verpackung Ihres Produkts anzuzeigen. Laden Sie zusätzliche Bilder hoch, die verschiedene Ansichten des Artikels zeigen oder den Artikel in einer emotional ansprechenden Umgebung darstellen. | E21: a. Für Kleidung: i. Seitenverhältnis: 3:4 ii. Breite: min. 1340 px iii. Höhe: min. 1785 px iv. Dateigröße: max. 3 MB v. Dateitypen: JPEG, JPG, PNG b. Für andere Produkte: i. Seitenverhältnis: 1:1 ii. Breite oder Höhe: min. 800 px iii. Dateigröße: max. 3 MB iv. Dateitypen: JPEG, JPG, PNG | F21: http://www.companyname.com/images/1250.main.jpg | G21: Erforderlich
B22: t_5_dimensions | C22: Abmessungen | D22: Bitte verwenden Sie zur Angabe der Produktabmessungen imperiale Einheiten. Dies kann Käufern helfen, die Größe und die Spezifikationen des Produkts besser einzuschätzen. | E22: a. Für Kleidung: i. Seitenverhältnis: 3:4 ii. Breite: min. 1340 px iii. Höhe: min. 1785 px iv. Dateigröße: max. 3 MB v. Dateitypen: JPEG, JPG, PNG b. Für andere Produkte: i. Seitenverhältnis: 1:1 ii. Breite oder Höhe: min. 800 px iii. Dateigröße: max. 3 MB iv. Dateitypen: JPEG, JPG, PNG | F22: http://www.companyname.com/images/1250.dimension.jpg | G22: Optional
B23: t_5_condition | C23: Zustand | D23: Das Feld „Zustand“ wird verwendet, um den Zustand eines gebrauchten Produkts zu beschreiben, einschließlich verschiedener Qualitätsstufen. Der Zustand muss für die Verbraucher angezeigt werden, um bei der Kaufentscheidung zu helfen. Alle SKUs in einem Produkt müssen die Einstellung für „Zustände“ aufweisen. | E23: Wählen Sie eine geeignete Option für das Produkt aus. Verschiedene Kategorien haben unterschiedliche Standards zur Einstufung der Zustandsstufen. Sie können sie im Temu Seller Center einsehen. | F23: Used - Like new | G23: Erforderlich
B24: t_5_quantity | C24: Anzahl | D24: Geben Sie die Menge des Artikels ein, die Sie zum Verkauf anbieten. Dies ist Ihre aktuelle BESTANDSVERPFLICHTUNG. Die Angabe der Menge ist für alle „untergeordneten“ oder eigenständigen Artikel erforderlich. Wenn Sie das Feld bei der ersten Übermittlung der Produktinformationen leer lassen, wird der Artikel als „Nicht vorrätig“ angezeigt. | E24: Geben Sie die Menge des Artikels ein, die Sie zum Verkauf anbieten. Dies ist Ihre aktuelle Bestandsverpflichtung (als ganze Zahl) | F24: 152 | G24: Erforderlich
B25: t_5_base_price_eur | C25: Grundpreis | D25: Der Basispreis sollte Ihre Kosten und den erwarteten Gewinn widerspiegeln. Sie erhalten Verkaufserlöse auf der Grundlage des operativen Preises für jedes verkaufte Produkt. Der endgültige Einzelhandelspreis ist nicht direkt mit Ihrer Zahlungsabrechnung verknüpft. Der Basispreis muss niedriger als der Listenpreis sein. | E25: Der Preisbereich liegt zwischen 0,01 € und 99999999,99 € mit maximal 2 Dezimalstellen und wird aufgerundet. | F25: 3.99 | G25: Erforderlich
B26: t_5_Reference Link | C26: Referenzlink | D26: Geben Sie (einen) Link(s) zu diesem Produkt aus anderen Quellen als Referenz an, um die Preisanpassung zu beschleunigen. | E26: Links zu diesem Produkt auf anderen Plattformen beginnen mit „https://“ oder „http://“
B27: t_5_list_price_eur | C27: Unverbindliche Preisempfehlung | D27: <div>Die unverbindliche Preisempfehlung (UVP) ist der vorgeschlagene oder empfohlene Einzelhandelspreis eines Produkts, der vom Hersteller festgelegt wird. </div><div style='margin-top: 4px'><span style='color: #FB7701'>Die UVP muss ein echter Verkaufspreis auf dem Zielmarkt sein</span> und den geltenden Gesetzen und Vorschriften entsprechen. Das bedeutet, dass dasselbe Produkt in letzter Zeit von anderen Einzelhändlern in diesem Markt tatsächlich zu der UVP beworben und verkauft worden sein muss. Wenn Ihr Produkt nicht über eine UVP verfügt, die alle diese Kriterien erfüllt, können Sie diese UVP nicht eingeben, müssen aber N/A („Not available“ = „Nicht verfügbar“) eingeben. Sie müssen sicherstellen, dass alle genannten UVP aktualisiert werden, falls zutreffend.</div><div style='margin-top: 4px; color: #FB7701'><div>Durch die Eingabe einer UVP bestätigen Sie Folgendes:</div><div>• Sie sind nicht der einzige Verkäufer des Produkts auf dem Markt, auf dem das Produkt verkauft wird (und wo ein UVP-Vergleich durchgeführt wird);</div><div>• Die UVP, die Sie angeben, ist aktuell;</div><div>• Sie haben Nachweise dafür, dass es sich bei der UVP, die Sie angeben, um einen echten Preis handelt, zu dem das Produkt in letzter Zeit von anderen Einzelhändlern auf dem Zielmarkt beworben und verkauft wurde, und dass die UVP vom Hersteller sorgfältig berechnet und ausgewiesen wurde. Sie müssen Temu diese Nachweise auf Anfrage zur Verfügung stellen.</div></div><div style='margin-top: 4px'>Temu kann jede Angabe einer UVP nach eigenem Ermessen entfernen, wenn Temu darüber Kenntnis hat oder Temu bewusst wird, dass die oben genannten Kriterien für eine konforme UVP nicht erfüllt werden.</div> | E27: Der Preisbereich liegt zwischen 0,01 € und 99999999,99 € mit maximal 2 Dezimalstellen und wird aufgerundet. | F27: 5.79 | G27: Optional
B28: t_5_notavailableforlistprice | C28: Nicht verfügbar für Listenpreis | D28: list_price_4_RRP | E28: Wählen Sie „Nicht zutreffend (N/A)“, wenn Ihr Produkt keine unverbindliche Preisempfehlung hat | F28: N/A | G28: Erforderlich
B29: t_5_weight_lb | C29: Gewicht des Pakets | D29: Diese Angabe zeigt das Paketgewicht der SKU an und wird von Temu zur Einschätzung der Logistikkosten verwendet. Bitte geben Sie dies korrekt ein. | E29: Der Gewichtsbereich liegt zwischen 0,1 g und 9999999,9 g mit maximal 1 Dezimalstelle und wird aufgerundet | F29: 10.2 | G29: Optional
B30: t_5_length_in | C30: Länge | D30: Diese Angabe zeigt das Paketvolumen der SKU an und wird von Temu zur Einschätzung der Logistikkosten verwendet. Bitte geben Sie dies korrekt ein. | E30: Der Längenbereich liegt zwischen 0,1 cm und 9999,9 cm mit maximal 1 Dezimalstelle und wird aufgerundet | F30: 3.1 | G30: Optional
B31: t_5_width_in | C31: Breite | D31: Diese Angabe zeigt das Paketvolumen der SKU an und wird von Temu zur Einschätzung der Logistikkosten verwendet. Bitte geben Sie dies korrekt ein. | E31: Der Längenbereich liegt zwischen 0,1 cm und 9999,9 cm mit maximal 1 Dezimalstelle und wird aufgerundet | F31: 2.1 | G31: Optional
B32: t_5_height_in | C32: Höhe | D32: Diese Angabe zeigt das Paketvolumen der SKU an und wird von Temu zur Einschätzung der Logistikkosten verwendet. Bitte geben Sie dies korrekt ein. | E32: Der Längenbereich liegt zwischen 0,1 cm und 9999,9 cm mit maximal 1 Dezimalstelle und wird aufgerundet | F32: 1.1 | G32: Optional
B33: t_5_externalproductidtype | C33: Externer Produkt-ID-Typ | D33: Der Typ der standardmäßigen, eindeutigen Kennung, die in das Produkt-ID-Feld eingegeben wird. Dies ist ein Pflichtfeld, wenn die Produkt-ID angegeben wird. | E33: Der Typ der standardmäßigen, eindeutigen Kennung, die in das Produkt-ID-Feld eingegeben wird. Dies ist ein Pflichtfeld, wenn die Produkt-ID angegeben wird. | F33: UPC | G33: Erforderlich
B34: t_5_externalproductid | C34: Externe Produktnummer | D34: Eine alphanumerische Standardzeichenfolge, die das Produkt eindeutig identifiziert. Dies kann eine GCID- (16 alphanumerische Zeichen), UPC- oder EAN-Nummer sein. Dies ist ein Pflichtfeld, wenn product_id_type angegeben ist. | E34: Geben Sie den entsprechenden Wert für die externe Produkt-ID basierend auf dem ausgewählten Typ an | F34: 714532191586 | G34: Erforderlich
A35: Angebot: Diese Attribute sind erforderlich, um Ihr Produkt für Kunden auf der Website verfügbar zu machen
B36: t_6_handlingtime | C36: Bearbeitungszeit | D36: Gibt die Zeit in Tagen an, die zwischen dem Eingang einer Bestellung eines Artikels und dem Zeitpunkt, an dem Sie den Artikel versenden können, liegt. Die Standardproduktionszeit beträgt ein bis zwei Werktage. Verwenden Sie dieses Feld, wenn Ihre Produktionszeit mehr als zwei Werktage beträgt. | E36: Identisch mit MMS. Unterstützt nur 1, 2 Tage. | F36: 1 day | G36: Erforderlich
B37: t_6_shippingtemplate | C37: Versandvorlage | D37: Verkäufer können eine Reihe von Versandkonfigurationen basierend auf Geschäftsanforderungen und Anwendungsfällen erstellen. Die Versandkonfigurationen können regionenbasiert sein und Regeln zur Festlegung von SLA und Tarifen für die Region enthalten. Wenn Verkäufer ein Produkt listen, um ein Angebot zu erstellen, müssen sie eine Versandkonfiguration für das Produkt auswählen. Die Versandkonfiguration wird verwendet, um die gültigen Versandoptionen auf der Website abzurufen. | E37: Zuerst muss die Erstellung der Versandvorlage unter [https://seller-eu.temu.com/shipping-templates-create.html] abgeschlossen werden. Dann werden die Namen aller verfügbaren Versandvorlagen im Store hier angezeigt. | F37: "Free Shipping Template", "Default Template" | G37: Optional
B38: t_6_itemtaxcode | C38: Artikelsteuercode (ITC) | D38: Der Artikelsteuercode (ITC) verbindet ein Produkt mit dem korrekten Mehrwertsteuersatz, der für die jeweilige Produktkategorie vorgeschrieben ist. Wenn dem Produkt kein ITC zugewiesen ist, wird der Standardwert aus „Berechnungseinstellungen“ angewendet. | E38: Geben Sie den von temu.com zur Verfügung gestellten Artikelsteuercode ein. | G38: Erforderlich
B39: t_6_fulfillmentchannel | C39: Fulfillment-Kanal | G39: Erforderlich
A40: Qualifikationen – Attribute, die zur Einhaltung der Verbrauchergesetze in dem Land oder der Region verwendet werden, in der der Artikel verkauft wird
B41: t_7_productguide | C41: Produktführer | E41: Bitte rufen Sie die URL des Handbuchs von einer beliebigen Bildhosting-Website ab und tragen Sie sie in die Zelle ein. Produktleitfaden – Ausfüllanforderungen: a. Dateigröße: max. 15 MB b. Dateityp: PDF | F41: http://www.companyname.com/guide/1250.pdf | G41: Erforderlich
B42: t_7_Country/Region of Origin | C42: Ursprungsland/-region | D42: Das Ursprungsland/die -region eines Produkts ist im Allgemeinen das Land oder die Region, in dem das Produkt in seiner Gesamtheit hergestellt oder gefertigt wurde. Wenn das Produkt nicht nur in einem Land oder einer Region hergestellt oder gefertigt wurde, ist das Ursprungsland/die -region im Allgemeinen dasjenige, in dem die letzte „wesentliche Be- oder Verarbeitung“ des Produkts stattfand. | E42: Wählen Sie das Land/die Region des Produkts aus | F42: Germany | G42: Optional
B43: t_7_Province of Origin | C43: Herkunftsregion | D43: Wenn das Ursprungsland Festlandchina ist, darf die Ursprungsprovinz nicht leer sein. | E43: Wählen Sie die Provinz des Produkts aus | G43: Erforderlich
B44: t_7_Product Label For Country/Region of Origin | C44: Produktetikett für Ursprungsland/Ursprungsregion | G44: Erforderlich
B45: t_8_Have any products under this goods ID been placed on the EU (or Northern Ireland) market after December 13, 2024? | C45: Wurden Produkte unter dieser Waren-ID nach dem 13. Dezember 2024 in der EU (oder Nordirland) platziert? | D45: Wenn Sie auswählen: „Ja. Produkte mit dieser Waren-ID sind nach dem 13. Dezember 2024 in der EU (oder Nordirland) in Verkehr gebracht worden.“ Ihr Produkt muss den einschlägigen GPSR-Anforderungen entsprechen. Geben Sie den Hersteller, den EU-Verantwortlichen, den Identifizierungscode und ggf. Warn- und Sicherheitsinformationen an, und lade auf der Seite zur Produktkonformität entsprechende Bilder hoch. Andernfalls werden nicht konforme Waren vom EU-Standort und der Region Nordirland im Vereinigten Königreich entfernt. Wenn Sie die erforderlichen Informationen noch nicht übermittelt haben, senden Sie sie bitte so schnell wie möglich über die Produktbearbeitungsseite ab. Weitere Informationen zu den GPSR-Anforderungen erfahren Sie, indem Sie „GPSR-Informationen und FAQs“ auf der Artikelseite zu Richtlinien & Betrieb suchen. | G45: Erforderlich
B46: t_8_Product Identification | C46: Produktidentifikation | D46: Für Produkte, die nach dem 13. Dezember 2024 in der EU (oder Nordirland) in Verkehr gebracht werden, müssen Sie die Produktkennzeichnung angeben, da sonst der Verkauf in der EU (oder Nordirland) beeinträchtigt wird. Sie können die Chargennummer, die Seriennummer oder andere Elemente angeben, die als Produktidentifikation zur Identifizierung und Rückverfolgung des Produkts verwendet werden können. | G46: Optional
B47: t_8_Manufacturer | C47: Hersteller | D47: Der Hersteller muss mit den Angaben auf dem Foto übereinstimmen. | E47: Zuerst muss der Hersteller unter [https://seller-eu.temu.com/performance/account-health.html?subTab=manufacturer] hinzugefügt werden. Dann werden alle Herstellernamen im Store hier angezeigt. | G47: Optional
B48: t_8_EU responsible person | C48: EU-Verantwortlicher | D48: Wenn sich der Hersteller innerhalb der EU befindet, muss keine verantwortliche Person ausgewählt werden. Wenn Sie eine verantwortliche Person auswählen, stellen Sie bitte sicher, dass diese mit den Informationen auf dem Foto übereinstimmt. | E48: Zuerst muss die verantwortliche Person unter [https://seller-eu.temu.com/performance/account-health.html?subTab=person] hinzugefügt werden. Dann werden alle Namen der verantwortlichen Personen im Store hier angezeigt. | G48: Optional

Sheet Template
A1: Verarbeitungsergebnisse | E1: Produktidentität | T1: Produktbeschreibung | BY1: Produktdetails | DA1: Verkaufseigenschaft | DO1: Variationen | ET1: Angebot | EX1: Qualifikationen
A2: Warennummer | B2: SKU-ID | C2: Status | D2: Details | E2: Kategorie | F2: Kategoriename | G2: Produkttyp | H2: Verarbeitungsverfahren zur Anpassung | I2: Primärverfahren | J2: Sekundärverfahren | K2: Sekundärverfahren | L2: Produktname | M2: Verkäufer Goods | N2: Verkäufer SKU | O2: Aktualisieren oder hinzufügen | P2: Warennummer | Q2: SKU-ID | R2: Marke | S2: Markenzeichen | T2: Produktbeschreibung | U2: Aufzählungspunkt | V2: Aufzählungspunkt | W2: Aufzählungspunkt | X2: Aufzählungspunkt | Y2: Aufzählungspunkt | Z2: Aufzählungspunkt | AA2: URL für Detailbilder | AB2: URL für Detailbilder | AC2: URL für Detailbilder | AD2: URL für Detailbilder | AE2: URL für Detailbilder | AF2: URL für Detailbilder | AG2: URL für Detailbilder | AH2: URL für Detailbilder | AI2: URL für Detailbilder | AJ2: URL für Detailbilder | AK2: URL für Detailbilder | AL2: URL für Detailbilder | AM2: URL für Detailbilder | AN2: URL für Detailbilder | AO2: URL für Detailbilder | AP2: URL für Detailbilder | AQ2: URL für Detailbilder | AR2: URL für Detailbilder | AS2: URL für Detailbilder | AT2: URL für Detailbilder | AU2: URL für Detailbilder | AV2: URL für Detailbilder | AW2: URL für Detailbilder | AX2: URL für Detailbilder | AY2: URL für Detailbilder | AZ2: URL für Detailbilder | BA2: URL für Detailbilder | BB2: URL für Detailbilder | BC2: URL für Detailbilder | BD2: URL für Detailbilder | BE2: URL für Detailbilder | BF2: URL für Detailbilder | BG2: URL für Detailbilder | BH2: URL für Detailbilder | BI2: URL für Detailbilder | BJ2: URL für Detailbilder | BK2: URL für Detailbilder | BL2: URL für Detailbilder | BM2: URL für Detailbilder | BN2: URL für Detailbilder | BO2: URL für Detailbilder | BP2: URL für Detailbilder | BQ2: URL für Detailbilder | BR2: URL für Detailbilder | BS2: URL für Detailbilder | BT2: URL für Detailbilder | BU2: URL für Detailbilder | BV2: URL für Detailbilder | BW2: URL für Detailbilder | BX2: Detail-Video-URL | BY2: 1920 - Hauptmaterial | BZ2: 4109 - Echte Ledersorte | CA2: 7317 - Holzart | CB2: 7318 - Holzarten | CC2: 1941 - Anwendbare Modelle | CD2: 1450 - OEM-Nummer | CE2: 120 - Bauteilposition | CF2: 121 - Material | CG2: 335 - Produktgrad | CH2: 1081 - Oberflächenbehandlungsprozess | CI2: 402 - Beschreibung Krümmung | CJ2: 25 - Geeignete Typen | CK2: 134 - Artikelform | CL2: 200 - Äußeres Finish | CM2: 1279 - Verwendungszweck | CN2: 1125 - Lichtquellenart | CO2: 358 - Spezifische Verwendungsszenarien | CP2: 2153 - Batterieeigenschaften | CQ2: 2147 - Wiederaufladbare Batterie | CR2: 2154 - Solarbatterie | CS2: 3740 - Nicht wiederaufladbare Batterie | CT2: 1067 - Stromversorgungsart | CU2: 1132 - Betriebsspannung | CV2: 1485 - Steckertyp | CW2: 1271 - Fahrzeugreihe | CX2: 1420 - Produkttypen | CY2: 15 - Zusammensetzung:Neopren | CZ2: 15 - Zusammensetzung:Sonstige Fasern | DA2: Variationsdesign | DB2: Farbe | DC2: Größe | DD2: Stil | DE2: Material | DF2: Aromen | DG2: Anwendbare Personen | DH2: Kapazität | DI2: Komposition | DJ2: Gewicht | DK2: Artikel | DL2: Menge | DM2: Modell | DN2: Haarlänge | DO2: URL für SKU-Bilder | DP2: URL für SKU-Bilder | DQ2: URL für SKU-Bilder | DR2: URL für SKU-Bilder | DS2: URL für SKU-Bilder | DT2: URL für SKU-Bilder | DU2: URL für SKU-Bilder | DV2: URL für SKU-Bilder | DW2: URL für SKU-Bilder | DX2: URL für SKU-Bilder | DY2: Abmessungen | DZ2: Anzahl | EA2: Basispreis - EUR | EB2: Referenzlink | EC2: Listenpreis - EUR | ED2: Nicht verfügbar für Listenpreis | EE2: Gewicht des Pakets - g | EF2: Länge - cm | EG2: Breite - cm | EH2: Höhe - cm | EI2: SKU-Typ | EJ2: Einzeln verpackt | EK2: Gesamtverpackungsanzahl | EL2: Verpackungseinheit | EM2: Gesamtartikelanzahl | EN2: Artikeleinheit | EO2: Nettoinhalt | EP2: Gesamtnettoinhalt | EQ2: Nettoinhaltseinheit | ER2: Externer Produkt-ID-Typ | ES2: Externe Produktnummer | ET2: Versandvorlage | EU2: Bearbeitungszeit | EV2: Fulfillment-Kanal | EW2: Artikelsteuercode (ITC) | EX2: Ursprungsland/-region | EY2: Herkunftsregion | EZ2: SKU-Verpackungsinformationen (mit sichtbarem Etikett) | FA2: SKU-Verpackungsinformationen (mit sichtbarem Etikett) | FB2: SKU-Verpackungsinformationen (mit sichtbarem Etikett) | FC2: SKU-Verpackungsinformationen (mit sichtbarem Etikett) | FD2: SKU-Verpackungsinformationen (mit sichtbarem Etikett) | FE2: SKU-Verpackungsinformationen (mit sichtbarem Etikett) | FF2: SKU-Verpackungsinformationen (mit sichtbarem Etikett) | FG2: SKU-Verpackungsinformationen (mit sichtbarem Etikett) | FH2: SKU-Verpackungsinformationen (mit sichtbarem Etikett) | FI2: SKU-Verpackungsinformationen (mit sichtbarem Etikett) | FJ2: SKU-Verpackungsinformationen (mit sichtbarem Etikett) | FK2: SKU-Verpackungsinformationen (mit sichtbarem Etikett) | FL2: SKU-Verpackungsinformationen (mit sichtbarem Etikett) | FM2: SKU-Verpackungsinformationen (mit sichtbarem Etikett) | FN2: SKU-Verpackungsinformationen (mit sichtbarem Etikett) | FO2: SKU-Verpackungsinformationen (mit sichtbarem Etikett) | FP2: SKU-Verpackungsinformationen (mit sichtbarem Etikett) | FQ2: SKU-Verpackungsinformationen (mit sichtbarem Etikett) | FR2: SKU-Verpackungsinformationen (mit sichtbarem Etikett) | FS2: SKU-Verpackungsinformationen (mit sichtbarem Etikett) | FT2: SKU-Verpackungsinformationen (mit sichtbarem Etikett) | FU2: SKU-Verpackungsinformationen (mit sichtbarem Etikett) | FV2: SKU-Verpackungsinformationen (mit sichtbarem Etikett) | FW2: SKU-Verpackungsinformationen (mit sichtbarem Etikett) | FX2: SKU-Verpackungsinformationen (mit sichtbarem Etikett) | FY2: SKU-Verpackungsinformationen (mit sichtbarem Etikett) | FZ2: SKU-Verpackungsinformationen (mit sichtbarem Etikett) | GA2: SKU-Verpackungsinformationen (mit sichtbarem Etikett) | GB2: SKU-Verpackungsinformationen (mit sichtbarem Etikett) | GC2: SKU-Verpackungsinformationen (mit sichtbarem Etikett) | GD2: SKU-Verpackungsinformationen (mit sichtbarem Etikett) | GE2: SKU-Verpackungsinformationen (mit sichtbarem Etikett) | GF2: SKU-Verpackungsinformationen (mit sichtbarem Etikett) | GG2: SKU-Verpackungsinformationen (mit sichtbarem Etikett) | GH2: SKU-Verpackungsinformationen (mit sichtbarem Etikett) | GI2: SKU-Verpackungsinformationen (mit sichtbarem Etikett) | GJ2: SKU-Verpackungsinformationen (mit sichtbarem Etikett) | GK2: SKU-Verpackungsinformationen (mit sichtbarem Etikett) | GL2: SKU-Verpackungsinformationen (mit sichtbarem Etikett) | GM2: SKU-Verpackungsinformationen (mit sichtbarem Etikett) | GN2: SKU-Verpackungsinformationen (mit sichtbarem Etikett) | GO2: SKU-Verpackungsinformationen (mit sichtbarem Etikett) | GP2: SKU-Verpackungsinformationen (mit sichtbarem Etikett) | GQ2: SKU-Verpackungsinformationen (mit sichtbarem Etikett) | GR2: SKU-Verpackungsinformationen (mit sichtbarem Etikett) | GS2: Ursprungsetikett & Herstellerinformationen | GT2: Ursprungsetikett & Herstellerinformationen | GU2: Ursprungsetikett & Herstellerinformationen | GV2: Ursprungsetikett & Herstellerinformationen | GW2: Ursprungsetikett & Herstellerinformationen | GX2: Produktführer - English | GY2: Wurden Produkte unter dieser Waren-ID nach dem 13. Dezember 2024 in der EU (oder Nordirland) platziert? | GZ2: Produktidentifikation | HA2: Hersteller | HB2: EU-Verantwortlicher
A3: Reserved line, prohibit any operation. | B3: Reserved line, prohibit any operation. | C3: Reserved line, prohibit any operation. | D3: Reserved line, prohibit any operation. | E3: eyJ0ZW1wbGF0ZV9pZCI6MjgzMjQxOTkwMTg1MjI1LCJjYXRfaWRzIjoiMjEyMjYsMjE2ODAsMjE2OTEsMjE3NzUsMjE3ODUsMjE3OTIsMjE4NDIsMjE4NzMsMjE5MDMsMjIxODQsMjIyMjYsMjIyMjkiLCJ0ZW1wbGF0ZV9sYW5ndWFnZSI6ImRlIiwic2l0ZV9pZCI6MTA1LCJ2ZXJzaW9uIjoiMy4wLjAiLCJ0eXBlIjowfQ== | F3: Reserved line, prohibit any operation. | G3: Reserved line, prohibit any operation. | H3: Reserved line, prohibit any operation. | I3: Reserved line, prohibit any operation. | J3: Reserved line, prohibit any operation. | K3: Reserved line, prohibit any operation. | L3: Reserved line, prohibit any operation. | M3: Reserved line, prohibit any operation. | N3: Reserved line, prohibit any operation. | O3: Reserved line, prohibit any operation. | P3: Reserved line, prohibit any operation. | Q3: Reserved line, prohibit any operation. | R3: Reserved line, prohibit any operation. | S3: Reserved line, prohibit any operation. | T3: Reserved line, prohibit any operation. | U3: Reserved line, prohibit any operation. | V3: Reserved line, prohibit any operation. | W3: Reserved line, prohibit any operation. | X3: Reserved line, prohibit any operation. | Y3: Reserved line, prohibit any operation. | Z3: Reserved line, prohibit any operation. | AA3: Reserved line, prohibit any operation. | AB3: Reserved line, prohibit any operation. | AC3: Reserved line, prohibit any operation. | AD3: Reserved line, prohibit any operation. | AE3: Reserved line, prohibit any operation. | AF3: Reserved line, prohibit any operation. | AG3: Reserved line, prohibit any operation. | AH3: Reserved line, prohibit any operation. | AI3: Reserved line, prohibit any operation. | AJ3: Reserved line, prohibit any operation. | AK3: Reserved line, prohibit any operation. | AL3: Reserved line, prohibit any operation. | AM3: Reserved line, prohibit any operation. | AN3: Reserved line, prohibit any operation. | AO3: Reserved line, prohibit any operation. | AP3: Reserved line, prohibit any operation. | AQ3: Reserved line, prohibit any operation. | AR3: Reserved line, prohibit any operation. | AS3: Reserved line, prohibit any operation. | AT3: Reserved line, prohibit any operation. | AU3: Reserved line, prohibit any operation. | AV3: Reserved line, prohibit any operation. | AW3: Reserved line, prohibit any operation. | AX3: Reserved line, prohibit any operation. | AY3: Reserved line, prohibit any operation. | AZ3: Reserved line, prohibit any operation. | BA3: Reserved line, prohibit any operation. | BB3: Reserved line, prohibit any operation. | BC3: Reserved line, prohibit any operation. | BD3: Reserved line, prohibit any operation. | BE3: Reserved line, prohibit any operation. | BF3: Reserved line, prohibit any operation. | BG3: Reserved line, prohibit any operation. | BH3: Reserved line, prohibit any operation. | BI3: Reserved line, prohibit any operation. | BJ3: Reserved line, prohibit any operation. | BK3: Reserved line, prohibit any operation. | BL3: Reserved line, prohibit any operation. | BM3: Reserved line, prohibit any operation. | BN3: Reserved line, prohibit any operation. | BO3: Reserved line, prohibit any operation. | BP3: Reserved line, prohibit any operation. | BQ3: Reserved line, prohibit any operation. | BR3: Reserved line, prohibit any operation. | BS3: Reserved line, prohibit any operation. | BT3: Reserved line, prohibit any operation. | BU3: Reserved line, prohibit any operation. | BV3: Reserved line, prohibit any operation. | BW3: Reserved line, prohibit any operation. | BX3: Reserved line, prohibit any operation. | BY3: Reserved line, prohibit any operation. | BZ3: Reserved line, prohibit any operation. | CA3: Reserved line, prohibit any operation. | CB3: Reserved line, prohibit any operation. | CC3: Reserved line, prohibit any operation. | CD3: Reserved line, prohibit any operation. | CE3: Reserved line, prohibit any operation. | CF3: Reserved line, prohibit any operation. | CG3: Reserved line, prohibit any operation. | CH3: Reserved line, prohibit any operation. | CI3: Reserved line, prohibit any operation. | CJ3: Reserved line, prohibit any operation. | CK3: Reserved line, prohibit any operation. | CL3: Reserved line, prohibit any operation. | CM3: Reserved line, prohibit any operation. | CN3: Reserved line, prohibit any operation. | CO3: Reserved line, prohibit any operation. | CP3: Reserved line, prohibit any operation. | CQ3: Reserved line, prohibit any operation. | CR3: Reserved line, prohibit any operation. | CS3: Reserved line, prohibit any operation. | CT3: Reserved line, prohibit any operation. | CU3: Reserved line, prohibit any operation. | CV3: Reserved line, prohibit any operation. | CW3: Reserved line, prohibit any operation. | CX3: Reserved line, prohibit any operation. | CY3: Reserved line, prohibit any operation. | CZ3: Reserved line, prohibit any operation. | DA3: Reserved line, prohibit any operation. | DB3: Reserved line, prohibit any operation. | DC3: Reserved line, prohibit any operation. | DD3: Reserved line, prohibit any operation. | DE3: Reserved line, prohibit any operation. | DF3: Reserved line, prohibit any operation. | DG3: Reserved line, prohibit any operation. | DH3: Reserved line, prohibit any operation. | DI3: Reserved line, prohibit any operation. | DJ3: Reserved line, prohibit any operation. | DK3: Reserved line, prohibit any operation. | DL3: Reserved line, prohibit any operation. | DM3: Reserved line, prohibit any operation. | DN3: Reserved line, prohibit any operation. | DO3: Reserved line, prohibit any operation. | DP3: Reserved line, prohibit any operation. | DQ3: Reserved line, prohibit any operation. | DR3: Reserved line, prohibit any operation. | DS3: Reserved line, prohibit any operation. | DT3: Reserved line, prohibit any operation. | DU3: Reserved line, prohibit any operation. | DV3: Reserved line, prohibit any operation. | DW3: Reserved line, prohibit any operation. | DX3: Reserved line, prohibit any operation. | DY3: Reserved line, prohibit any operation. | DZ3: Reserved line, prohibit any operation. | EA3: Reserved line, prohibit any operation. | EB3: Reserved line, prohibit any operation. | EC3: Reserved line, prohibit any operation. | ED3: Reserved line, prohibit any operation. | EE3: Reserved line, prohibit any operation. | EF3: Reserved line, prohibit any operation. | EG3: Reserved line, prohibit any operation. | EH3: Reserved line, prohibit any operation. | EI3: Reserved line, prohibit any operation. | EJ3: Reserved line, prohibit any operation. | EK3: Reserved line, prohibit any operation. | EL3: Reserved line, prohibit any operation. | EM3: Reserved line, prohibit any operation. | EN3: Reserved line, prohibit any operation. | EO3: Reserved line, prohibit any operation. | EP3: Reserved line, prohibit any operation. | EQ3: Reserved line, prohibit any operation. | ER3: Reserved line, prohibit any operation. | ES3: Reserved line, prohibit any operation. | ET3: Reserved line, prohibit any operation. | EU3: Reserved line, prohibit any operation. | EV3: Reserved line, prohibit any operation. | EW3: Reserved line, prohibit any operation. | EX3: Reserved line, prohibit any operation. | EY3: Reserved line, prohibit any operation. | EZ3: Reserved line, prohibit any operation. | FA3: Reserved line, prohibit any operation. | FB3: Reserved line, prohibit any operation. | FC3: Reserved line, prohibit any operation. | FD3: Reserved line, prohibit any operation. | FE3: Reserved line, prohibit any operation. | FF3: Reserved line, prohibit any operation. | FG3: Reserved line, prohibit any operation. | FH3: Reserved line, prohibit any operation. | FI3: Reserved line, prohibit any operation. | FJ3: Reserved line, prohibit any operation. | FK3: Reserved line, prohibit any operation. | FL3: Reserved line, prohibit any operation. | FM3: Reserved line, prohibit any operation. | FN3: Reserved line, prohibit any operation. | FO3: Reserved line, prohibit any operation. | FP3: Reserved line, prohibit any operation. | FQ3: Reserved line, prohibit any operation. | FR3: Reserved line, prohibit any operation. | FS3: Reserved line, prohibit any operation. | FT3: Reserved line, prohibit any operation. | FU3: Reserved line, prohibit any operation. | FV3: Reserved line, prohibit any operation. | FW3: Reserved line, prohibit any operation. | FX3: Reserved line, prohibit any operation. | FY3: Reserved line, prohibit any operation. | FZ3: Reserved line, prohibit any operation. | GA3: Reserved line, prohibit any operation. | GB3: Reserved line, prohibit any operation. | GC3: Reserved line, prohibit any operation. | GD3: Reserved line, prohibit any operation. | GE3: Reserved line, prohibit any operation. | GF3: Reserved line, prohibit any operation. | GG3: Reserved line, prohibit any operation. | GH3: Reserved line, prohibit any operation. | GI3: Reserved line, prohibit any operation. | GJ3: Reserved line, prohibit any operation. | GK3: Reserved line, prohibit any operation. | GL3: Reserved line, prohibit any operation. | GM3: Reserved line, prohibit any operation. | GN3: Reserved line, prohibit any operation. | GO3: Reserved line, prohibit any operation. | GP3: Reserved line, prohibit any operation. | GQ3: Reserved line, prohibit any operation. | GR3: Reserved line, prohibit any operation. | GS3: Reserved line, prohibit any operation. | GT3: Reserved line, prohibit any operation. | GU3: Reserved line, prohibit any operation. | GV3: Reserved line, prohibit any operation. | GW3: Reserved line, prohibit any operation. | GX3: Reserved line, prohibit any operation. | GY3: Reserved line, prohibit any operation. | GZ3: Reserved line, prohibit any operation. | HA3: Reserved line, prohibit any operation. | HB3: Reserved line, prohibit any operation.
A4: t_0_Goods Id | B4: t_0_Sku Id | C4: t_0_Status | D4: t_0_Details | E4: t_1_Category | F4: t_1_Category Name | G4: t_1_Product type | H4: t_1_Customization processing technique | I4: t_1_Primary technique | J4: t_1_Secondary technique | K4: t_1_Secondary technique | L4: t_1_Product Name | M4: t_1_Contribution Goods | N4: t_1_Contribution SKU | O4: t_1_Update or Add | P4: t_1_Goods Id | Q4: t_1_Sku Id | R4: t_1_Brand | S4: t_1_Trademark | T4: t_2_Product Description | U4: t_2_Bullet Point | V4: t_2_Bullet Point | W4: t_2_Bullet Point | X4: t_2_Bullet Point | Y4: t_2_Bullet Point | Z4: t_2_Bullet Point | AA4: t_2_Detail Images URL | AB4: t_2_Detail Images URL | AC4: t_2_Detail Images URL | AD4: t_2_Detail Images URL | AE4: t_2_Detail Images URL | AF4: t_2_Detail Images URL | AG4: t_2_Detail Images URL | AH4: t_2_Detail Images URL | AI4: t_2_Detail Images URL | AJ4: t_2_Detail Images URL | AK4: t_2_Detail Images URL | AL4: t_2_Detail Images URL | AM4: t_2_Detail Images URL | AN4: t_2_Detail Images URL | AO4: t_2_Detail Images URL | AP4: t_2_Detail Images URL | AQ4: t_2_Detail Images URL | AR4: t_2_Detail Images URL | AS4: t_2_Detail Images URL | AT4: t_2_Detail Images URL | AU4: t_2_Detail Images URL | AV4: t_2_Detail Images URL | AW4: t_2_Detail Images URL | AX4: t_2_Detail Images URL | AY4: t_2_Detail Images URL | AZ4: t_2_Detail Images URL | BA4: t_2_Detail Images URL | BB4: t_2_Detail Images URL | BC4: t_2_Detail Images URL | BD4: t_2_Detail Images URL | BE4: t_2_Detail Images URL | BF4: t_2_Detail Images URL | BG4: t_2_Detail Images URL | BH4: t_2_Detail Images URL | BI4: t_2_Detail Images URL | BJ4: t_2_Detail Images URL | BK4: t_2_Detail Images URL | BL4: t_2_Detail Images URL | BM4: t_2_Detail Images URL | BN4: t_2_Detail Images URL | BO4: t_2_Detail Images URL | BP4: t_2_Detail Images URL | BQ4: t_2_Detail Images URL | BR4: t_2_Detail Images URL | BS4: t_2_Detail Images URL | BT4: t_2_Detail Images URL | BU4: t_2_Detail Images URL | BV4: t_2_Detail Images URL | BW4: t_2_Detail Images URL | BX4: t_2_Detail Video URL | BY4: t_3_Property:1920 | BZ4: t_3_Property:4109 | CA4: t_3_Property:7317 | CB4: t_3_Property:7318 | CC4: t_3_Property:1941 | CD4: t_3_Property:1450 | CE4: t_3_Property:120 | CF4: t_3_Property:121 | CG4: t_3_Property:335 | CH4: t_3_Property:1081 | CI4: t_3_Property:402 | CJ4: t_3_Property:25 | CK4: t_3_Property:134 | CL4: t_3_Property:200 | CM4: t_3_Property:1279 | CN4: t_3_Property:1125 | CO4: t_3_Property:358 | CP4: t_3_Property:2153 | CQ4: t_3_Property:2147 | CR4: t_3_Property:2154 | CS4: t_3_Property:3740 | CT4: t_3_Property:1067 | CU4: t_3_Property:1132 | CV4: t_3_Property:1485 | CW4: t_3_Property:1271 | CX4: t_3_Property:1420 | CY4: t_3_Property:15:35723 | CZ4: t_3_Property:15:36254 | DA4: t_4_Variation Theme | DB4: t_4_Custom Spec:1001 | DC4: t_4_Custom Spec:3001 | DD4: t_4_Custom Spec:18012 | DE4: t_4_Custom Spec:17017 | DF4: t_4_Custom Spec:18013 | DG4: t_4_Custom Spec:17018 | DH4: t_4_Custom Spec:18014 | DI4: t_4_Custom Spec:17019 | DJ4: t_4_Custom Spec:18016 | DK4: t_4_Custom Spec:17020 | DL4: t_4_Custom Spec:15998553 | DM4: t_4_Custom Spec:45114199 | DN4: t_4_Custom Spec:44214483 | DO4: t_6_SKU Images URL | DP4: t_6_SKU Images URL | DQ4: t_6_SKU Images URL | DR4: t_6_SKU Images URL | DS4: t_6_SKU Images URL | DT4: t_6_SKU Images URL | DU4: t_6_SKU Images URL | DV4: t_6_SKU Images URL | DW4: t_6_SKU Images URL | DX4: t_6_SKU Images URL | DY4: t_6_Dimensions | DZ4: t_6_Quantity | EA4: t_6_Base Price | EB4: t_6_Reference Link | EC4: t_6_List Price | ED4: t_6_Not available for List price | EE4: t_6_Weight | EF4: t_6_Length | EG4: t_6_Width | EH4: t_6_Height | EI4: t_6_SKU type | EJ4: t_6_Individually packed | EK4: t_6_Total packaging quantity | EL4: t_6_Packaging unit | EM4: t_6_Total item quantity | EN4: t_6_Item unit | EO4: t_6_Net content | EP4: t_6_Total net content | EQ4: t_6_Net content unit | ER4: t_6_External Product ID Type | ES4: t_6_External Product ID | ET4: t_7_Shipping Template | EU4: t_7_Handling Time | EV4: t_7_Fulfillment Channel | EW4: t_7_Item Tax Code | EX4: t_8_Country/Region of Origin | EY4: t_8_Province of Origin | EZ4: t_8_SKU Packaging Information (with visible label) | FA4: t_8_SKU Packaging Information (with visible label) | FB4: t_8_SKU Packaging Information (with visible label) | FC4: t_8_SKU Packaging Information (with visible label) | FD4: t_8_SKU Packaging Information (with visible label) | FE4: t_8_SKU Packaging Information (with visible label) | FF4: t_8_SKU Packaging Information (with visible label) | FG4: t_8_SKU Packaging Information (with visible label) | FH4: t_8_SKU Packaging Information (with visible label) | FI4: t_8_SKU Packaging Information (with visible label) | FJ4: t_8_SKU Packaging Information (with visible label) | FK4: t_8_SKU Packaging Information (with visible label) | FL4: t_8_SKU Packaging Information (with visible label) | FM4: t_8_SKU Packaging Information (with visible label) | FN4: t_8_SKU Packaging Information (with visible label) | FO4: t_8_SKU Packaging Information (with visible label) | FP4: t_8_SKU Packaging Information (with visible label) | FQ4: t_8_SKU Packaging Information (with visible label) | FR4: t_8_SKU Packaging Information (with visible label) | FS4: t_8_SKU Packaging Information (with visible label) | FT4: t_8_SKU Packaging Information (with visible label) | FU4: t_8_SKU Packaging Information (with visible label) | FV4: t_8_SKU Packaging Information (with visible label) | FW4: t_8_SKU Packaging Information (with visible label) | FX4: t_8_SKU Packaging Information (with visible label) | FY4: t_8_SKU Packaging Information (with visible label) | FZ4: t_8_SKU Packaging Information (with visible label) | GA4: t_8_SKU Packaging Information (with visible label) | GB4: t_8_SKU Packaging Information (with visible label) | GC4: t_8_SKU Packaging Information (with visible label) | GD4: t_8_SKU Packaging Information (with visible label) | GE4: t_8_SKU Packaging Information (with visible label) | GF4: t_8_SKU Packaging Information (with visible label) | GG4: t_8_SKU Packaging Information (with visible label) | GH4: t_8_SKU Packaging Information (with visible label) | GI4: t_8_SKU Packaging Information (with visible label) | GJ4: t_8_SKU Packaging Information (with visible label) | GK4: t_8_SKU Packaging Information (with visible label) | GL4: t_8_SKU Packaging Information (with visible label) | GM4: t_8_SKU Packaging Information (with visible label) | GN4: t_8_SKU Packaging Information (with visible label) | GO4: t_8_SKU Packaging Information (with visible label) | GP4: t_8_SKU Packaging Information (with visible label) | GQ4: t_8_SKU Packaging Information (with visible label) | GR4: t_8_SKU Packaging Information (with visible label) | GS4: t_8_Origin Label & Manufacturer Information | GT4: t_8_Origin Label & Manufacturer Information | GU4: t_8_Origin Label & Manufacturer Information | GV4: t_8_Origin Label & Manufacturer Information | GW4: t_8_Origin Label & Manufacturer Information | GX4: t_8_Product Guide | GY4: t_8_Governance Property:1100100224 | GZ4: t_8_Governance Property:1100100115 | HA4: t_8_Governance Property:3 | HB4: t_8_Governance Property:2
F5: =IFERROR(VLOOKUP(INDIRECT(ADDRESS(ROW(), COLUMN()-1)), 'Category Name'!$A:$B, 2, FALSE), "Bitte wählen Sie zunächst die [Kategorie] aus. Nach der Auswahl wird hier der vollständige Kategorienpfad angezeigt. Bitte ändern Sie die Funktionen in den Zellen nicht") -> 0
F6: =IFERROR(VLOOKUP(INDIRECT(ADDRESS(ROW(), COLUMN()-1)), 'Category Name'!$A:$B, 2, FALSE), "Bitte wählen Sie zunächst die [Kategorie] aus. Nach der Auswahl wird hier der vollständige Kategorienpfad angezeigt. Bitte ändern Sie die Funktionen in den Zellen nicht") -> 0
F7: =IFERROR(VLOOKUP(INDIRECT(ADDRESS(ROW(), COLUMN()-1)), 'Category Name'!$A:$B, 2, FALSE), "Bitte wählen Sie zunächst die [Kategorie] aus. Nach der Auswahl wird hier der vollständige Kategorienpfad angezeigt. Bitte ändern Sie die Funktionen in den Zellen nicht") -> 0
F8: =IFERROR(VLOOKUP(INDIRECT(ADDRESS(ROW(), COLUMN()-1)), 'Category Name'!$A:$B, 2, FALSE), "Bitte wählen Sie zunächst die [Kategorie] aus. Nach der Auswahl wird hier der vollständige Kategorienpfad angezeigt. Bitte ändern Sie die Funktionen in den Zellen nicht") -> 0
F9: =IFERROR(VLOOKUP(INDIRECT(ADDRESS(ROW(), COLUMN()-1)), 'Category Name'!$A:$B, 2, FALSE), "Bitte wählen Sie zunächst die [Kategorie] aus. Nach der Auswahl wird hier der vollständige Kategorienpfad angezeigt. Bitte ändern Sie die Funktionen in den Zellen nicht") -> 0
F10: =IFERROR(VLOOKUP(INDIRECT(ADDRESS(ROW(), COLUMN()-1)), 'Category Name'!$A:$B, 2, FALSE), "Bitte wählen Sie zunächst die [Kategorie] aus. Nach der Auswahl wird hier der vollständige Kategorienpfad angezeigt. Bitte ändern Sie die Funktionen in den Zellen nicht") -> 0
F11: =IFERROR(VLOOKUP(INDIRECT(ADDRESS(ROW(), COLUMN()-1)), 'Category Name'!$A:$B, 2, FALSE), "Bitte wählen Sie zunächst die [Kategorie] aus. Nach der Auswahl wird hier der vollständige Kategorienpfad angezeigt. Bitte ändern Sie die Funktionen in den Zellen nicht") -> 0
F12: =IFERROR(VLOOKUP(INDIRECT(ADDRESS(ROW(), COLUMN()-1)), 'Category Name'!$A:$B, 2, FALSE), "Bitte wählen Sie zunächst die [Kategorie] aus. Nach der Auswahl wird hier der vollständige Kategorienpfad angezeigt. Bitte ändern Sie die Funktionen in den Zellen nicht") -> 0
F13: =IFERROR(VLOOKUP(INDIRECT(ADDRESS(ROW(), COLUMN()-1)), 'Category Name'!$A:$B, 2, FALSE), "Bitte wählen Sie zunächst die [Kategorie] aus. Nach der Auswahl wird hier der vollständige Kategorienpfad angezeigt. Bitte ändern Sie die Funktionen in den Zellen nicht") -> 0
F14: =IFERROR(VLOOKUP(INDIRECT(ADDRESS(ROW(), COLUMN()-1)), 'Category Name'!$A:$B, 2, FALSE), "Bitte wählen Sie zunächst die [Kategorie] aus. Nach der Auswahl wird hier der vollständige Kategorienpfad angezeigt. Bitte ändern Sie die Funktionen in den Zellen nicht") -> 0
F15: =IFERROR(VLOOKUP(INDIRECT(ADDRESS(ROW(), COLUMN()-1)), 'Category Name'!$A:$B, 2, FALSE), "Bitte wählen Sie zunächst die [Kategorie] aus. Nach der Auswahl wird hier der vollständige Kategorienpfad angezeigt. Bitte ändern Sie die Funktionen in den Zellen nicht") -> 0
F16: =IFERROR(VLOOKUP(INDIRECT(ADDRESS(ROW(), COLUMN()-1)), 'Category Name'!$A:$B, 2, FALSE), "Bitte wählen Sie zunächst die [Kategorie] aus. Nach der Auswahl wird hier der vollständige Kategorienpfad angezeigt. Bitte ändern Sie die Funktionen in den Zellen nicht") -> 0
... F2000: =IFERROR(VLOOKUP(INDIRECT(ADDRESS(ROW(), COLUMN()-1)), 'Category Name'!$A:$B, 2, FALSE), "Bitte wählen Sie zunächst die [Kategorie] aus. Nach der Auswahl wird hier der vollständige Kategorienpfad angezeigt. Bitte ändern Sie die Funktionen in den Zellen nicht") -> 0

Sheet Dropdown Lists
A1: t_1_Kategorie | B1: t_7092566280593B3BB2C1334FFD87BB75 | C1: 21226 | D1: 21680 | E1: 21691 | F1: 21775 | G1: 21785 | H1: 21792 | I1: 21842 | J1: 21873 | K1: 21903 | L1: 22184 | M1: 22226 | N1: 22229
A2: t_1_Produkttyp | B2: t_EBE942180826316599849DBDC67BC840 | C2: Normales Produkt | D2: Kundenspezifisches Produkt
A3: t_1_Kundenspezifisches Produkt_Verarbeitungsverfahren zur Anpassung | B3: t_B57E8C7A770F35A0BB7753EC0D5DEE56 | C3: Einzelverfahren | D3: Kombinierte Verfahren
A4: t_1_Kundenspezifisches Produkt_Kombinierte Verfahren_Primärverfahren | B4: t_14F2526269293CCF896C9AED8757E81A | C4: Technik zur Anpassung von Metallprodukten | D4: Leder-/Stoff-Personalisierungstechnik | E4: Technik zur Anpassung von Holzprodukten | F4: Anpassungstechnik für organische Materialien (z. B. Acryl/Harz) | G4: Leinwand-/Papier-Anpassungstechnik
A5: t_1_Kundenspezifisches Produkt_Einzelverfahren_Primärverfahren | B5: t_12506A60C0C93D84978C908BCC35B3F8 | C5: Grundtechnik | D5: Technik zur Anpassung von Metallprodukten | E5: Leder-/Stoff-Personalisierungstechnik | F5: Technik zur Anpassung von Holzprodukten | G5: Anpassungstechnik für organische Materialien (z. B. Acryl/Harz) | H5: Leinwand-/Papier-Anpassungstechnik
A6: t_1_Kundenspezifisches Produkt_Einzelverfahren_Technik zur Anpassung von Holzprodukten_Sekundärverfahren | B6: t_8A82F0D250A131CB9678F7CD269E83CC | C6: Lasergravur - Text | D6: Lasergravur - Bilder | E6: Mechanische Gravur - Text | F6: Prägung
A7: t_1_Kundenspezifisches Produkt_Kombinierte Verfahren_Technik zur Anpassung von Metallprodukten_Sekundärverfahren | B7: t_CAFFECC57A233C6B8496E27E94BD00CB | C7: Lasergravur - Text | D7: Lasergravur - Bilder | E7: Mechanische Gravur - Text | F7: Prägung | G7: Schweißen | H7: UV | I7: Siebdruck - Text | J7: Siebdruck - Bild | K7: Sprühlackierung | L7: Weicher Emaille | M7: Laserschneiden - Text | N7: Laserschneiden - Bild | O7: Strass-Fassung | P7: Galvanisieren
A8: t_1_Kundenspezifisches Produkt_Einzelverfahren_Leder-/Stoff-Personalisierungstechnik_Sekundärverfahren | B8: t_D6AB99606DBC3456B889DB0B1F4983B5 | C8: Lasergravur - Text | D8: Lasergravur - Bilder | E8: UV | F8: Siebdruck - Text | G8: Siebdruck - Bild | H8: Weicher Emaille | I8: Epoxy - Text | J8: Epoxidharz - Bilder | K8: Heißprägung - Text | L8: Heißprägung - Bild | M8: Blechprägung | N8: Thermotransferdruck - Text | O8: Thermotransferdruck - Bild | P8: Stickerei | Q8: Beflockung | R8: Thermopressendruck – Text | S8: Wärmepressendruck - Bild | T8: Digitaldruck | U8: Prägung | V8: Webmuster - Klebepatch
A9: t_1_Kundenspezifisches Produkt_Einzelverfahren_Anpassungstechnik für organische Materialien (z. B. Acryl/Harz)_Sekundärverfahren | B9: t_1E1124B7FC7B3954A750E25A69DB0658 | C9: Lasergravur - Text | D9: Lasergravur - Bilder | E9: Mechanische Gravur - Text | F9: Prägung | G9: UV | H9: Siebdruck - Text | I9: Siebdruck - Bild | J9: Laserschneiden - Text | K9: Laserschneiden - Bild | L9: Handgemalte Nagelkunst
A10: t_1_Kundenspezifisches Produkt_Kombinierte Verfahren_Technik zur Anpassung von Holzprodukten_Sekundärverfahren | B10: t_051693175F4C3966A32680C3E926669D | C10: Lasergravur - Text | D10: Lasergravur - Bilder | E10: Mechanische Gravur - Text | F10: Prägung
A11: t_1_Kundenspezifisches Produkt_Kombinierte Verfahren_Leder-/Stoff-Personalisierungstechnik_Sekundärverfahren | B11: t_8D7DCDFB1275340BB941677042807F6D | C11: Lasergravur - Text | D11: Lasergravur - Bilder | E11: UV | F11: Siebdruck - Text | G11: Siebdruck - Bild | H11: Weicher Emaille | I11: Heißprägung - Text | J11: Heißprägung - Bild | K11: Prägung
A12: t_1_Kundenspezifisches Produkt_Kombinierte Verfahren_Anpassungstechnik für organische Materialien (z. B. Acryl/Harz)_Sekundärverfahren | B12: t_918E40D3EBF332149A0D44DF1196300A | C12: Lasergravur - Text | D12: Lasergravur - Bilder | E12: Mechanische Gravur - Text | F12: Prägung | G12: UV | H12: Siebdruck - Text | I12: Siebdruck - Bild | J12: Laserschneiden - Text | K12: Laserschneiden - Bild
A13: t_1_Kundenspezifisches Produkt_Einzelverfahren_Technik zur Anpassung von Metallprodukten_Sekundärverfahren | B13: t_B828B691B56D3478B51C1F1C2D71B611 | C13: Lasergravur - Text | D13: Lasergravur - Bilder | E13: Mechanische Gravur - Text | F13: Prägung | G13: Schweißen | H13: Radierung | I13: UV | J13: Siebdruck - Text | K13: Siebdruck - Bild | L13: Sprühlackierung | M13: Weicher Emaille | N13: Epoxy - Text | O13: Epoxidharz - Bilder | P13: Laserschneiden - Text | Q13: Laserschneiden - Bild | R13: Strass-Fassung | S13: Galvanisieren
A14: t_1_Kundenspezifisches Produkt_Kombinierte Verfahren_Leinwand-/Papier-Anpassungstechnik_Sekundärverfahren | B14: t_967ABFFF1F2A3DF9AD8906E53C9D7D59 | C14: Siebdruck - Text | D14: Siebdruck - Bild | E14: Heißprägung - Text | F14: Heißprägung - Bild | G14: Prägung
A15: t_1_Kundenspezifisches Produkt_Einzelverfahren_Leinwand-/Papier-Anpassungstechnik_Sekundärverfahren | B15: t_D959B5776CF4385C84E15E547C8B411C | C15: Handmalerei - Skizze | D15: Handmalerei - Aquarell | E15: Handmalerei - Ölmalerei | F15: Handmalerei - Druckgrafik | G15: Handbemalung - Comic | H15: Prägung
A16: t_1_Aktualisieren oder hinzufügen | B16: t_96546FBB0668356C839991263B8C6D21 | C16: Aktualisieren/Neu hinzufügen | D16: PartialUpdate | E16: Hinzufügen
A17: t_1_Marke | B17: t_DA27226285E53EEF9D162B1EF4365EE2 | C17: GOINGFAST
A18: t_1_GOINGFAST_Markenzeichen | B18: t_A27F3AA7885C3505852C3B301309B57B | C18: goingfast
A19: t_3_21680_1920 - Hauptmaterial | B19: t_3773E4160E40388BA98ED300101B52CD | C19: Leinen | D19: Seide | E19: Lycra (Spandex) | F19: PU-Leder | G19: Baumwolle | H19: Polyamid | I19: Silikon | J19: Wolle | K19: Eisen | L19: Kupfer | M19: PET | N19: Aluminiumlegierung | O19: Edelstahl | P19: Aluminium | Q19: Keramik | R19: Kork | S19: Glas | T19: Stahl | U19: Ton | V19: Kunstpelz | W19: PVC | X19: Kohlenstoffstahl | Y19: Papier | Z19: Bambus | AA19: PC | AB19: Synthesekautschuk | AC19: ABS | AD19: PP | AE19: EVA | AF19: PE (Polyethylen) | AG19: Gehärtetes Glas | AH19: Sonstige | AI19: Rattan | AJ19: Diamant | AK19: Polyester (Polyesterfaser) | AL19: Titanlegierung | AM19: Acryl | AN19: Kohlefaser | AO19: Natürliches Gummi | AP19: Fiberglas | AQ19: Schilf | AR19: Echt | AS19: Natürliche Feder | AT19: Naturstein | AU19: Pappe | AV19: Kunstleder | AW19: Acryl (PMMA) | AX19: Rohholz | AY19: Holzfaserplatte | AZ19: Sperrholz | BA19: Laminat | BB19: Anderer Kunststoff | BC19: Recycelter Gummi | BD19: Vulkanisierter Gummi | BE19: Schwammgummi | BF19: Hartes Gummi | BG19: Anderer Gummi | BH19: Anderes Holz | BI19: Hergestellt aus anderen Pflanzenmaterialien | BJ19: Andere Metallmaterialien | BK19: Gips | BL19: Anderes Glas | BM19: Andere Papierprodukte | BN19: Acrylfaser (Polyacrylnitrilfaser) | BO19: Vinylon (Polyvinylformalfaser) | BP19: Polyvinylchlorid (Polyvinylchloridfaser) | BQ19: Andere Textilmaterialien | BR19: TPU (Thermoplastisches Polyurethan) | BS19: Gefährdetes Holz | BT19: Natürliche Blumen, Blätter, Früchte | BU19: Künstliche Blumen, Blätter und Früchte | BV19: Zinklegierung | BW19: Zink | BX19: Kupferlegierung | BY19: Magnesiumlegierung
A20: t_3_22229_1920 - Hauptmaterial | B20: t_8814DB9E78153D73A2DE4EFFFCEF1256 | C20: Leinen | D20: Seide | E20: Lycra (Spandex) | F20: PU-Leder | G20: Baumwolle | H20: Polyamid | I20: Silikon | J20: Wolle | K20: Eisen | L20: Kupfer | M20: PET | N20: Aluminiumlegierung | O20: Edelstahl | P20: Aluminium | Q20: Keramik | R20: Kork | S20: Glas | T20: Stahl | U20: Ton | V20: Kunstpelz | W20: PVC | X20: Kohlenstoffstahl | Y20: Papier | Z20: Bambus | AA20: PC | AB20: Synthesekautschuk | AC20: ABS | AD20: PP | AE20: EVA | AF20: PE (Polyethylen) | AG20: Gehärtetes Glas | AH20: Sonstige | AI20: Rattan | AJ20: Diamant | AK20: Polyester (Polyesterfaser) | AL20: Titanlegierung | AM20: Acryl | AN20: Kohlefaser | AO20: Natürliches Gummi | AP20: Fiberglas | AQ20: Schilf | AR20: Echt | AS20: Naturstein | AT20: Pappe | AU20: Kunstleder | AV20: Acryl (PMMA) | AW20: Rohholz | AX20: Holzfaserplatte | AY20: Sperrholz | AZ20: Laminat | BA20: Anderer Kunststoff | BB20: Recycelter Gummi | BC20: Vulkanisierter Gummi | BD20: Schwammgummi | BE20: Hartes Gummi | BF20: Anderer Gummi | BG20: Anderes Holz | BH20: Hergestellt aus anderen Pflanzenmaterialien | BI20: Andere Metallmaterialien | BJ20: Gips | BK20: Anderes Glas | BL20: Andere Papierprodukte | BM20: Acrylfaser (Polyacrylnitrilfaser) | BN20: Vinylon (Polyvinylformalfaser) | BO20: Polyvinylchlorid (Polyvinylchloridfaser) | BP20: Andere Textilmaterialien | BQ20: TPU (Thermoplastisches Polyurethan) | BR20: Gefährdetes Holz | BS20: Natürliche Feder | BT20: Natürliche Blumen, Blätter, Früchte | BU20: Künstliche Blumen, Blätter und Früchte
A21: t_3_21785_1920 - Hauptmaterial | B21: t_D166DE0F832B3D4689BF54F4F9DD5454 | C21: Leinen | D21: Seide | E21: Lycra (Spandex) | F21: PU-Leder | G21: Baumwolle | H21: Polyamid | I21: Silikon | J21: Wolle | K21: Eisen | L21: Kupfer | M21: PET | N21: Aluminiumlegierung | O21: Edelstahl | P21: Aluminium | Q21: Keramik | R21: Kork | S21: Glas | T21: Stahl | U21: Ton | V21: Kunstpelz | W21: PVC | X21: Kohlenstoffstahl | Y21: Papier | Z21: Bambus | AA21: PC | AB21: Synthesekautschuk | AC21: ABS | AD21: PP | AE21: EVA | AF21: PE (Polyethylen) | AG21: Gehärtetes Glas | AH21: Sonstige | AI21: Rattan | AJ21: Diamant | AK21: Polyester (Polyesterfaser) | AL21: Titanlegierung | AM21: Acryl | AN21: Kohlefaser | AO21: Natürliches Gummi | AP21: Fiberglas | AQ21: Schilf | AR21: Echt | AS21: Natürliche Feder | AT21: Naturstein | AU21: Pappe | AV21: Kunstleder | AW21: Acryl (PMMA) | AX21: Rohholz | AY21: Holzfaserplatte | AZ21: Sperrholz | BA21: Laminat | BB21: Anderer Kunststoff | BC21: Recycelter Gummi | BD21: Vulkanisierter Gummi | BE21: Schwammgummi | BF21: Hartes Gummi | BG21: Anderer Gummi | BH21: Anderes Holz | BI21: Hergestellt aus anderen Pflanzenmaterialien | BJ21: Andere Metallmaterialien | BK21: Gips | BL21: Anderes Glas | BM21: Andere Papierprodukte | BN21: Acrylfaser (Polyacrylnitrilfaser) | BO21: Vinylon (Polyvinylformalfaser) | BP21: Polyvinylchlorid (Polyvinylchloridfaser) | BQ21: Andere Textilmaterialien | BR21: TPU (Thermoplastisches Polyurethan) | BS21: Gefährdetes Holz | BT21: Natürliche Blumen, Blätter, Früchte | BU21: Künstliche Blumen, Blätter und Früchte | BV21: Zinklegierung | BW21: Zink | BX21: Kupferlegierung | BY21: Magnesiumlegierung
A22: t_3_21775_1920 - Hauptmaterial | B22: t_A20C14220EF237158FD9CCA8C686F5B6 | C22: Leinen | D22: Seide | E22: Lycra (Spandex) | F22: PU-Leder | G22: Baumwolle | H22: Polyamid | I22: Silikon | J22: Wolle | K22: Eisen | L22: Kupfer | M22: PET | N22: Aluminiumlegierung | O22: Edelstahl | P22: Aluminium | Q22: Keramik | R22: Kork | S22: Glas | T22: Stahl | U22: Ton | V22: Kunstpelz | W22: PVC | X22: Kohlenstoffstahl | Y22: Papier | Z22: Bambus | AA22: PC | AB22: Synthesekautschuk | AC22: ABS | AD22: PP | AE22: EVA | AF22: PE (Polyethylen) | AG22: Gehärtetes Glas | AH22: Sonstige | AI22: Rattan | AJ22: Diamant | AK22: Polyester (Polyesterfaser) | AL22: Titanlegierung | AM22: Acryl | AN22: Kohlefaser | AO22: Natürliches Gummi | AP22: Fiberglas | AQ22: Schilf | AR22: Echt | AS22: Natürliche Feder | AT22: Naturstein | AU22: Pappe | AV22: Kunstleder | AW22: Acryl (PMMA) | AX22: Rohholz | AY22: Holzfaserplatte | AZ22: Sperrholz | BA22: Laminat | BB22: Anderer Kunststoff | BC22: Recycelter Gummi | BD22: Vulkanisierter Gummi | BE22: Schwammgummi | BF22: Hartes Gummi | BG22: Anderer Gummi | BH22: Anderes Holz | BI22: Hergestellt aus anderen Pflanzenmaterialien | BJ22: Andere Metallmaterialien | BK22: Gips | BL22: Anderes Glas | BM22: Andere Papierprodukte | BN22: Acrylfaser (Polyacrylnitrilfaser) | BO22: Vinylon (Polyvinylformalfaser) | BP22: Polyvinylchlorid (Polyvinylchloridfaser) | BQ22: Andere Textilmaterialien | BR22: TPU (Thermoplastisches Polyurethan) | BS22: Gefährdetes Holz | BT22: Natürliche Blumen, Blätter, Früchte | BU22: Künstliche Blumen, Blätter und Früchte | BV22: Zinklegierung | BW22: Zink | BX22: Kupferlegierung | BY22: Magnesiumlegierung
A23: t_3_21775_Echt_4109 - Echte Ledersorte | B23: t_F98DCB3AE762307DA38D7F30833DF73F | C23: Andere Tierhäute | D23: Schaffell | E23: Wildleder | F23: Schweinsleder | G23: Rindsleder | H23: Pferdeleder
A24: t_3_22229_Echt_4109 - Echte Ledersorte | B24: t_C01086A5CDC33871996916645423B4C8 | C24: Andere Tierhäute | D24: Schaffell | E24: Wildleder | F24: Schweinsleder | G24: Rindsleder | H24: Pferdeleder
A25: t_3_21785_Echt_4109 - Echte Ledersorte | B25: t_1DEB50D24B7633DEB568D46CD0DEE18A | C25: Andere Tierhäute | D25: Schaffell | E25: Wildleder | F25: Schweinsleder | G25: Rindsleder | H25: Pferdeleder
A26: t_3_21680_Echt_4109 - Echte Ledersorte | B26: t_10B93B27AE6432F7A309E668D2CC9EDD | C26: Andere Tierhäute | D26: Schaffell | E26: Wildleder | F26: Schweinsleder | G26: Rindsleder | H26: Pferdeleder
A27: t_3_21775_Rohholz_7317 - Holzart | B27: t_7BF920BAC1E832CBA736C384387E7A64 | C27: Verbundholz | D27: Protokoll
A28: t_3_21680_Gefährdetes Holz_7317 - Holzart | B28: t_1A4E538CD7F63317BF625E62EEEBBC3D | C28: Verbundholz | D28: Protokoll
A29: t_3_21775_Holzfaserplatte_7317 - Holzart | B29: t_D8E40E3C11163CDE8776515BCDB9008B | C29: Verbundholz | D29: Protokoll
A30: t_3_21785_Kork_7317 - Holzart | B30: t_E18D138B932938D2B244867CB5CA5F8D | C30: Verbundholz | D30: Protokoll
A31: t_3_21785_Gefährdetes Holz_7317 - Holzart | B31: t_2641CB45323E330DA4A86DBF28925232 | C31: Verbundholz | D31: Protokoll
A32: t_3_21775_Gefährdetes Holz_7317 - Holzart | B32: t_5902DC47A34934A6B275A7ABB0F18706 | C32: Verbundholz | D32: Protokoll
A33: t_3_22229_Hergestellt aus anderen Pflanzenmaterialien_7317 - Holzart | B33: t_A8996EFB19463551AD2FD78E6CFFFA06 | C33: Verbundholz | D33: Protokoll
A34: t_3_22229_Gefährdetes Holz_7317 - Holzart | B34: t_E412CE876AE93AD5AC0D5C1480E444C3 | C34: Verbundholz | D34: Protokoll
A35: t_3_21680_Rohholz_7317 - Holzart | B35: t_8ED06C1BC7523579B7FCB86101DC9F37 | C35: Verbundholz | D35: Protokoll
A36: t_3_21785_Rohholz_7317 - Holzart | B36: t_261CDA0339713BDD94255721F6AC1E98 | C36: Verbundholz | D36: Protokoll
A37: t_3_21785_Holzfaserplatte_7317 - Holzart | B37: t_5A6FEE3097733D8EBA56B406A1BFEBF3 | C37: Verbundholz | D37: Protokoll
A38: t_3_21680_Hergestellt aus anderen Pflanzenmaterialien_7317 - Holzart | B38: t_8CB41F7CB92D3DE09250B594F82216BC | C38: Verbundholz | D38: Protokoll
... A54: t_3_21775_Anderes Holz_7317 - Holzart | B54: t_F3F0BCE81CAE3DA08E421109EEFE4D3E | C54: Verbundholz | D54: Protokoll
A55: t_3_21785_Holzfaserplatte_Protokoll_7318 - Holzarten | B55: t_0B6A9C9F1908395D95B606E715119DED | C55: Dipentodon sinicus | D55: Neocheiropteris palmatopedata | E55: Pennisetum sichuanense | F55: Larix mastersiana | G55: Acidosasa chinensis | H55: Diospyros celebica | I55: Dicksonia antarctica | J55: Larix chinensis | K55: Keteleeria davidiana var. formosana | L55: Cassia siamea | M55: Dipterocarpus conformis | N55: Camptotheca acuminata | O55: Amomum subulatum | P55: Amphicarpaea linearis | Q55: Plectocomia microstachys | R55: Cistanche salsa | S55: Betula halophila | T55: Euphorbia pulcherrima | U55: Anisachne gracilis | V55: Mussaenda anomala | W55: Cinnamomum mairei | X55: Picea brachytyla var. complanata | Y55: Sorolepidium glaciale | Z55: Pterocarpus cambodianus | AA55: Cinnamomum camphora | AB55: Cinnamomum glanduliferum | AC55: Changiostyrax dolichocarpa | AD55: Sinopteris grevilleoides | AE55: Erisma uncinatum | AF55: Skapanthus oreophilus | AG55: Chosenia arbutifolia | AH55: Pterocarpus indicus | AI55: Amomum testaceum | AJ55: Pterocarpus dalbergioides | AK55: Semiliquidambar cathayensis | AL55: Millettia leucantha | AM55: Sinojackia xylocarpa | AN55: Amoora dasyclada | AO55: Aloe vera | AP55: Dipterocarpus grandiflorus | AQ55: Pterocarpus macrocarpus | AR55: Cyrtomium hemionitis | AS55: Metabriggsia ovalifolia | AT55: Trailliaedoxa gracilis | AU55: Elymus breviaristatus | AV55: Tilia tuan | AW55: Diospyros philippensis | AX55: Millettia laurentii | AY55: Dichocarpum hypoglaucum | AZ55: Nuphar bornetii | BA55: Archangiopteris henryi | BB55: Diospyros crassiflora | BC55: Khaya ivorensis | BD55: Pseudotsuga menziesii | BE55: Ajaniopsis penicilliformis | BF55: Betula jinpingensis | BG55: Dipterocarpus cornutus | BH55: Zelkova schneideriana | BI55: Rhoiptelea chiliantha | BJ55: Diospyros pilosanthera | BK55: Pterocarpus marsupium | BL55: Fagus sylvatica | BM55: Pterocarpus pedatus | BN55: Najas pseudogracillima | BO55: Diospyros poncej | BP55: Torreya nucifera | BQ55: Zenia insignis | BR55: Myristica Fragrans | BS55: Anisodus tanguticus
A56: t_3_22229_Anderes Holz_Protokoll_7318 - Holzarten | B56: t_0815AE15C0663BAE95DDDC17B942AA0E | C56: Dipentodon sinicus | D56: Neocheiropteris palmatopedata | E56: Pennisetum sichuanense | F56: Larix mastersiana | G56: Acidosasa chinensis | H56: Diospyros celebica | I56: Dicksonia antarctica | J56: Larix chinensis | K56: Keteleeria davidiana var. formosana | L56: Cassia siamea | M56: Dipterocarpus conformis | N56: Camptotheca acuminata | O56: Amomum subulatum | P56: Amphicarpaea linearis | Q56: Plectocomia microstachys | R56: Cistanche salsa | S56: Betula halophila | T56: Euphorbia pulcherrima | U56: Anisachne gracilis | V56: Mussaenda anomala | W56: Cinnamomum mairei | X56: Picea brachytyla var. complanata | Y56: Sorolepidium glaciale | Z56: Pterocarpus cambodianus | AA56: Cinnamomum camphora | AB56: Cinnamomum glanduliferum | AC56: Changiostyrax dolichocarpa | AD56: Sinopteris grevilleoides | AE56: Erisma uncinatum | AF56: Skapanthus oreophilus | AG56: Chosenia arbutifolia | AH56: Pterocarpus indicus | AI56: Amomum testaceum | AJ56: Pterocarpus dalbergioides | AK56: Semiliquidambar cathayensis | AL56: Millettia leucantha | AM56: Sinojackia xylocarpa | AN56: Amoora dasyclada | AO56: Aloe vera | AP56: Dipterocarpus grandiflorus | AQ56: Pterocarpus macrocarpus | AR56: Cyrtomium hemionitis | AS56: Metabriggsia ovalifolia | AT56: Trailliaedoxa gracilis | AU56: Elymus breviaristatus | AV56: Tilia tuan | AW56: Diospyros philippensis | AX56: Millettia laurentii | AY56: Dichocarpum hypoglaucum | AZ56: Nuphar bornetii | BA56: Archangiopteris henryi | BB56: Diospyros crassiflora | BC56: Khaya ivorensis | BD56: Pseudotsuga menziesii | BE56: Ajaniopsis penicilliformis | BF56: Betula jinpingensis | BG56: Dipterocarpus cornutus | BH56: Zelkova schneideriana | BI56: Rhoiptelea chiliantha | BJ56: Diospyros pilosanthera | BK56: Pterocarpus marsupium | BL56: Fagus sylvatica | BM56: Pterocarpus pedatus | BN56: Najas pseudogracillima | BO56: Diospyros poncej | BP56: Torreya nucifera | BQ56: Zenia insignis | BR56: Myristica Fragrans | BS56: Anisodus tanguticus
A57: t_3_22229_Rohholz_Protokoll_7318 - Holzarten | B57: t_2176EB6E9ECC38E99443FCEA3B6EAFFB | C57: Dipentodon sinicus | D57: Neocheiropteris palmatopedata | E57: Pennisetum sichuanense | F57: Larix mastersiana | G57: Acidosasa chinensis | H57: Diospyros celebica | I57: Dicksonia antarctica | J57: Larix chinensis | K57: Keteleeria davidiana var. formosana | L57: Cassia siamea | M57: Dipterocarpus conformis | N57: Camptotheca acuminata | O57: Amomum subulatum | P57: Amphicarpaea linearis | Q57: Plectocomia microstachys | R57: Cistanche salsa | S57: Betula halophila | T57: Euphorbia pulcherrima | U57: Anisachne gracilis | V57: Mussaenda anomala | W57: Cinnamomum mairei | X57: Picea brachytyla var. complanata | Y57: Sorolepidium glaciale | Z57: Pterocarpus cambodianus | AA57: Cinnamomum camphora | AB57: Cinnamomum glanduliferum | AC57: Changiostyrax dolichocarpa | AD57: Sinopteris grevilleoides | AE57: Erisma uncinatum | AF57: Skapanthus oreophilus | AG57: Chosenia arbutifolia | AH57: Pterocarpus indicus | AI57: Amomum testaceum | AJ57: Pterocarpus dalbergioides | AK57: Semiliquidambar cathayensis | AL57: Millettia leucantha | AM57: Sinojackia xylocarpa | AN57: Amoora dasyclada | AO57: Aloe vera | AP57: Dipterocarpus grandiflorus | AQ57: Pterocarpus macrocarpus | AR57: Cyrtomium hemionitis | AS57: Metabriggsia ovalifolia | AT57: Trailliaedoxa gracilis | AU57: Elymus breviaristatus | AV57: Tilia tuan | AW57: Diospyros philippensis | AX57: Millettia laurentii | AY57: Dichocarpum hypoglaucum | AZ57: Nuphar bornetii | BA57: Archangiopteris henryi | BB57: Diospyros crassiflora | BC57: Khaya ivorensis | BD57: Pseudotsuga menziesii | BE57: Ajaniopsis penicilliformis | BF57: Betula jinpingensis | BG57: Dipterocarpus cornutus | BH57: Zelkova schneideriana | BI57: Rhoiptelea chiliantha | BJ57: Diospyros pilosanthera | BK57: Pterocarpus marsupium | BL57: Fagus sylvatica | BM57: Pterocarpus pedatus | BN57: Najas pseudogracillima | BO57: Diospyros poncej | BP57: Torreya nucifera | BQ57: Zenia insignis | BR57: Myristica Fragrans | BS57: Anisodus tanguticus
A58: t_3_21785_Rohholz_Protokoll_7318 - Holzarten | B58: t_56720A2F7E653636BA1E4305A9628763 | C58: Dipentodon sinicus | D58: Neocheiropteris palmatopedata | E58: Pennisetum sichuanense | F58: Larix mastersiana | G58: Acidosasa chinensis | H58: Diospyros celebica | I58: Dicksonia antarctica | J58: Larix chinensis | K58: Keteleeria davidiana var. formosana | L58: Cassia siamea | M58: Dipterocarpus conformis | N58: Camptotheca acuminata | O58: Amomum subulatum | P58: Amphicarpaea linearis | Q58: Plectocomia microstachys | R58: Cistanche salsa | S58: Betula halophila | T58: Euphorbia pulcherrima | U58: Anisachne gracilis | V58: Mussaenda anomala | W58: Cinnamomum mairei | X58: Picea brachytyla var. complanata | Y58: Sorolepidium glaciale | Z58: Pterocarpus cambodianus | AA58: Cinnamomum camphora | AB58: Cinnamomum glanduliferum | AC58: Changiostyrax dolichocarpa | AD58: Sinopteris grevilleoides | AE58: Erisma uncinatum | AF58: Skapanthus oreophilus | AG58: Chosenia arbutifolia | AH58: Pterocarpus indicus | AI58: Amomum testaceum | AJ58: Pterocarpus dalbergioides | AK58: Semiliquidambar cathayensis | AL58: Millettia leucantha | AM58: Sinojackia xylocarpa | AN58: Amoora dasyclada | AO58: Aloe vera | AP58: Dipterocarpus grandiflorus | AQ58: Pterocarpus macrocarpus | AR58: Cyrtomium hemionitis | AS58: Metabriggsia ovalifolia | AT58: Trailliaedoxa gracilis | AU58: Elymus breviaristatus | AV58: Tilia tuan | AW58: Diospyros philippensis | AX58: Millettia laurentii | AY58: Dichocarpum hypoglaucum | AZ58: Nuphar bornetii | BA58: Archangiopteris henryi | BB58: Diospyros crassiflora | BC58: Khaya ivorensis | BD58: Pseudotsuga menziesii | BE58: Ajaniopsis penicilliformis | BF58: Betula jinpingensis | BG58: Dipterocarpus cornutus | BH58: Zelkova schneideriana | BI58: Rhoiptelea chiliantha | BJ58: Diospyros pilosanthera | BK58: Pterocarpus marsupium | BL58: Fagus sylvatica | BM58: Pterocarpus pedatus | BN58: Najas pseudogracillima | BO58: Diospyros poncej | BP58: Torreya nucifera | BQ58: Zenia insignis | BR58: Myristica Fragrans | BS58: Anisodus tanguticus
A59: t_3_21785_Laminat_Protokoll_7318 - Holzarten | B59: t_D097CE9D29693045AE3A663CF490EEC0 | C59: Dipentodon sinicus | D59: Neocheiropteris palmatopedata | E59: Pennisetum sichuanense | F59: Larix mastersiana | G59: Acidosasa chinensis | H59: Diospyros celebica | I59: Dicksonia antarctica | J59: Larix chinensis | K59: Keteleeria davidiana var. formosana | L59: Cassia siamea | M59: Dipterocarpus conformis | N59: Camptotheca acuminata | O59: Amomum subulatum | P59: Amphicarpaea linearis | Q59: Plectocomia microstachys | R59: Cistanche salsa | S59: Betula halophila | T59: Euphorbia pulcherrima | U59: Anisachne gracilis | V59: Mussaenda anomala | W59: Cinnamomum mairei | X59: Picea brachytyla var. complanata | Y59: Sorolepidium glaciale | Z59: Pterocarpus cambodianus | AA59: Cinnamomum camphora | AB59: Cinnamomum glanduliferum | AC59: Changiostyrax dolichocarpa | AD59: Sinopteris grevilleoides | AE59: Erisma uncinatum | AF59: Skapanthus oreophilus | AG59: Chosenia arbutifolia | AH59: Pterocarpus indicus | AI59: Amomum testaceum | AJ59: Pterocarpus dalbergioides | AK59: Semiliquidambar cathayensis | AL59: Millettia leucantha | AM59: Sinojackia xylocarpa | AN59: Amoora dasyclada | AO59: Aloe vera | AP59: Dipterocarpus grandiflorus | AQ59: Pterocarpus macrocarpus | AR59: Cyrtomium hemionitis | AS59: Metabriggsia ovalifolia | AT59: Trailliaedoxa gracilis | AU59: Elymus breviaristatus | AV59: Tilia tuan | AW59: Diospyros philippensis | AX59: Millettia laurentii | AY59: Dichocarpum hypoglaucum | AZ59: Nuphar bornetii | BA59: Archangiopteris henryi | BB59: Diospyros crassiflora | BC59: Khaya ivorensis | BD59: Pseudotsuga menziesii | BE59: Ajaniopsis penicilliformis | BF59: Betula jinpingensis | BG59: Dipterocarpus cornutus | BH59: Zelkova schneideriana | BI59: Rhoiptelea chiliantha | BJ59: Diospyros pilosanthera | BK59: Pterocarpus marsupium | BL59: Fagus sylvatica | BM59: Pterocarpus pedatus | BN59: Najas pseudogracillima | BO59: Diospyros poncej | BP59: Torreya nucifera | BQ59: Zenia insignis | BR59: Myristica Fragrans | BS59: Anisodus tanguticus
A60: t_3_21775_Gefährdetes Holz_Protokoll_7318 - Holzarten | B60: t_77B205B7C3DD3B1BBEF38D3B352A8D84 | C60: Dipentodon sinicus | D60: Neocheiropteris palmatopedata | E60: Pennisetum sichuanense | F60: Larix mastersiana | G60: Acidosasa chinensis | H60: Diospyros celebica | I60: Dicksonia antarctica | J60: Larix chinensis | K60: Keteleeria davidiana var. formosana | L60: Cassia siamea | M60: Dipterocarpus conformis | N60: Camptotheca acuminata | O60: Amomum subulatum | P60: Amphicarpaea linearis | Q60: Plectocomia microstachys | R60: Cistanche salsa | S60: Betula halophila | T60: Euphorbia pulcherrima | U60: Anisachne gracilis | V60: Mussaenda anomala | W60: Cinnamomum mairei | X60: Picea brachytyla var. complanata | Y60: Sorolepidium glaciale | Z60: Pterocarpus cambodianus | AA60: Cinnamomum camphora | AB60: Cinnamomum glanduliferum | AC60: Changiostyrax dolichocarpa | AD60: Sinopteris grevilleoides | AE60: Erisma uncinatum | AF60: Skapanthus oreophilus | AG60: Chosenia arbutifolia | AH60: Pterocarpus indicus | AI60: Amomum testaceum | AJ60: Pterocarpus dalbergioides | AK60: Semiliquidambar cathayensis | AL60: Millettia leucantha | AM60: Sinojackia xylocarpa | AN60: Amoora dasyclada | AO60: Aloe vera | AP60: Dipterocarpus grandiflorus | AQ60: Pterocarpus macrocarpus | AR60: Cyrtomium hemionitis | AS60: Metabriggsia ovalifolia | AT60: Trailliaedoxa gracilis | AU60: Elymus breviaristatus | AV60: Tilia tuan | AW60: Diospyros philippensis | AX60: Millettia laurentii | AY60: Dichocarpum hypoglaucum | AZ60: Nuphar bornetii | BA60: Archangiopteris henryi | BB60: Diospyros crassiflora | BC60: Khaya ivorensis | BD60: Pseudotsuga menziesii | BE60: Ajaniopsis penicilliformis | BF60: Betula jinpingensis | BG60: Dipterocarpus cornutus | BH60: Zelkova schneideriana | BI60: Rhoiptelea chiliantha | BJ60: Diospyros pilosanthera | BK60: Pterocarpus marsupium | BL60: Fagus sylvatica | BM60: Pterocarpus pedatus | BN60: Najas pseudogracillima | BO60: Diospyros poncej | BP60: Torreya nucifera | BQ60: Zenia insignis | BR60: Myristica Fragrans | BS60: Anisodus tanguticus
A61: t_3_21680_Gefährdetes Holz_Protokoll_7318 - Holzarten | B61: t_91C48261679E3626A507C855F7F40D75 | C61: Dipentodon sinicus | D61: Neocheiropteris palmatopedata | E61: Pennisetum sichuanense | F61: Larix mastersiana | G61: Acidosasa chinensis | H61: Diospyros celebica | I61: Dicksonia antarctica | J61: Larix chinensis | K61: Keteleeria davidiana var. formosana | L61: Cassia siamea | M61: Dipterocarpus conformis | N61: Camptotheca acuminata | O61: Amomum subulatum | P61: Amphicarpaea linearis | Q61: Plectocomia microstachys | R61: Cistanche salsa | S61: Betula halophila | T61: Euphorbia pulcherrima | U61: Anisachne gracilis | V61: Mussaenda anomala | W61: Cinnamomum mairei | X61: Picea brachytyla var. complanata | Y61: Sorolepidium glaciale | Z61: Pterocarpus cambodianus | AA61: Cinnamomum camphora | AB61: Cinnamomum glanduliferum | AC61: Changiostyrax dolichocarpa | AD61: Sinopteris grevilleoides | AE61: Erisma uncinatum | AF61: Skapanthus oreophilus | AG61: Chosenia arbutifolia | AH61: Pterocarpus indicus | AI61: Amomum testaceum | AJ61: Pterocarpus dalbergioides | AK61: Semiliquidambar cathayensis | AL61: Millettia leucantha | AM61: Sinojackia xylocarpa | AN61: Amoora dasyclada | AO61: Aloe vera | AP61: Dipterocarpus grandiflorus | AQ61: Pterocarpus macrocarpus | AR61: Cyrtomium hemionitis | AS61: Metabriggsia ovalifolia | AT61: Trailliaedoxa gracilis | AU61: Elymus breviaristatus | AV61: Tilia tuan | AW61: Diospyros philippensis | AX61: Millettia laurentii | AY61: Dichocarpum hypoglaucum | AZ61: Nuphar bornetii | BA61: Archangiopteris henryi | BB61: Diospyros crassiflora | BC61: Khaya ivorensis | BD61: Pseudotsuga menziesii | BE61: Ajaniopsis penicilliformis | BF61: Betula jinpingensis | BG61: Dipterocarpus cornutus | BH61: Zelkova schneideriana | BI61: Rhoiptelea chiliantha | BJ61: Diospyros pilosanthera | BK61: Pterocarpus marsupium | BL61: Fagus sylvatica | BM61: Pterocarpus pedatus | BN61: Najas pseudogracillima | BO61: Diospyros poncej | BP61: Torreya nucifera | BQ61: Zenia insignis | BR61: Myristica Fragrans | BS61: Anisodus tanguticus
A62: t_3_21680_Laminat_Protokoll_7318 - Holzarten | B62: t_0CFB49832B75321C9D0CA49D009E865F | C62: Dipentodon sinicus | D62: Neocheiropteris palmatopedata | E62: Pennisetum sichuanense | F62: Larix mastersiana | G62: Acidosasa chinensis | H62: Diospyros celebica | I62: Dicksonia antarctica | J62: Larix chinensis | K62: Keteleeria davidiana var. formosana | L62: Cassia siamea | M62: Dipterocarpus conformis | N62: Camptotheca acuminata | O62: Amomum subulatum | P62: Amphicarpaea linearis | Q62: Plectocomia microstachys | R62: Cistanche salsa | S62: Betula halophila | T62: Euphorbia pulcherrima | U62: Anisachne gracilis | V62: Mussaenda anomala | W62: Cinnamomum mairei | X62: Picea brachytyla var. complanata | Y62: Sorolepidium glaciale | Z62: Pterocarpus cambodianus | AA62: Cinnamomum camphora | AB62: Cinnamomum glanduliferum | AC62: Changiostyrax dolichocarpa | AD62: Sinopteris grevilleoides | AE62: Erisma uncinatum | AF62: Skapanthus oreophilus | AG62: Chosenia arbutifolia | AH62: Pterocarpus indicus | AI62: Amomum testaceum | AJ62: Pterocarpus dalbergioides | AK62: Semiliquidambar cathayensis | AL62: Millettia leucantha | AM62: Sinojackia xylocarpa | AN62: Amoora dasyclada | AO62: Aloe vera | AP62: Dipterocarpus grandiflorus | AQ62: Pterocarpus macrocarpus | AR62: Cyrtomium hemionitis | AS62: Metabriggsia ovalifolia | AT62: Trailliaedoxa gracilis | AU62: Elymus breviaristatus | AV62: Tilia tuan | AW62: Diospyros philippensis | AX62: Millettia laurentii | AY62: Dichocarpum hypoglaucum | AZ62: Nuphar bornetii | BA62: Archangiopteris henryi | BB62: Diospyros crassiflora | BC62: Khaya ivorensis | BD62: Pseudotsuga menziesii | BE62: Ajaniopsis penicilliformis | BF62: Betula jinpingensis | BG62: Dipterocarpus cornutus | BH62: Zelkova schneideriana | BI62: Rhoiptelea chiliantha | BJ62: Diospyros pilosanthera | BK62: Pterocarpus marsupium | BL62: Fagus sylvatica | BM62: Pterocarpus pedatus | BN62: Najas pseudogracillima | BO62: Diospyros poncej | BP62: Torreya nucifera | BQ62: Zenia insignis | BR62: Myristica Fragrans | BS62: Anisodus tanguticus
A63: t_3_21680_Anderes Holz_Protokoll_7318 - Holzarten | B63: t_16E96FBE3CD93D5FA1F558943E5A0B39 | C63: Dipentodon sinicus | D63: Neocheiropteris palmatopedata | E63: Pennisetum sichuanense | F63: Larix mastersiana | G63: Acidosasa chinensis | H63: Diospyros celebica | I63: Dicksonia antarctica | J63: Larix chinensis | K63: Keteleeria davidiana var. formosana | L63: Cassia siamea | M63: Dipterocarpus conformis | N63: Camptotheca acuminata | O63: Amomum subulatum | P63: Amphicarpaea linearis | Q63: Plectocomia microstachys | R63: Cistanche salsa | S63: Betula halophila | T63: Euphorbia pulcherrima | U63: Anisachne gracilis | V63: Mussaenda anomala | W63: Cinnamomum mairei | X63: Picea brachytyla var. complanata | Y63: Sorolepidium glaciale | Z63: Pterocarpus cambodianus | AA63: Cinnamomum camphora | AB63: Cinnamomum glanduliferum | AC63: Changiostyrax dolichocarpa | AD63: Sinopteris grevilleoides | AE63: Erisma uncinatum | AF63: Skapanthus oreophilus | AG63: Chosenia arbutifolia | AH63: Pterocarpus indicus | AI63: Amomum testaceum | AJ63: Pterocarpus dalbergioides | AK63: Semiliquidambar cathayensis | AL63: Millettia leucantha | AM63: Sinojackia xylocarpa | AN63: Amoora dasyclada | AO63: Aloe vera | AP63: Dipterocarpus grandiflorus | AQ63: Pterocarpus macrocarpus | AR63: Cyrtomium hemionitis | AS63: Metabriggsia ovalifolia | AT63: Trailliaedoxa gracilis | AU63: Elymus breviaristatus | AV63: Tilia tuan | AW63: Diospyros philippensis | AX63: Millettia laurentii | AY63: Dichocarpum hypoglaucum | AZ63: Nuphar bornetii | BA63: Archangiopteris henryi | BB63: Diospyros crassiflora | BC63: Khaya ivorensis | BD63: Pseudotsuga menziesii | BE63: Ajaniopsis penicilliformis | BF63: Betula jinpingensis | BG63: Dipterocarpus cornutus | BH63: Zelkova schneideriana | BI63: Rhoiptelea chiliantha | BJ63: Diospyros pilosanthera | BK63: Pterocarpus marsupium | BL63: Fagus sylvatica | BM63: Pterocarpus pedatus | BN63: Najas pseudogracillima | BO63: Diospyros poncej | BP63: Torreya nucifera | BQ63: Zenia insignis | BR63: Myristica Fragrans | BS63: Anisodus tanguticus
A64: t_3_21680_Rohholz_Protokoll_7318 - Holzarten | B64: t_95D354AC9C2236CAAF5CC00E072F89C8 | C64: Dipentodon sinicus | D64: Neocheiropteris palmatopedata | E64: Pennisetum sichuanense | F64: Larix mastersiana | G64: Acidosasa chinensis | H64: Diospyros celebica | I64: Dicksonia antarctica | J64: Larix chinensis | K64: Keteleeria davidiana var. formosana | L64: Cassia siamea | M64: Dipterocarpus conformis | N64: Camptotheca acuminata | O64: Amomum subulatum | P64: Amphicarpaea linearis | Q64: Plectocomia microstachys | R64: Cistanche salsa | S64: Betula halophila | T64: Euphorbia pulcherrima | U64: Anisachne gracilis | V64: Mussaenda anomala | W64: Cinnamomum mairei | X64: Picea brachytyla var. complanata | Y64: Sorolepidium glaciale | Z64: Pterocarpus cambodianus | AA64: Cinnamomum camphora | AB64: Cinnamomum glanduliferum | AC64: Changiostyrax dolichocarpa | AD64: Sinopteris grevilleoides | AE64: Erisma uncinatum | AF64: Skapanthus oreophilus | AG64: Chosenia arbutifolia | AH64: Pterocarpus indicus | AI64: Amomum testaceum | AJ64: Pterocarpus dalbergioides | AK64: Semiliquidambar cathayensis | AL64: Millettia leucantha | AM64: Sinojackia xylocarpa | AN64: Amoora dasyclada | AO64: Aloe vera | AP64: Dipterocarpus grandiflorus | AQ64: Pterocarpus macrocarpus | AR64: Cyrtomium hemionitis | AS64: Metabriggsia ovalifolia | AT64: Trailliaedoxa gracilis | AU64: Elymus breviaristatus | AV64: Tilia tuan | AW64: Diospyros philippensis | AX64: Millettia laurentii | AY64: Dichocarpum hypoglaucum | AZ64: Nuphar bornetii | BA64: Archangiopteris henryi | BB64: Diospyros crassiflora | BC64: Khaya ivorensis | BD64: Pseudotsuga menziesii | BE64: Ajaniopsis penicilliformis | BF64: Betula jinpingensis | BG64: Dipterocarpus cornutus | BH64: Zelkova schneideriana | BI64: Rhoiptelea chiliantha | BJ64: Diospyros pilosanthera | BK64: Pterocarpus marsupium | BL64: Fagus sylvatica | BM64: Pterocarpus pedatus | BN64: Najas pseudogracillima | BO64: Diospyros poncej | BP64: Torreya nucifera | BQ64: Zenia insignis | BR64: Myristica Fragrans | BS64: Anisodus tanguticus
A65: t_3_22229_Hergestellt aus anderen Pflanzenmaterialien_Protokoll_7318 - Holzarten | B65: t_02D22A59659A388E8E356504A61A3003 | C65: Dipentodon sinicus | D65: Neocheiropteris palmatopedata | E65: Pennisetum sichuanense | F65: Larix mastersiana | G65: Acidosasa chinensis | H65: Diospyros celebica | I65: Dicksonia antarctica | J65: Larix chinensis | K65: Keteleeria davidiana var. formosana | L65: Cassia siamea | M65: Dipterocarpus conformis | N65: Camptotheca acuminata | O65: Amomum subulatum | P65: Amphicarpaea linearis | Q65: Plectocomia microstachys | R65: Cistanche salsa | S65: Betula halophila | T65: Euphorbia pulcherrima | U65: Anisachne gracilis | V65: Mussaenda anomala | W65: Cinnamomum mairei | X65: Picea brachytyla var. complanata | Y65: Sorolepidium glaciale | Z65: Pterocarpus cambodianus | AA65: Cinnamomum camphora | AB65: Cinnamomum glanduliferum | AC65: Changiostyrax dolichocarpa | AD65: Sinopteris grevilleoides | AE65: Erisma uncinatum | AF65: Skapanthus oreophilus | AG65: Chosenia arbutifolia | AH65: Pterocarpus indicus | AI65: Amomum testaceum | AJ65: Pterocarpus dalbergioides | AK65: Semiliquidambar cathayensis | AL65: Millettia leucantha | AM65: Sinojackia xylocarpa | AN65: Amoora dasyclada | AO65: Aloe vera | AP65: Dipterocarpus grandiflorus | AQ65: Pterocarpus macrocarpus | AR65: Cyrtomium hemionitis | AS65: Metabriggsia ovalifolia | AT65: Trailliaedoxa gracilis | AU65: Elymus breviaristatus | AV65: Tilia tuan | AW65: Diospyros philippensis | AX65: Millettia laurentii | AY65: Dichocarpum hypoglaucum | AZ65: Nuphar bornetii | BA65: Archangiopteris henryi | BB65: Diospyros crassiflora | BC65: Khaya ivorensis | BD65: Pseudotsuga menziesii | BE65: Ajaniopsis penicilliformis | BF65: Betula jinpingensis | BG65: Dipterocarpus cornutus | BH65: Zelkova schneideriana | BI65: Rhoiptelea chiliantha | BJ65: Diospyros pilosanthera | BK65: Pterocarpus marsupium | BL65: Fagus sylvatica | BM65: Pterocarpus pedatus | BN65: Najas pseudogracillima | BO65: Diospyros poncej | BP65: Torreya nucifera | BQ65: Zenia insignis | BR65: Myristica Fragrans | BS65: Anisodus tanguticus
A66: t_3_21785_Anderes Holz_Protokoll_7318 - Holzarten | B66: t_4B70ECAAACF13EBDA3D4300657E1FF95 | C66: Dipentodon sinicus | D66: Neocheiropteris palmatopedata | E66: Pennisetum sichuanense | F66: Larix mastersiana | G66: Acidosasa chinensis | H66: Diospyros celebica | I66: Dicksonia antarctica | J66: Larix chinensis | K66: Keteleeria davidiana var. formosana | L66: Cassia siamea | M66: Dipterocarpus conformis | N66: Camptotheca acuminata | O66: Amomum subulatum | P66: Amphicarpaea linearis | Q66: Plectocomia microstachys | R66: Cistanche salsa | S66: Betula halophila | T66: Euphorbia pulcherrima | U66: Anisachne gracilis | V66: Mussaenda anomala | W66: Cinnamomum mairei | X66: Picea brachytyla var. complanata | Y66: Sorolepidium glaciale | Z66: Pterocarpus cambodianus | AA66: Cinnamomum camphora | AB66: Cinnamomum glanduliferum | AC66: Changiostyrax dolichocarpa | AD66: Sinopteris grevilleoides | AE66: Erisma uncinatum | AF66: Skapanthus oreophilus | AG66: Chosenia arbutifolia | AH66: Pterocarpus indicus | AI66: Amomum testaceum | AJ66: Pterocarpus dalbergioides | AK66: Semiliquidambar cathayensis | AL66: Millettia leucantha | AM66: Sinojackia xylocarpa | AN66: Amoora dasyclada | AO66: Aloe vera | AP66: Dipterocarpus grandiflorus | AQ66: Pterocarpus macrocarpus | AR66: Cyrtomium hemionitis | AS66: Metabriggsia ovalifolia | AT66: Trailliaedoxa gracilis | AU66: Elymus breviaristatus | AV66: Tilia tuan | AW66: Diospyros philippensis | AX66: Millettia laurentii | AY66: Dichocarpum hypoglaucum | AZ66: Nuphar bornetii | BA66: Archangiopteris henryi | BB66: Diospyros crassiflora | BC66: Khaya ivorensis | BD66: Pseudotsuga menziesii | BE66: Ajaniopsis penicilliformis | BF66: Betula jinpingensis | BG66: Dipterocarpus cornutus | BH66: Zelkova schneideriana | BI66: Rhoiptelea chiliantha | BJ66: Diospyros pilosanthera | BK66: Pterocarpus marsupium | BL66: Fagus sylvatica | BM66: Pterocarpus pedatus | BN66: Najas pseudogracillima | BO66: Diospyros poncej | BP66: Torreya nucifera | BQ66: Zenia insignis | BR66: Myristica Fragrans | BS66: Anisodus tanguticus
... A82: t_3_21785_Gefährdetes Holz_Protokoll_7318 - Holzarten | B82: t_544481F8EA4735E49140898A6CDEEBBE | C82: Dipentodon sinicus | D82: Neocheiropteris palmatopedata | E82: Pennisetum sichuanense | F82: Larix mastersiana | G82: Acidosasa chinensis | H82: Diospyros celebica | I82: Dicksonia antarctica | J82: Larix chinensis | K82: Keteleeria davidiana var. formosana | L82: Cassia siamea | M82: Dipterocarpus conformis | N82: Camptotheca acuminata | O82: Amomum subulatum | P82: Amphicarpaea linearis | Q82: Plectocomia microstachys | R82: Cistanche salsa | S82: Betula halophila | T82: Euphorbia pulcherrima | U82: Anisachne gracilis | V82: Mussaenda anomala | W82: Cinnamomum mairei | X82: Picea brachytyla var. complanata | Y82: Sorolepidium glaciale | Z82: Pterocarpus cambodianus | AA82: Cinnamomum camphora | AB82: Cinnamomum glanduliferum | AC82: Changiostyrax dolichocarpa | AD82: Sinopteris grevilleoides | AE82: Erisma uncinatum | AF82: Skapanthus oreophilus | AG82: Chosenia arbutifolia | AH82: Pterocarpus indicus | AI82: Amomum testaceum | AJ82: Pterocarpus dalbergioides | AK82: Semiliquidambar cathayensis | AL82: Millettia leucantha | AM82: Sinojackia xylocarpa | AN82: Amoora dasyclada | AO82: Aloe vera | AP82: Dipterocarpus grandiflorus | AQ82: Pterocarpus macrocarpus | AR82: Cyrtomium hemionitis | AS82: Metabriggsia ovalifolia | AT82: Trailliaedoxa gracilis | AU82: Elymus breviaristatus | AV82: Tilia tuan | AW82: Diospyros philippensis | AX82: Millettia laurentii | AY82: Dichocarpum hypoglaucum | AZ82: Nuphar bornetii | BA82: Archangiopteris henryi | BB82: Diospyros crassiflora | BC82: Khaya ivorensis | BD82: Pseudotsuga menziesii | BE82: Ajaniopsis penicilliformis | BF82: Betula jinpingensis | BG82: Dipterocarpus cornutus | BH82: Zelkova schneideriana | BI82: Rhoiptelea chiliantha | BJ82: Diospyros pilosanthera | BK82: Pterocarpus marsupium | BL82: Fagus sylvatica | BM82: Pterocarpus pedatus | BN82: Najas pseudogracillima | BO82: Diospyros poncej | BP82: Torreya nucifera | BQ82: Zenia insignis | BR82: Myristica Fragrans | BS82: Anisodus tanguticus
A83: t_3_21226_1941 - Anwendbare Modelle | B83: t_D9A4F9D917FD3961B64DE6D9BB50A1EC | C83: Produktdetails ansehen | D83: Universell Anwendbar
A84: t_3_22226_1941 - Anwendbare Modelle | B84: t_42F092B8BDDB3648A59398E54853C7F9 | C84: Produktdetails ansehen | D84: Universell Anwendbar
A85: t_3_22229_1941 - Anwendbare Modelle | B85: t_8645B3039E213673A8A8E13416D95FFB | C85: Produktdetails ansehen | D85: Universell Anwendbar
A86: t_3_21903_1941 - Anwendbare Modelle | B86: t_B3E0718EC29137A1AE7A25CEB424C8ED | C86: Produktdetails ansehen | D86: Universell Anwendbar
A87: t_3_21842_1941 - Anwendbare Modelle | B87: t_5794CF77308B30488DAA7AFBD3BEF7BA | C87: Produktdetails ansehen | D87: Universell Anwendbar
A88: t_3_21873_1941 - Anwendbare Modelle | B88: t_1D1E329B1F2A391CA3DDDA099BCB3CB3 | C88: Produktdetails ansehen | D88: Universell Anwendbar
A89: t_3_21792_1941 - Anwendbare Modelle | B89: t_2E0DDE0D4E6D390585BABC803E3D7379 | C89: Produktdetails ansehen | D89: Universell Anwendbar
A90: t_3_21691_1941 - Anwendbare Modelle | B90: t_6B27049ED99638CDB6E5075FADAC93C0 | C90: Produktdetails ansehen | D90: Universell Anwendbar
A91: t_3_21785_1941 - Anwendbare Modelle | B91: t_3AFA2680C46934DF938715F837C3CD4D | C91: Produktdetails ansehen | D91: Universell Anwendbar
A92: t_3_21775_1941 - Anwendbare Modelle | B92: t_1E4AB652A49D3EF18B19F626A3CBFA34 | C92: Produktdetails ansehen | D92: Universell Anwendbar
A93: t_3_21680_1941 - Anwendbare Modelle | B93: t_A1D0C884D3DB3FD290C9F04B05B08344 | C93: Produktdetails ansehen | D93: Universell Anwendbar
A94: t_3_22184_1941 - Anwendbare Modelle | B94: t_D1A508BC95413EFEBD07684EA371CE0D | C94: Produktdetails ansehen | D94: Universell Anwendbar
A95: t_3_21903_120 - Bauteilposition | B95: t_5A472AA2A8FD3707990D9AA426A98184 | C95: Links | D95: Rechts | E95: Vorderseite | F95: Rückseite
A96: t_3_21792_120 - Bauteilposition | B96: t_4C7B5F1B67813E78846D43872BF60314 | C96: Links | D96: Rechts | E96: Vorderseite | F96: Rückseite
A97: t_3_22229_120 - Bauteilposition | B97: t_2B7A74DA3E193621B6A01CC2062A886A | C97: Links | D97: Rechts | E97: Vorderseite | F97: Rückseite
A98: t_3_22226_120 - Bauteilposition | B98: t_F787325F20B83C608BB29A18FAD61426 | C98: Links | D98: Rechts | E98: Vorderseite | F98: Rückseite
A99: t_3_21785_120 - Bauteilposition | B99: t_CA855D339D8A3A25BC878326A7EE6EE1 | C99: Links | D99: Rechts | E99: Vorderseite | F99: Rückseite
A100: t_3_22184_120 - Bauteilposition | B100: t_78A085F3705A3D958B2E958CEC1D539A | C100: Links | D100: Rechts | E100: Vorderseite | F100: Rückseite
A101: t_3_21873_120 - Bauteilposition | B101: t_CD8C3F9A2A33361AB8E828424F9A9193 | C101: Links | D101: Rechts | E101: Vorderseite | F101: Rückseite
A102: t_3_22184_121 - Material | B102: t_BFB9EA9F8D5539BAA5CAD92CDB6C0A9D | C102: Metall | D102: Plastik | E102: Vinyl | F102: Polyurethan | G102: Fiberglas | H102: Aluminium | I102: Edelstahl | J102: Acryl | K102: Polypropylen | L102: Nylon | M102: Legierter Stahl | N102: Acrylnitril-Butadien-Styrol | O102: Titan | P102: Kohlenstoffstahl | Q102: Kohlefaser | R102: Faserverstärkter Kunststoff | S102: Eisen | T102: Stahl | U102: Kupfer | V102: Aluminiumlegierung | W102: Titanlegierung | X102: Kohlenstoffstahl | Y102: Andere Metallmaterialien | Z102: PVC | AA102: PE (Polyethylen) | AB102: PP (Polypropylen) | AC102: PC (Polycarbonat) | AD102: ABS (ABS-Harz) | AE102: TPU (Thermoplastisches Polyurethan) | AF102: Silikon | AG102: Anderer Kunststoff | AH102: Natürliches Gummi | AI102: Synthesekautschuk | AJ102: Vulkanisierter Gummi | AK102: Schwammgummi | AL102: Hartes Gummi | AM102: Anderer Gummi | AN102: Abs | AO102: PET (Polyethylenterephthalat) | AP102: EVA (Ethylen-Vinylacetat-Copolymer) | AQ102: Acryl (PMMA)
A103: t_3_21792_121 - Material | B103: t_FBF1D71D4AE73A7A89AED8B74CB92CA6 | C103: Metall | D103: Plastik | E103: Vinyl | F103: Polyurethan | G103: Fiberglas | H103: Aluminium | I103: Stahl | J103: Kupfer | K103: Edelstahl | L103: Acryl | M103: Eisen | N103: Polypropylen | O103: Nylon | P103: Legierter Stahl | Q103: Acrylnitril-Butadien-Styrol | R103: Titan | S103: Kohlenstoffstahl | T103: Kohlefaser | U103: Faserverstärkter Kunststoff | V103: Abs | W103: Aluminiumlegierung | X103: Kohlenstoffstahl | Y103: Titanlegierung | Z103: Andere Metallmaterialien | AA103: Zink | AB103: Zinklegierung | AC103: Kupferlegierung | AD103: Magnesiumlegierung Golden
A104: t_3_21792_335 - Produktgrad | B104: t_BDB899FC3F5033C09746C0BB5AD158C4 | C104: Abstimmung | D104: Ersatzteil | E104: Leistungsteil
A105: t_3_22184_335 - Produktgrad | B105: t_23917E8BCA2A3CD39B8476C8C941CDAE | C105: Abstimmung | D105: Ersatzteil | E105: Leistungsteil
A106: t_3_22184_1081 - Oberflächenbehandlungsprozess | B106: t_64A01142E9743CCBA4AD5272FE1B594B | C106: Matt | D106: Polieren | E106: Chrom | F106: Rückgängig gemacht | G106: Gebürstet | H106: Pulverbeschichtung | I106: Öl reiben | J106: Gemalt | K106: Bemalt | L106: Öl reiben | M106: Öl reiben
A107: t_3_21792_1081 - Oberflächenbehandlungsprozess | B107: t_E7E70C6F4B403B61ABE00C74DCA2DF43 | C107: Matt | D107: Rückgängig gemacht | E107: Polieren | F107: Gebürstet | G107: Pulverbeschichtung | H107: Öl reiben | I107: Gemalt | J107: Bemalt | K107: Öl reiben | L107: Öl reiben | M107: Chrom
A108: t_3_22229_1081 - Oberflächenbehandlungsprozess | B108: t_FF14C6B051F034DDB115EE33AB0B52D1 | C108: Matt | D108: Polieren | E108: Chrom
A109: t_3_21873_402 - Beschreibung Krümmung | B109: t_DD35AEFDADBC346488AEC9EA18C63BB6 | C109: Konvex | D109: Asphärisch | E109: Flach
A110: t_3_21873_25 - Geeignete Typen | B110: t_6C120C52B6E93C42A95450340DFB98B2 | C110: Fahrzeugspezifische Passform | D110: Universelle Passform
A111: t_3_21873_134 - Artikelform | B111: t_6CD9317F586035B1A4DE5FF35BF9A086 | C111: Oval | D111: Dreieck | E111: Runden | F111: Rechteck | G111: Achteckig | H111: Sechseckig | I111: Quadrat | J111: Diamant | K111: Fünfeckig | L111: Länglich | M111: Fan
A112: t_3_21785_200 - Äußeres Finish | B112: t_6D85458AE2113C92889407A78C764DDB | C112: Schwarzoxid | D112: Schwarzes Phosphat | E112: Cadmium | F112: Galvanisiert | G112: Verchromt | H112: Nickel | I112: Passiviert | J112: Unbehandelt | K112: Zink | L112: Blaues Phosphat | M112: Korrosionsschutz-Decklack | N112: Messing | O112: Bronze | P112: Kupfer | Q112: Diamant | R112: Goldener Chem-Film | S112: Fluorpolymer | T112: Vergoldet verzinkt | U112: Feuerverzinkt | V112: Loctite204 | W112: Geschmiert | X112: Öl | Y112: Lackiert | Z112: Phosphat | AA112: Plastik | AB112: Poliert | AC112: PVC (Polyvinylchlorid) | AD112: Gummi | AE112: Silber | AF112: Zinn | AG112: Extrem korrosionsbeständig | AH112: Vinyl | AI112: Zink Chromat | AJ112: Gelb-Zink | AK112: Wachs | AL112: Zinkflocken | AM112: Zink-Aluminium | AN112: Zinkgelbchromat | AO112: 1000 Stunden Epoxidbeschichtung | AP112: 500 Stunden Epoxidbeschichtung | AQ112: Aluminium | AR112: Schwarzoxid & Öl | AS112: Antikes Messing | AT112: Schwarzer Dfar | AU112: Schwarzes Oxid & Wachs | AV112: Schwarzes Phosphat & Öl | AW112: Schwarzes Zink | AX112: Blaues Zink | AY112: Blaues Zink & Wachs | AZ112: Blaues Dauersiegel | BA112: Bronzene Epoxidbeschichtung | BB112: Keramik | BC112: Dacrotisiert | BD112: Elektrozink | BE112: Ecoguard Silber | BF112: Elektrisch galvanisiert | BG112: Grünes Zink | BH112: Epoxidbeschichtung | BI112: Hitzebehandelt | BJ112: Matt eloxiert | BK112: Mechanisches blaues Zink | BL112: Mechanisch verzinkt | BM112: Mechanisches Zink | BN112: Nylon | BO112: Passiviert & Wachs | BP112: Phosphat & Öl | BQ112: Satin | BR112: Edelstahl | BS112: Stahl | BT112: Tanxl1500 | BU112: Thermisches Schwarzoxid | BV112: Dreiwertiges Chromat (rohs) | BW112: Kriegsbeschichtung | BX112: Gelbes Kadmium | BY112: Gelbes Zink & Wachs | BZ112: Zink mit Dickschichtpassivierung | CA112: Zink & Wachs
A113: t_3_21775_200 - Äußeres Finish | B113: t_6B6CC7D17A863651879D74B1A714F7DC | C113: Lackiert | D113: Poliert | E113: Gebürstet | F113: Bearbeitet | G113: Chrom | H113: Gemahlen
A114: t_3_21873_200 - Äußeres Finish | B114: t_DA08332CA34D3C64B0E52A07416AED3C | C114: Chrom* | D114: Matt | E114: Poliert
A115: t_3_21873_1279 - Verwendungszweck | B115: t_1D75873E8074362AABAA71422D1DB341 | C115: Rückspiegel-Ersatzteile/OE-Teile | D115: Rückspiegel-Dekorationen
A116: t_3_21842_1125 - Lichtquellenart | B116: t_42EC343BBFBC3654A6A87577842C0C5D | C116: LED Lichter | D116: Xenon-Lichter | E116: Wolfram-Halogenlampe | F116: Glühlampe | G116: Leuchtstofflampe | H116: Bogenlampe | I116: UV-Lampe | J116: Infrarot-Glühbirne | K116: Beiliegender Scheinwerfer | L116: Andere | M116: Natriumdampflampe | N116: Quecksilberdampflampe | O116: Keine
A117: t_3_21842_358 - Spezifische Verwendungsszenarien | B117: t_BA286A171AA1350691087C8B28AA2865 | C117: Weihnachten | D117: Für Fahrräder | E117: Kraftfahrzeuge | F117: Haushalt | G117: Dekoration | H117: Für wissenschaftliche Forschung und medizinische Zwecke | I117: Außenbereich | J117: Für Leuchtschilder oder Namensschilder | K117: Eigenversorgte Energie für den mobilen Einsatz | L117: Für Verkehrssignalgeräte | M117: Lichtanlagen | N117: Andere
A118: t_3_2153 - Batterieeigenschaften | B118: t_03D7EF1598193732B62DDBECBC0A36C5 | C118: Solarbatterie | D118: Nicht wiederaufladbare Batterie | E118: ohne Akku | F118: Wiederaufladbare Batterie
A119: t_3_2147 - Wiederaufladbare Batterie | B119: t_F51258181CDB39ADBC8E70EDCF0F6ED3 | C119: Lithium-Knopfbatterie | D119: Nickelbatterie | E119: Lithium-Polymer-Batterie | F119: Blei-Säure-Batterie | G119: Lithiumbatterie-18650 Series | H119: Lithiumbatterie-Andere Serie
A120: t_3_2154 - Solarbatterie | B120: t_A135562AC54F3386BD85DC491A9B74B0 | C120: Lithium Batterie | D120: Nickelbatterie
A121: t_3_3740 - Nicht wiederaufladbare Batterie | B121: t_12556C4DE26B361AA913A6EB69237C76 | C121: Nicht-Standard-Batterie Batterie 9v | D121: AA-Batterie | E121: AAA-Batterie | F121: Knopfbatterie (Durchmesser < 20 mm) | G121: Knopfbatterie (Durchmesser ≥ 20 mm) | H121: Andere Batterien
A122: t_3_21226_1067 - Stromversorgungsart | B122: t_6A5C3EB4B056335FA73830D07629ABF5 | C122: Stromversorgung | D122: Batterie/Strom für zwei Zwecke | E122: USB-Aufladung | F122: USB | G122: Batteriebetrieben/USB-Dual-Use | H122: Batteriebetrieben | I122: Ungeladen | J122: Solarbetrieben | K122: Zigarettenanzünder eingesteckt | L122: Elektrische/Festverdrahtung im Zimmer | M122: OBD-Anschluss
A123: t_3_21903_1067 - Stromversorgungsart | B123: t_A21A64F6B3B83E12AF7336471D323DC5 | C123: Stromversorgung | D123: Batterie/Strom für zwei Zwecke | E123: USB-Aufladung | F123: USB | G123: Batteriebetrieben/USB-Dual-Use | H123: Batteriebetrieben | I123: Ungeladen | J123: Solarbetrieben | K123: Zigarettenanzünder eingesteckt | L123: Elektrische/Festverdrahtung im Zimmer | M123: OBD-Anschluss
A124: t_3_21226_Solarbetrieben_1132 - Betriebsspannung | B124: t_3CCBB437E06433EB857E606AC08BD24B | C124: 36V (nicht enthalten)-100V (nicht enthalten) | D124: 5V | E124: 6V | F124: 12V | G124: 24V | H124: 12-24V | I124: 9-36V | J124: ≤36V
A125: t_3_21226_OBD-Anschluss_1132 - Betriebsspannung | B125: t_72B2575FD6A8314B8C8C485126C725AB | C125: ≤36V
A126: t_3_21226_USB_1132 - Betriebsspannung | B126: t_AC43D4C5399D336F87A35AF31172C3E6 | C126: 36V (nicht enthalten)-100V (nicht enthalten) | D126: 5V | E126: 6V | F126: 12V | G126: 24V | H126: 12-24V | I126: 9-36V | J126: ≤36V
A127: t_3_21226_Batterie/Strom für zwei Zwecke_1132 - Betriebsspannung | B127: t_49D9A025AC18300FB8DFE28A41142EFF | C127: 220V | D127: 175-265 V | E127: 230V | F127: 85V-265V | G127: 240V | H127: 110V/220V | I127: 265 V (nicht enthalten)-1000 V | J127: 220 V (enthalten)-240 V (enthalten)
A128: t_3_21903_OBD-Anschluss_1132 - Betriebsspannung | B128: t_FBAFA08447293BD58F3315F4EB00BFC0 | C128: ≤36V
A129: t_3_21226_Zigarettenanzünder eingesteckt_1132 - Betriebsspannung | B129: t_90DD3AD042A939C7838A54772B00CC1D | C129: 36V (nicht enthalten)-100V (nicht enthalten) | D129: 5V | E129: 6V | F129: 12V | G129: 24V | H129: 12-24V | I129: 9-36V | J129: ≤36V
A130: t_3_21903_Zigarettenanzünder eingesteckt_1132 - Betriebsspannung | B130: t_061A6990706D3FEC8D9A6158E9B9DF14 | C130: 36V (nicht enthalten)-100V (nicht enthalten) | D130: 5V | E130: 6V | F130: 12V | G130: 24V | H130: 12-24V | I130: 9-36V | J130: ≤36V
...

Sheet GoodsLevelMode
A1: t_0_Warennummer | B1: t_0_SKU-ID | C1: t_0_Status | D1: t_0_Details | E1: t_1_Kategorie | F1: t_1_Kategoriename | G1: t_1_Produkttyp | H1: t_1_Verarbeitungsverfahren zur Anpassung | I1: t_1_Primärverfahren | J1: t_1_Sekundärverfahren | K1: t_1_Sekundärverfahren | L1: t_1_Produktname | M1: t_1_Verkäufer Goods | N1: t_1_Verkäufer SKU | O1: t_1_Aktualisieren oder hinzufügen | P1: t_1_Warennummer | Q1: t_1_SKU-ID | R1: t_1_Marke | S1: t_1_Markenzeichen | T1: t_2_Produktbeschreibung | U1: t_2_Aufzählungspunkt | V1: t_2_Aufzählungspunkt | W1: t_2_Aufzählungspunkt | X1: t_2_Aufzählungspunkt | Y1: t_2_Aufzählungspunkt | Z1: t_2_Aufzählungspunkt | AA1: t_2_URL für Detailbilder | AB1: t_2_URL für Detailbilder | AC1: t_2_URL für Detailbilder | AD1: t_2_URL für Detailbilder | AE1: t_2_URL für Detailbilder | AF1: t_2_URL für Detailbilder | AG1: t_2_URL für Detailbilder | AH1: t_2_URL für Detailbilder | AI1: t_2_URL für Detailbilder | AJ1: t_2_URL für Detailbilder | AK1: t_2_URL für Detailbilder | AL1: t_2_URL für Detailbilder | AM1: t_2_URL für Detailbilder | AN1: t_2_URL für Detailbilder | AO1: t_2_URL für Detailbilder | AP1: t_2_URL für Detailbilder | AQ1: t_2_URL für Detailbilder | AR1: t_2_URL für Detailbilder | AS1: t_2_URL für Detailbilder | AT1: t_2_URL für Detailbilder | AU1: t_2_URL für Detailbilder | AV1: t_2_URL für Detailbilder | AW1: t_2_URL für Detailbilder | AX1: t_2_URL für Detailbilder | AY1: t_2_URL für Detailbilder | AZ1: t_2_URL für Detailbilder | BA1: t_2_URL für Detailbilder | BB1: t_2_URL für Detailbilder | BC1: t_2_URL für Detailbilder | BD1: t_2_URL für Detailbilder | BE1: t_2_URL für Detailbilder | BF1: t_2_URL für Detailbilder | BG1: t_2_URL für Detailbilder | BH1: t_2_URL für Detailbilder | BI1: t_2_URL für Detailbilder | BJ1: t_2_URL für Detailbilder | BK1: t_2_URL für Detailbilder | BL1: t_2_URL für Detailbilder | BM1: t_2_URL für Detailbilder | BN1: t_2_URL für Detailbilder | BO1: t_2_URL für Detailbilder | BP1: t_2_URL für Detailbilder | BQ1: t_2_URL für Detailbilder | BR1: t_2_URL für Detailbilder | BS1: t_2_URL für Detailbilder | BT1: t_2_URL für Detailbilder | BU1: t_2_URL für Detailbilder | BV1: t_2_URL für Detailbilder | BW1: t_2_URL für Detailbilder | BX1: t_2_Detail-Video-URL | BY1: t_3_21680_21775_21785_22229_1920 - Hauptmaterial | BZ1: t_3_21680_21775_21785_22229_4109 - Echte Ledersorte | CA1: t_3_21680_21775_21785_22229_7317 - Holzart | CB1: t_3_21680_21775_21785_22229_7318 - Holzarten | CC1: t_3_21226_21680_21691_21775_21785_21792_21842_21873_21903_22184_22226_22229_1941 - Anwendbare Modelle | CD1: t_3_21226_21680_21691_21775_21785_21792_21842_21873_21903_22184_22226_22229_1450 - OEM-Nummer | CE1: t_3_21785_21792_21873_21903_22184_22226_22229_120 - Bauteilposition | CF1: t_3_21792_22184_121 - Material | CG1: t_3_21792_22184_335 - Produktgrad | CH1: t_3_21792_22184_22229_1081 - Oberflächenbehandlungsprozess | CI1: t_3_21873_402 - Beschreibung Krümmung | CJ1: t_3_21873_25 - Geeignete Typen | CK1: t_3_21873_134 - Artikelform | CL1: t_3_21775_21785_21873_200 - Äußeres Finish | CM1: t_3_21873_1279 - Verwendungszweck | CN1: t_3_21842_1125 - Lichtquellenart | CO1: t_3_21842_358 - Spezifische Verwendungsszenarien | CP1: t_3_21226_21842_21903_2153 - Batterieeigenschaften | CQ1: t_3_21226_21842_21903_2147 - Wiederaufladbare Batterie | CR1: t_3_21226_21842_21903_2154 - Solarbatterie | CS1: t_3_21226_21842_21903_3740 - Nicht wiederaufladbare Batterie | CT1: t_3_21226_21903_1067 - Stromversorgungsart | CU1: t_3_21226_21903_1132 - Betriebsspannung | CV1: t_3_21226_21903_1485 - Steckertyp | CW1: t_3_21226_21691_1271 - Fahrzeugreihe | CX1: t_3_21226_1420 - Produkttypen | CY1: t_3_21691_15 - Zusammensetzung:Neopren | CZ1: t_3_21691_15 - Zusammensetzung:Sonstige Fasern | DA1: t_4_21226_21680_21691_21775_21785_21792_21842_21873_21903_22184_22226_22229_Variationsdesign | DB1: t_4_21226_21680_21691_21775_21785_21792_21842_21873_21903_22184_22226_22229_Farbe | DC1: t_4_21226_21680_21691_21775_21785_21792_21842_21873_21903_22184_22226_22229_Größe | DD1: t_4_21226_21680_21691_21775_21785_21792_21842_21873_21903_22184_22226_22229_Stil | DE1: t_4_21226_21680_21691_21775_21785_21792_21842_21873_21903_22184_22226_22229_Material | DF1: t_4_21226_21680_21691_21775_21785_21792_21842_21873_21903_22184_22226_22229_Aromen | DG1: t_4_21226_21680_21691_21775_21785_21792_21842_21873_21903_22184_22226_22229_Anwendbare Personen | DH1: t_4_21226_21680_21691_21775_21785_21792_21842_21873_21903_22184_22226_22229_Kapazität | DI1: t_4_21226_21680_21691_21775_21785_21792_21842_21873_21903_22184_22226_22229_Komposition | DJ1: t_4_21226_21680_21691_21775_21785_21792_21842_21873_21903_22184_22226_22229_Gewicht | DK1: t_4_21226_21680_21691_21775_21785_21792_21842_21873_21903_22184_22226_22229_Artikel | DL1: t_4_21226_21680_21691_21775_21785_21792_21842_21873_21903_22184_22226_22229_Menge | DM1: t_4_21226_21680_21691_21775_21785_21792_21842_21873_21903_22184_22226_22229_Modell | DN1: t_4_21226_21680_21691_21775_21785_21792_21842_21873_21903_22184_22226_22229_Haarlänge | DO1: t_6_URL für SKU-Bilder | DP1: t_6_URL für SKU-Bilder | DQ1: t_6_URL für SKU-Bilder | DR1: t_6_URL für SKU-Bilder | DS1: t_6_URL für SKU-Bilder | DT1: t_6_URL für SKU-Bilder | DU1: t_6_URL für SKU-Bilder | DV1: t_6_URL für SKU-Bilder | DW1: t_6_URL für SKU-Bilder | DX1: t_6_URL für SKU-Bilder | DY1: t_6_21226_21680_21691_21775_21785_21792_21842_21873_21903_22184_22226_22229_Abmessungen | DZ1: t_6_Anzahl | EA1: t_6_Basispreis - EUR | EB1: t_6_Referenzlink | EC1: t_6_Listenpreis - EUR | ED1: t_6_Nicht verfügbar für Listenpreis | EE1: t_6_Gewicht des Pakets - g | EF1: t_6_Länge - cm | EG1: t_6_Breite - cm | EH1: t_6_Höhe - cm | EI1: t_6_SKU-Typ | EJ1: t_6_Einzeln verpackt | EK1: t_6_Gesamtverpackungsanzahl | EL1: t_6_Verpackungseinheit | EM1: t_6_Gesamtartikelanzahl | EN1: t_6_Artikeleinheit | EO1: t_6_21226_21680_21691_21775_21785_21792_21842_21873_21903_22184_22226_22229_Nettoinhalt | EP1: t_6_21226_21680_21691_21775_21785_21792_21842_21873_21903_22184_22226_22229_Gesamtnettoinhalt | EQ1: t_6_21226_21680_21691_21775_21785_21792_21842_21873_21903_22184_22226_22229_Nettoinhaltseinheit | ER1: t_6_Externer Produkt-ID-Typ | ES1: t_6_Externe Produktnummer | ET1: t_7_Versandvorlage | EU1: t_7_Bearbeitungszeit | EV1: t_7_Fulfillment-Kanal | EW1: t_7_Artikelsteuercode (ITC) | EX1: t_8_Ursprungsland/-region | EY1: t_8_Herkunftsregion | EZ1: t_8_SKU-Verpackungsinformationen (mit sichtbarem Etikett) | FA1: t_8_SKU-Verpackungsinformationen (mit sichtbarem Etikett) | FB1: t_8_SKU-Verpackungsinformationen (mit sichtbarem Etikett) | FC1: t_8_SKU-Verpackungsinformationen (mit sichtbarem Etikett) | FD1: t_8_SKU-Verpackungsinformationen (mit sichtbarem Etikett) | FE1: t_8_SKU-Verpackungsinformationen (mit sichtbarem Etikett) | FF1: t_8_SKU-Verpackungsinformationen (mit sichtbarem Etikett) | FG1: t_8_SKU-Verpackungsinformationen (mit sichtbarem Etikett) | FH1: t_8_SKU-Verpackungsinformationen (mit sichtbarem Etikett) | FI1: t_8_SKU-Verpackungsinformationen (mit sichtbarem Etikett) | FJ1: t_8_SKU-Verpackungsinformationen (mit sichtbarem Etikett) | FK1: t_8_SKU-Verpackungsinformationen (mit sichtbarem Etikett) | FL1: t_8_SKU-Verpackungsinformationen (mit sichtbarem Etikett) | FM1: t_8_SKU-Verpackungsinformationen (mit sichtbarem Etikett) | FN1: t_8_SKU-Verpackungsinformationen (mit sichtbarem Etikett) | FO1: t_8_SKU-Verpackungsinformationen (mit sichtbarem Etikett) | FP1: t_8_SKU-Verpackungsinformationen (mit sichtbarem Etikett) | FQ1: t_8_SKU-Verpackungsinformationen (mit sichtbarem Etikett) | FR1: t_8_SKU-Verpackungsinformationen (mit sichtbarem Etikett) | FS1: t_8_SKU-Verpackungsinformationen (mit sichtbarem Etikett) | FT1: t_8_SKU-Verpackungsinformationen (mit sichtbarem Etikett) | FU1: t_8_SKU-Verpackungsinformationen (mit sichtbarem Etikett) | FV1: t_8_SKU-Verpackungsinformationen (mit sichtbarem Etikett) | FW1: t_8_SKU-Verpackungsinformationen (mit sichtbarem Etikett) | FX1: t_8_SKU-Verpackungsinformationen (mit sichtbarem Etikett) | FY1: t_8_SKU-Verpackungsinformationen (mit sichtbarem Etikett) | FZ1: t_8_SKU-Verpackungsinformationen (mit sichtbarem Etikett) | GA1: t_8_SKU-Verpackungsinformationen (mit sichtbarem Etikett) | GB1: t_8_SKU-Verpackungsinformationen (mit sichtbarem Etikett) | GC1: t_8_SKU-Verpackungsinformationen (mit sichtbarem Etikett) | GD1: t_8_SKU-Verpackungsinformationen (mit sichtbarem Etikett) | GE1: t_8_SKU-Verpackungsinformationen (mit sichtbarem Etikett) | GF1: t_8_SKU-Verpackungsinformationen (mit sichtbarem Etikett) | GG1: t_8_SKU-Verpackungsinformationen (mit sichtbarem Etikett) | GH1: t_8_SKU-Verpackungsinformationen (mit sichtbarem Etikett) | GI1: t_8_SKU-Verpackungsinformationen (mit sichtbarem Etikett) | GJ1: t_8_SKU-Verpackungsinformationen (mit sichtbarem Etikett) | GK1: t_8_SKU-Verpackungsinformationen (mit sichtbarem Etikett) | GL1: t_8_SKU-Verpackungsinformationen (mit sichtbarem Etikett) | GM1: t_8_SKU-Verpackungsinformationen (mit sichtbarem Etikett) | GN1: t_8_SKU-Verpackungsinformationen (mit sichtbarem Etikett) | GO1: t_8_SKU-Verpackungsinformationen (mit sichtbarem Etikett) | GP1: t_8_SKU-Verpackungsinformationen (mit sichtbarem Etikett) | GQ1: t_8_SKU-Verpackungsinformationen (mit sichtbarem Etikett) | GR1: t_8_SKU-Verpackungsinformationen (mit sichtbarem Etikett) | GS1: t_8_Ursprungsetikett & Herstellerinformationen | GT1: t_8_Ursprungsetikett & Herstellerinformationen | GU1: t_8_Ursprungsetikett & Herstellerinformationen | GV1: t_8_Ursprungsetikett & Herstellerinformationen | GW1: t_8_Ursprungsetikett & Herstellerinformationen | GX1: t_8_21226_21680_21691_21775_21785_21792_21842_21873_21903_22184_22226_22229_Produktführer - English | GY1: t_8_21226_21680_21691_21775_21785_21792_21842_21873_21903_22184_22226_22229_Wurden Produkte unter dieser Waren-ID nach dem 13. Dezember 2024 in der EU (oder Nordirland) platziert? | GZ1: t_8_21226_21680_21691_21775_21785_21792_21842_21873_21903_22184_22226_22229_Produktidentifikation | HA1: t_8_21226_21680_21691_21775_21785_21792_21842_21873_21903_22184_22226_22229_Hersteller | HB1: t_8_21226_21680_21691_21775_21785_21792_21842_21873_21903_22184_22226_22229_EU-Verantwortlicher
A2: 21226_require | E2: require | L2: require | M2: require | N2: require | CT2: require | CX2: require | DA2: require | DO2: require | DZ2: require | EA2: require | EC2: require | EE2: require | EF2: require | EG2: require | EH2: require | EJ2: require | EK2: require | EL2: require | ET2: require | EX2: require | HA2: require | HB2: require
A3: 21226_disabled | BY3: disabled | BZ3: disabled | CA3: disabled | CB3: disabled | CE3: disabled | CF3: disabled | CG3: disabled | CH3: disabled | CI3: disabled | CJ3: disabled | CK3: disabled | CL3: disabled | CM3: disabled | CN3: disabled | CO3: disabled | CY3: disabled | CZ3: disabled
A4: 21226_condition_require | CU4: condition_require | CV4: condition_require | EY4: condition_require
A5: 21680_require | E5: require | L5: require | M5: require | N5: require | DA5: require | DO5: require | DZ5: require | EA5: require | EC5: require | EE5: require | EF5: require | EG5: require | EH5: require | EJ5: require | EK5: require | EL5: require | ET5: require | EX5: require | HA5: require | HB5: require
A6: 21680_disabled | CE6: disabled | CF6: disabled | CG6: disabled | CH6: disabled | CI6: disabled | CJ6: disabled | CK6: disabled | CL6: disabled | CM6: disabled | CN6: disabled | CO6: disabled | CP6: disabled | CQ6: disabled | CR6: disabled | CS6: disabled | CT6: disabled | CU6: disabled | CV6: disabled | CW6: disabled | CX6: disabled | CY6: disabled | CZ6: disabled
A7: 21680_condition_require | EY7: condition_require
A8: 21691_require | E8: require | L8: require | M8: require | N8: require | DA8: require | DO8: require | DZ8: require | EA8: require | EC8: require | EE8: require | EF8: require | EG8: require | EH8: require | EJ8: require | EK8: require | EL8: require | ET8: require | EX8: require | HA8: require | HB8: require
A9: 21691_disabled | BY9: disabled | BZ9: disabled | CA9: disabled | CB9: disabled | CE9: disabled | CF9: disabled | CG9: disabled | CH9: disabled | CI9: disabled | CJ9: disabled | CK9: disabled | CL9: disabled | CM9: disabled | CN9: disabled | CO9: disabled | CP9: disabled | CQ9: disabled | CR9: disabled | CS9: disabled | CT9: disabled | CU9: disabled | CV9: disabled | CX9: disabled
A10: 21691_condition_require | EY10: condition_require
A11: 21775_require | E11: require | L11: require | M11: require | N11: require | DA11: require | DO11: require | DZ11: require | EA11: require | EC11: require | EE11: require | EF11: require | EG11: require | EH11: require | EJ11: require | EK11: require | EL11: require | ET11: require | EX11: require | HA11: require | HB11: require
A12: 21775_disabled | CE12: disabled | CF12: disabled | CG12: disabled | CH12: disabled | CI12: disabled | CJ12: disabled | CK12: disabled | CM12: disabled | CN12: disabled | CO12: disabled | CP12: disabled | CQ12: disabled | CR12: disabled | CS12: disabled | CT12: disabled | CU12: disabled | CV12: disabled | CW12: disabled | CX12: disabled | CY12: disabled | CZ12: disabled
A13: 21775_condition_require | EY13: condition_require
A14: 21785_require | E14: require | L14: require | M14: require | N14: require | DA14: require | DO14: require | DZ14: require | EA14: require | EC14: require | EE14: require | EF14: require | EG14: require | EH14: require | EJ14: require | EK14: require | EL14: require | ET14: require | EX14: require | HA14: require | HB14: require
A15: 21785_disabled | CF15: disabled | CG15: disabled | CH15: disabled | CI15: disabled | CJ15: disabled | CK15: disabled | CM15: disabled | CN15: disabled | CO15: disabled | CP15: disabled | CQ15: disabled | CR15: disabled | CS15: disabled | CT15: disabled | CU15: disabled | CV15: disabled | CW15: disabled | CX15: disabled | CY15: disabled | CZ15: disabled
A16: 21785_condition_require | EY16: condition_require
A17: 21792_require | E17: require | L17: require | M17: require | N17: require | DA17: require | DO17: require | DZ17: require | EA17: require | EC17: require | EE17: require | EF17: require | EG17: require | EH17: require | EJ17: require | EK17: require | EL17: require | ET17: require | EX17: require | HA17: require | HB17: require
A18: 21792_disabled | BY18: disabled | BZ18: disabled | CA18: disabled | CB18: disabled | CI18: disabled | CJ18: disabled | CK18: disabled | CL18: disabled | CM18: disabled | CN18: disabled | CO18: disabled | CP18: disabled | CQ18: disabled | CR18: disabled | CS18: disabled | CT18: disabled | CU18: disabled | CV18: disabled | CW18: disabled | CX18: disabled | CY18: disabled | CZ18: disabled
A19: 21792_condition_require | EY19: condition_require
A20: 21842_require | E20: require | L20: require | M20: require | N20: require | DA20: require | DO20: require | DZ20: require | EA20: require | EC20: require | EE20: require | EF20: require | EG20: require | EH20: require | EJ20: require | EK20: require | EL20: require | ET20: require | EX20: require | HA20: require | HB20: require
A21: 21842_disabled | BY21: disabled | BZ21: disabled | CA21: disabled | CB21: disabled | CE21: disabled | CF21: disabled | CG21: disabled | CH21: disabled | CI21: disabled | CJ21: disabled | CK21: disabled | CL21: disabled | CM21: disabled | CT21: disabled | CU21: disabled | CV21: disabled | CW21: disabled | CX21: disabled | CY21: disabled | CZ21: disabled
A22: 21842_condition_require | EY22: condition_require
A23: 21873_require | E23: require | L23: require | M23: require | N23: require | CM23: require | DA23: require | DO23: require | DZ23: require | EA23: require | EC23: require | EE23: require | EF23: require | EG23: require | EH23: require | EJ23: require | EK23: require | EL23: require | ET23: require | EX23: require | HA23: require | HB23: require
A24: 21873_disabled | BY24: disabled | BZ24: disabled | CA24: disabled | CB24: disabled | CF24: disabled | CG24: disabled | CH24: disabled | CN24: disabled | CO24: disabled | CP24: disabled | CQ24: disabled | CR24: disabled | CS24: disabled | CT24: disabled | CU24: disabled | CV24: disabled | CW24: disabled | CX24: disabled | CY24: disabled | CZ24: disabled
A25: 21873_condition_require | EY25: condition_require
A26: 21903_require | E26: require | L26: require | M26: require | N26: require | DA26: require | DO26: require | DZ26: require | EA26: require | EC26: require | EE26: require | EF26: require | EG26: require | EH26: require | EJ26: require | EK26: require | EL26: require | ET26: require | EX26: require | HA26: require | HB26: require
A27: 21903_disabled | BY27: disabled | BZ27: disabled | CA27: disabled | CB27: disabled | CF27: disabled | CG27: disabled | CH27: disabled | CI27: disabled | CJ27: disabled | CK27: disabled | CL27: disabled | CM27: disabled | CN27: disabled | CO27: disabled | CW27: disabled | CX27: disabled | CY27: disabled | CZ27: disabled
A28: 21903_condition_require | CU28: condition_require | CV28: condition_require | EY28: condition_require
A29: 22184_require | E29: require | L29: require | M29: require | N29: require | DA29: require | DO29: require | DZ29: require | EA29: require | EC29: require | EE29: require | EF29: require | EG29: require | EH29: require | EJ29: require | EK29: require | EL29: require | ET29: require | EX29: require | HA29: require | HB29: require
A30: 22184_disabled | BY30: disabled | BZ30: disabled | CA30: disabled | CB30: disabled | CI30: disabled | CJ30: disabled | CK30: disabled | CL30: disabled | CM30: disabled | CN30: disabled | CO30: disabled | CP30: disabled | CQ30: disabled | CR30: disabled | CS30: disabled | CT30: disabled | CU30: disabled | CV30: disabled | CW30: disabled | CX30: disabled | CY30: disabled | CZ30: disabled
A31: 22184_condition_require | EY31: condition_require
A32: 22226_require | E32: require | L32: require | M32: require | N32: require | DA32: require | DO32: require | DZ32: require | EA32: require | EC32: require | EE32: require | EF32: require | EG32: require | EH32: require | EJ32: require | EK32: require | EL32: require | ET32: require | EX32: require | HA32: require | HB32: require
A33: 22226_disabled | BY33: disabled | BZ33: disabled | CA33: disabled | CB33: disabled | CF33: disabled | CG33: disabled | CH33: disabled | CI33: disabled | CJ33: disabled | CK33: disabled | CL33: disabled | CM33: disabled | CN33: disabled | CO33: disabled | CP33: disabled | CQ33: disabled | CR33: disabled | CS33: disabled | CT33: disabled | CU33: disabled | CV33: disabled | CW33: disabled | CX33: disabled | CY33: disabled | CZ33: disabled
A34: 22226_condition_require | EY34: condition_require
A35: 22229_require | E35: require | L35: require | M35: require | N35: require | CH35: require | DA35: require | DO35: require | DZ35: require | EA35: require | EC35: require | EE35: require | EF35: require | EG35: require | EH35: require | EJ35: require | EK35: require | EL35: require | ET35: require | EX35: require | HA35: require | HB35: require
A36: 22229_disabled | CF36: disabled | CG36: disabled | CI36: disabled | CJ36: disabled | CK36: disabled | CL36: disabled | CM36: disabled | CN36: disabled | CO36: disabled | CP36: disabled | CQ36: disabled | CR36: disabled | CS36: disabled | CT36: disabled | CU36: disabled | CV36: disabled | CW36: disabled | CX36: disabled | CY36: disabled | CZ36: disabled
A37: 22229_condition_require | EY37: condition_require

Sheet Daten durchsuchen
A1: 21680 | B1: Automobil / Ersatzteile / Abgase & Emissionen / Auspuffrohre & -Endrohre
A2: 21792 | B2: Automobil / Ersatzteile / Karosserie & Zierleisten / Körper / Kühlergrills
A3: 21873 | B3: Automobil / Ersatzteile / Karosserie & Zierleisten / Körper / Spiegel & Teile / Außenspiegel
A4: 21842 | B4: Automobil / Ersatzteile / Karosserie & Zierleisten / Körper / Beleuchtungsbaugruppen / Scheinwerferbaugruppen, Teile & Zubehör / Scheinwerferbaugruppen
A5: 22226 | B5: Automobil / Außenzubehör / Spoiler-, Flügel- & Styling-Kits / Frontspoiler
A6: 22229 | B6: Automobil / Außenzubehör / Spoiler-, Flügel- & Styling-Kits / Spoiler
A7: 22184 | B7: Automobil / Außenzubehör / Kühlergrills & Grillschutzgitter / Kühlergrills
A8: 21785 | B8: Automobil / Ersatzteile / Karosserie & Zierleisten / Körper / Karosseriesätze
A9: 21226 | B9: Automobil / Ersatzteile / Beleuchtung & Elektrik / Beleuchtung
A10: 21691 | B10: Automobil / Ersatzteile / Stoßdämpfer, Federbeine & Aufhängung / Dämpfer
A11: 21775 | B11: Automobil / Ersatzteile / Stoßdämpfer, Federbeine & Aufhängung / Stoßdämpfer
A12: 21903 | B12: Automobil / Ersatzteile / Karosserie & Zierleisten / Blende / Innenraum / Innenraumschalter / Multifunktional

Sheet Conditions List
A1: t_1_Verarbeitungsverfahren zur Anpassung | B1: condition_4381B80A439A39F98F41275128C83798 | C1: Kundenspezifisches Produkt
A2: t_1_Primärverfahren | B2: condition_67587732A1B332119E13084DE0D1D4D5 | C2: Einzelverfahren | D2: Kombinierte Verfahren
A3: t_1_Sekundärverfahren | B3: condition_D89F7DAB83D73B69B2C7FB60524C7A01 | C3: Technik zur Anpassung von Metallprodukten | D3: Leder-/Stoff-Personalisierungstechnik | E3: Technik zur Anpassung von Holzprodukten | F3: Anpassungstechnik für organische Materialien (z. B. Acryl/Harz) | G3: Leinwand-/Papier-Anpassungstechnik
A4: t_3_4109 - Echte Ledersorte | B4: condition_E2AB879EB2193CA5997BBA62B425B82B | C4: Echt
A5: t_3_7317 - Holzart | B5: condition_2153A031F33F3106B22BB29F7635A1EE | C5: Hergestellt aus anderen Pflanzenmaterialien | D5: Gefährdetes Holz | E5: Rohholz | F5: Holzfaserplatte | G5: Laminat | H5: Kork | I5: Anderes Holz
A6: t_3_7318 - Holzarten | B6: condition_3E6C9B44DDBA3A4983AD8311EAD6F8BD | C6: Protokoll
A7: t_3_1450 - OEM-Nummer | B7: condition_234F940DDF4239A397F64CC529F286CC | C7: Produktdetails ansehen
A8: t_3_2147 - Wiederaufladbare Batterie | B8: condition_F51258181CDB39ADBC8E70EDCF0F6ED3 | C8: Wiederaufladbare Batterie
A9: t_3_2154 - Solarbatterie | B9: condition_A135562AC54F3386BD85DC491A9B74B0 | C9: Solarbatterie
A10: t_3_3740 - Nicht wiederaufladbare Batterie | B10: condition_12556C4DE26B361AA913A6EB69237C76 | C10: Nicht wiederaufladbare Batterie
A11: t_3_1132 - Betriebsspannung | B11: condition_9D1140D2328E30789698E2417AB422EF | C11: Elektrische/Festverdrahtung im Zimmer | D11: USB | E11: OBD-Anschluss | F11: Batteriebetrieben/USB-Dual-Use | G11: USB-Aufladung | H11: Batteriebetrieben | I11: Stromversorgung | J11: Zigarettenanzünder eingesteckt | K11: Batterie/Strom für zwei Zwecke | L11: Solarbetrieben
A12: t_3_1485 - Steckertyp | B12: condition_07F44E89E1A53DBDA857211760CB6FEC | C12: Stromversorgung | D12: Batterie/Strom für zwei Zwecke
A13: t_4_Farbe | B13: condition_1516982AA4AD3EA098CF8DE8CAB04154 | C13: Farbe | D13: Anwendbare Personen × Farbe | E13: Aromen × Farbe | F13: Artikel × Farbe | G13: Farbe × Gewicht | H13: Farbe × Größe | I13: Farbe × Haarlänge | J13: Farbe × Kapazität | K13: Farbe × Komposition | L13: Farbe × Material | M13: Farbe × Menge | N13: Farbe × Modell | O13: Farbe × Stil | P13: Farbe | Q13: Anwendbare Personen × Farbe | R13: Aromen × Farbe | S13: Artikel × Farbe | T13: Farbe × Gewicht | U13: Farbe × Größe | V13: Farbe × Haarlänge | W13: Farbe × Kapazität | X13: Farbe × Komposition | Y13: Farbe × Material | Z13: Farbe × Menge | AA13: Farbe × Modell | AB13: Farbe × Stil | AC13: Farbe | AD13: Anwendbare Personen × Farbe | AE13: Aromen × Farbe | AF13: Artikel × Farbe | AG13: Farbe × Gewicht | AH13: Farbe × Größe | AI13: Farbe × Haarlänge | AJ13: Farbe × Kapazität | AK13: Farbe × Komposition | AL13: Farbe × Material | AM13: Farbe × Menge | AN13: Farbe × Modell | AO13: Farbe × Stil | AP13: Farbe | AQ13: Anwendbare Personen × Farbe | AR13: Aromen × Farbe | AS13: Artikel × Farbe | AT13: Farbe × Gewicht | AU13: Farbe × Größe | AV13: Farbe × Haarlänge | AW13: Farbe × Kapazität | AX13: Farbe × Komposition | AY13: Farbe × Material | AZ13: Farbe × Menge | BA13: Farbe × Modell | BB13: Farbe × Stil | BC13: Farbe | BD13: Anwendbare Personen × Farbe | BE13: Aromen × Farbe | BF13: Artikel × Farbe | BG13: Farbe × Gewicht | BH13: Farbe × Größe | BI13: Farbe × Haarlänge | BJ13: Farbe × Kapazität | BK13: Farbe × Komposition | BL13: Farbe × Material | BM13: Farbe × Menge | BN13: Farbe × Modell | BO13: Farbe × Stil | BP13: Farbe | BQ13: Anwendbare Personen × Farbe | BR13: Aromen × Farbe | BS13: Artikel × Farbe | BT13: Farbe × Gewicht | BU13: Farbe × Größe | BV13: Farbe × Haarlänge | BW13: Farbe × Kapazität | BX13: Farbe × Komposition | BY13: Farbe × Material | BZ13: Farbe × Menge | CA13: Farbe × Modell | CB13: Farbe × Stil | CC13: Farbe | CD13: Anwendbare Personen × Farbe | CE13: Aromen × Farbe | CF13: Artikel × Farbe | CG13: Farbe × Gewicht | CH13: Farbe × Größe | CI13: Farbe × Haarlänge | CJ13: Farbe × Kapazität | CK13: Farbe × Komposition | CL13: Farbe × Material | CM13: Farbe × Menge | CN13: Farbe × Modell | CO13: Farbe × Stil | CP13: Farbe | CQ13: Anwendbare Personen × Farbe | CR13: Aromen × Farbe | CS13: Artikel × Farbe | CT13: Farbe × Gewicht | CU13: Farbe × Größe | CV13: Farbe × Haarlänge | CW13: Farbe × Kapazität | CX13: Farbe × Komposition | CY13: Farbe × Material | CZ13: Farbe × Menge | DA13: Farbe × Modell | DB13: Farbe × Stil | DC13: Farbe | DD13: Anwendbare Personen × Farbe | DE13: Aromen × Farbe | DF13: Artikel × Farbe | DG13: Farbe × Gewicht | DH13: Farbe × Größe | DI13: Farbe × Haarlänge | DJ13: Farbe × Kapazität | DK13: Farbe × Komposition | DL13: Farbe × Material | DM13: Farbe × Menge | DN13: Farbe × Modell | DO13: Farbe × Stil | DP13: Farbe | DQ13: Anwendbare Personen × Farbe | DR13: Aromen × Farbe | DS13: Artikel × Farbe | DT13: Farbe × Gewicht | DU13: Farbe × Größe | DV13: Farbe × Haarlänge | DW13: Farbe × Kapazität | DX13: Farbe × Komposition | DY13: Farbe × Material | DZ13: Farbe × Menge | EA13: Farbe × Modell | EB13: Farbe × Stil | EC13: Farbe | ED13: Anwendbare Personen × Farbe | EE13: Aromen × Farbe | EF13: Artikel × Farbe | EG13: Farbe × Gewicht | EH13: Farbe × Größe | EI13: Farbe × Haarlänge | EJ13: Farbe × Kapazität | EK13: Farbe × Komposition | EL13: Farbe × Material | EM13: Farbe × Menge | EN13: Farbe × Modell | EO13: Farbe × Stil | EP13: Farbe | EQ13: Anwendbare Personen × Farbe | ER13: Aromen × Farbe | ES13: Artikel × Farbe | ET13: Farbe × Gewicht | EU13: Farbe × Größe | EV13: Farbe × Haarlänge | EW13: Farbe × Kapazität | EX13: Farbe × Komposition | EY13: Farbe × Material | EZ13: Farbe × Menge | FA13: Farbe × Modell | FB13: Farbe × Stil
A14: t_4_Größe | B14: condition_810999319F4D32A9BBBA00887E92C228 | C14: Größe | D14: Anwendbare Personen × Größe | E14: Aromen × Größe | F14: Artikel × Größe | G14: Farbe × Größe | H14: Gewicht × Größe | I14: Größe × Haarlänge | J14: Größe × Kapazität | K14: Größe × Komposition | L14: Größe × Material | M14: Größe × Menge | N14: Größe × Modell | O14: Größe × Stil | P14: Größe | Q14: Anwendbare Personen × Größe | R14: Aromen × Größe | S14: Artikel × Größe | T14: Farbe × Größe | U14: Gewicht × Größe | V14: Größe × Haarlänge | W14: Größe × Kapazität | X14: Größe × Komposition | Y14: Größe × Material | Z14: Größe × Menge | AA14: Größe × Modell | AB14: Größe × Stil | AC14: Größe | AD14: Anwendbare Personen × Größe | AE14: Aromen × Größe | AF14: Artikel × Größe | AG14: Farbe × Größe | AH14: Gewicht × Größe | AI14: Größe × Haarlänge | AJ14: Größe × Kapazität | AK14: Größe × Komposition | AL14: Größe × Material | AM14: Größe × Menge | AN14: Größe × Modell | AO14: Größe × Stil | AP14: Größe | AQ14: Anwendbare Personen × Größe | AR14: Aromen × Größe | AS14: Artikel × Größe | AT14: Farbe × Größe | AU14: Gewicht × Größe | AV14: Größe × Haarlänge | AW14: Größe × Kapazität | AX14: Größe × Komposition | AY14: Größe × Material | AZ14: Größe × Menge | BA14: Größe × Modell | BB14: Größe × Stil | BC14: Größe | BD14: Anwendbare Personen × Größe | BE14: Aromen × Größe | BF14: Artikel × Größe | BG14: Farbe × Größe | BH14: Gewicht × Größe | BI14: Größe × Haarlänge | BJ14: Größe × Kapazität | BK14: Größe × Komposition | BL14: Größe × Material | BM14: Größe × Menge | BN14: Größe × Modell | BO14: Größe × Stil | BP14: Größe | BQ14: Anwendbare Personen × Größe | BR14: Aromen × Größe | BS14: Artikel × Größe | BT14: Farbe × Größe | BU14: Gewicht × Größe | BV14: Größe × Haarlänge | BW14: Größe × Kapazität | BX14: Größe × Komposition | BY14: Größe × Material | BZ14: Größe × Menge | CA14: Größe × Modell | CB14: Größe × Stil | CC14: Größe | CD14: Anwendbare Personen × Größe | CE14: Aromen × Größe | CF14: Artikel × Größe | CG14: Farbe × Größe | CH14: Gewicht × Größe | CI14: Größe × Haarlänge | CJ14: Größe × Kapazität | CK14: Größe × Komposition | CL14: Größe × Material | CM14: Größe × Menge | CN14: Größe × Modell | CO14: Größe × Stil | CP14: Größe | CQ14: Anwendbare Personen × Größe | CR14: Aromen × Größe | CS14: Artikel × Größe | CT14: Farbe × Größe | CU14: Gewicht × Größe | CV14: Größe × Haarlänge | CW14: Größe × Kapazität | CX14: Größe × Komposition | CY14: Größe × Material | CZ14: Größe × Menge | DA14: Größe × Modell | DB14: Größe × Stil | DC14: Größe | DD14: Anwendbare Personen × Größe | DE14: Aromen × Größe | DF14: Artikel × Größe | DG14: Farbe × Größe | DH14: Gewicht × Größe | DI14: Größe × Haarlänge | DJ14: Größe × Kapazität | DK14: Größe × Komposition | DL14: Größe × Material | DM14: Größe × Menge | DN14: Größe × Modell | DO14: Größe × Stil | DP14: Größe | DQ14: Anwendbare Personen × Größe | DR14: Aromen × Größe | DS14: Artikel × Größe | DT14: Farbe × Größe | DU14: Gewicht × Größe | DV14: Größe × Haarlänge | DW14: Größe × Kapazität | DX14: Größe × Komposition | DY14: Größe × Material | DZ14: Größe × Menge | EA14: Größe × Modell | EB14: Größe × Stil | EC14: Größe | ED14: Anwendbare Personen × Größe | EE14: Aromen × Größe | EF14: Artikel × Größe | EG14: Farbe × Größe | EH14: Gewicht × Größe | EI14: Größe × Haarlänge | EJ14: Größe × Kapazität | EK14: Größe × Komposition | EL14: Größe × Material | EM14: Größe × Menge | EN14: Größe × Modell | EO14: Größe × Stil | EP14: Größe | EQ14: Anwendbare Personen × Größe | ER14: Aromen × Größe | ES14: Artikel × Größe | ET14: Farbe × Größe | EU14: Gewicht × Größe | EV14: Größe × Haarlänge | EW14: Größe × Kapazität | EX14: Größe × Komposition | EY14: Größe × Material | EZ14: Größe × Menge | FA14: Größe × Modell | FB14: Größe × Stil
A15: t_4_Stil | B15: condition_AAE0AE3367A73FE986F1D1207759AD6B | C15: Stil | D15: Anwendbare Personen × Stil | E15: Aromen × Stil | F15: Artikel × Stil | G15: Farbe × Stil | H15: Gewicht × Stil | I15: Größe × Stil | J15: Haarlänge × Stil | K15: Kapazität × Stil | L15: Komposition × Stil | M15: Material × Stil | N15: Menge × Stil | O15: Modell × Stil | P15: Stil | Q15: Anwendbare Personen × Stil | R15: Aromen × Stil | S15: Artikel × Stil | T15: Farbe × Stil | U15: Gewicht × Stil | V15: Größe × Stil | W15: Haarlänge × Stil | X15: Kapazität × Stil | Y15: Komposition × Stil | Z15: Material × Stil | AA15: Menge × Stil | AB15: Modell × Stil | AC15: Stil | AD15: Anwendbare Personen × Stil | AE15: Aromen × Stil | AF15: Artikel × Stil | AG15: Farbe × Stil | AH15: Gewicht × Stil | AI15: Größe × Stil | AJ15: Haarlänge × Stil | AK15: Kapazität × Stil | AL15: Komposition × Stil | AM15: Material × Stil | AN15: Menge × Stil | AO15: Modell × Stil | AP15: Stil | AQ15: Anwendbare Personen × Stil | AR15: Aromen × Stil | AS15: Artikel × Stil | AT15: Farbe × Stil | AU15: Gewicht × Stil | AV15: Größe × Stil | AW15: Haarlänge × Stil | AX15: Kapazität × Stil | AY15: Komposition × Stil | AZ15: Material × Stil | BA15: Menge × Stil | BB15: Modell × Stil | BC15: Stil | BD15: Anwendbare Personen × Stil | BE15: Aromen × Stil | BF15: Artikel × Stil | BG15: Farbe × Stil | BH15: Gewicht × Stil | BI15: Größe × Stil | BJ15: Haarlänge × Stil | BK15: Kapazität × Stil | BL15: Komposition × Stil | BM15: Material × Stil | BN15: Menge × Stil | BO15: Modell × Stil | BP15: Stil | BQ15: Anwendbare Personen × Stil | BR15: Aromen × Stil | BS15: Artikel × Stil | BT15: Farbe × Stil | BU15: Gewicht × Stil | BV15: Größe × Stil | BW15: Haarlänge × Stil | BX15: Kapazität × Stil | BY15: Komposition × Stil | BZ15: Material × Stil | CA15: Menge × Stil | CB15: Modell × Stil | CC15: Stil | CD15: Anwendbare Personen × Stil | CE15: Aromen × Stil | CF15: Artikel × Stil | CG15: Farbe × Stil | CH15: Gewicht × Stil | CI15: Größe × Stil | CJ15: Haarlänge × Stil | CK15: Kapazität × Stil | CL15: Komposition × Stil | CM15: Material × Stil | CN15: Menge × Stil | CO15: Modell × Stil | CP15: Stil | CQ15: Anwendbare Personen × Stil | CR15: Aromen × Stil | CS15: Artikel × Stil | CT15: Farbe × Stil | CU15: Gewicht × Stil | CV15: Größe × Stil | CW15: Haarlänge × Stil | CX15: Kapazität × Stil | CY15: Komposition × Stil | CZ15: Material × Stil | DA15: Menge × Stil | DB15: Modell × Stil | DC15: Stil | DD15: Anwendbare Personen × Stil | DE15: Aromen × Stil | DF15: Artikel × Stil | DG15: Farbe × Stil | DH15: Gewicht × Stil | DI15: Größe × Stil | DJ15: Haarlänge × Stil | DK15: Kapazität × Stil | DL15: Komposition × Stil | DM15: Material × Stil | DN15: Menge × Stil | DO15: Modell × Stil | DP15: Stil | DQ15: Anwendbare Personen × Stil | DR15: Aromen × Stil | DS15: Artikel × Stil | DT15: Farbe × Stil | DU15: Gewicht × Stil | DV15: Größe × Stil | DW15: Haarlänge × Stil | DX15: Kapazität × Stil | DY15: Komposition × Stil | DZ15: Material × Stil | EA15: Menge × Stil | EB15: Modell × Stil | EC15: Stil | ED15: Anwendbare Personen × Stil | EE15: Aromen × Stil | EF15: Artikel × Stil | EG15: Farbe × Stil | EH15: Gewicht × Stil | EI15: Größe × Stil | EJ15: Haarlänge × Stil | EK15: Kapazität × Stil | EL15: Komposition × Stil | EM15: Material × Stil | EN15: Menge × Stil | EO15: Modell × Stil | EP15: Stil | EQ15: Anwendbare Personen × Stil | ER15: Aromen × Stil | ES15: Artikel × Stil | ET15: Farbe × Stil | EU15: Gewicht × Stil | EV15: Größe × Stil | EW15: Haarlänge × Stil | EX15: Kapazität × Stil | EY15: Komposition × Stil | EZ15: Material × Stil | FA15: Menge × Stil | FB15: Modell × Stil
A16: t_4_Material | B16: condition_C19B0EBADE90385AB85E1D43AF04316A | C16: Material | D16: Anwendbare Personen × Material | E16: Aromen × Material | F16: Artikel × Material | G16: Farbe × Material | H16: Gewicht × Material | I16: Größe × Material | J16: Haarlänge × Material | K16: Kapazität × Material | L16: Komposition × Material | M16: Material × Menge | N16: Material × Modell | O16: Material × Stil | P16: Material | Q16: Anwendbare Personen × Material | R16: Aromen × Material | S16: Artikel × Material | T16: Farbe × Material | U16: Gewicht × Material | V16: Größe × Material | W16: Haarlänge × Material | X16: Kapazität × Material | Y16: Komposition × Material | Z16: Material × Menge | AA16: Material × Modell | AB16: Material × Stil | AC16: Material | AD16: Anwendbare Personen × Material | AE16: Aromen × Material | AF16: Artikel × Material | AG16: Farbe × Material | AH16: Gewicht × Material | AI16: Größe × Material | AJ16: Haarlänge × Material | AK16: Kapazität × Material | AL16: Komposition × Material | AM16: Material × Menge | AN16: Material × Modell | AO16: Material × Stil | AP16: Material | AQ16: Anwendbare Personen × Material | AR16: Aromen × Material | AS16: Artikel × Material | AT16: Farbe × Material | AU16: Gewicht × Material | AV16: Größe × Material | AW16: Haarlänge × Material | AX16: Kapazität × Material | AY16: Komposition × Material | AZ16: Material × Menge | BA16: Material × Modell | BB16: Material × Stil | BC16: Material | BD16: Anwendbare Personen × Material | BE16: Aromen × Material | BF16: Artikel × Material | BG16: Farbe × Material | BH16: Gewicht × Material | BI16: Größe × Material | BJ16: Haarlänge × Material | BK16: Kapazität × Material | BL16: Komposition × Material | BM16: Material × Menge | BN16: Material × Modell | BO16: Material × Stil | BP16: Material | BQ16: Anwendbare Personen × Material | BR16: Aromen × Material | BS16: Artikel × Material | BT16: Farbe × Material | BU16: Gewicht × Material | BV16: Größe × Material | BW16: Haarlänge × Material | BX16: Kapazität × Material | BY16: Komposition × Material | BZ16: Material × Menge | CA16: Material × Modell | CB16: Material × Stil | CC16: Material | CD16: Anwendbare Personen × Material | CE16: Aromen × Material | CF16: Artikel × Material | CG16: Farbe × Material | CH16: Gewicht × Material | CI16: Größe × Material | CJ16: Haarlänge × Material | CK16: Kapazität × Material | CL16: Komposition × Material | CM16: Material × Menge | CN16: Material × Modell | CO16: Material × Stil | CP16: Material | CQ16: Anwendbare Personen × Material | CR16: Aromen × Material | CS16: Artikel × Material | CT16: Farbe × Material | CU16: Gewicht × Material | CV16: Größe × Material | CW16: Haarlänge × Material | CX16: Kapazität × Material | CY16: Komposition × Material | CZ16: Material × Menge | DA16: Material × Modell | DB16: Material × Stil | DC16: Material | DD16: Anwendbare Personen × Material | DE16: Aromen × Material | DF16: Artikel × Material | DG16: Farbe × Material | DH16: Gewicht × Material | DI16: Größe × Material | DJ16: Haarlänge × Material | DK16: Kapazität × Material | DL16: Komposition × Material | DM16: Material × Menge | DN16: Material × Modell | DO16: Material × Stil | DP16: Material | DQ16: Anwendbare Personen × Material | DR16: Aromen × Material | DS16: Artikel × Material | DT16: Farbe × Material | DU16: Gewicht × Material | DV16: Größe × Material | DW16: Haarlänge × Material | DX16: Kapazität × Material | DY16: Komposition × Material | DZ16: Material × Menge | EA16: Material × Modell | EB16: Material × Stil | EC16: Material | ED16: Anwendbare Personen × Material | EE16: Aromen × Material | EF16: Artikel × Material | EG16: Farbe × Material | EH16: Gewicht × Material | EI16: Größe × Material | EJ16: Haarlänge × Material | EK16: Kapazität × Material | EL16: Komposition × Material | EM16: Material × Menge | EN16: Material × Modell | EO16: Material × Stil | EP16: Material | EQ16: Anwendbare Personen × Material | ER16: Aromen × Material | ES16: Artikel × Material | ET16: Farbe × Material | EU16: Gewicht × Material | EV16: Größe × Material | EW16: Haarlänge × Material | EX16: Kapazität × Material | EY16: Komposition × Material | EZ16: Material × Menge | FA16: Material × Modell | FB16: Material × Stil
A17: t_4_Aromen | B17: condition_369C7F57F4C23BAAAFA42AEC2D3341D3 | C17: Aromen | D17: Anwendbare Personen × Aromen | E17: Aromen × Artikel | F17: Aromen × Farbe | G17: Aromen × Gewicht | H17: Aromen × Größe | I17: Aromen × Haarlänge | J17: Aromen × Kapazität | K17: Aromen × Komposition | L17: Aromen × Material | M17: Aromen × Menge | N17: Aromen × Modell | O17: Aromen × Stil | P17: Aromen | Q17: Anwendbare Personen × Aromen | R17: Aromen × Artikel | S17: Aromen × Farbe | T17: Aromen × Gewicht | U17: Aromen × Größe | V17: Aromen × Haarlänge | W17: Aromen × Kapazität | X17: Aromen × Komposition | Y17: Aromen × Material | Z17: Aromen × Menge | AA17: Aromen × Modell | AB17: Aromen × Stil | AC17: Aromen | AD17: Anwendbare Personen × Aromen | AE17: Aromen × Artikel | AF17: Aromen × Farbe | AG17: Aromen × Gewicht | AH17: Aromen × Größe | AI17: Aromen × Haarlänge | AJ17: Aromen × Kapazität | AK17: Aromen × Komposition | AL17: Aromen × Material | AM17: Aromen × Menge | AN17: Aromen × Modell | AO17: Aromen × Stil | AP17: Aromen | AQ17: Anwendbare Personen × Aromen | AR17: Aromen × Artikel | AS17: Aromen × Farbe | AT17: Aromen × Gewicht | AU17: Aromen × Größe | AV17: Aromen × Haarlänge | AW17: Aromen × Kapazität | AX17: Aromen × Komposition | AY17: Aromen × Material | AZ17: Aromen × Menge | BA17: Aromen × Modell | BB17: Aromen × Stil | BC17: Aromen | BD17: Anwendbare Personen × Aromen | BE17: Aromen × Artikel | BF17: Aromen × Farbe | BG17: Aromen × Gewicht | BH17: Aromen × Größe | BI17: Aromen × Haarlänge | BJ17: Aromen × Kapazität | BK17: Aromen × Komposition | BL17: Aromen × Material | BM17: Aromen × Menge | BN17: Aromen × Modell | BO17: Aromen × Stil | BP17: Aromen | BQ17: Anwendbare Personen × Aromen | BR17: Aromen × Artikel | BS17: Aromen × Farbe | BT17: Aromen × Gewicht | BU17: Aromen × Größe | BV17: Aromen × Haarlänge | BW17: Aromen × Kapazität | BX17: Aromen × Komposition | BY17: Aromen × Material | BZ17: Aromen × Menge | CA17: Aromen × Modell | CB17: Aromen × Stil | CC17: Aromen | CD17: Anwendbare Personen × Aromen | CE17: Aromen × Artikel | CF17: Aromen × Farbe | CG17: Aromen × Gewicht | CH17: Aromen × Größe | CI17: Aromen × Haarlänge | CJ17: Aromen × Kapazität | CK17: Aromen × Komposition | CL17: Aromen × Material | CM17: Aromen × Menge | CN17: Aromen × Modell | CO17: Aromen × Stil | CP17: Aromen | CQ17: Anwendbare Personen × Aromen | CR17: Aromen × Artikel | CS17: Aromen × Farbe | CT17: Aromen × Gewicht | CU17: Aromen × Größe | CV17: Aromen × Haarlänge | CW17: Aromen × Kapazität | CX17: Aromen × Komposition | CY17: Aromen × Material | CZ17: Aromen × Menge | DA17: Aromen × Modell | DB17: Aromen × Stil | DC17: Aromen | DD17: Anwendbare Personen × Aromen | DE17: Aromen × Artikel | DF17: Aromen × Farbe | DG17: Aromen × Gewicht | DH17: Aromen × Größe | DI17: Aromen × Haarlänge | DJ17: Aromen × Kapazität | DK17: Aromen × Komposition | DL17: Aromen × Material | DM17: Aromen × Menge | DN17: Aromen × Modell | DO17: Aromen × Stil | DP17: Aromen | DQ17: Anwendbare Personen × Aromen | DR17: Aromen × Artikel | DS17: Aromen × Farbe | DT17: Aromen × Gewicht | DU17: Aromen × Größe | DV17: Aromen × Haarlänge | DW17: Aromen × Kapazität | DX17: Aromen × Komposition | DY17: Aromen × Material | DZ17: Aromen × Menge | EA17: Aromen × Modell | EB17: Aromen × Stil | EC17: Aromen | ED17: Anwendbare Personen × Aromen | EE17: Aromen × Artikel | EF17: Aromen × Farbe | EG17: Aromen × Gewicht | EH17: Aromen × Größe | EI17: Aromen × Haarlänge | EJ17: Aromen × Kapazität | EK17: Aromen × Komposition | EL17: Aromen × Material | EM17: Aromen × Menge | EN17: Aromen × Modell | EO17: Aromen × Stil | EP17: Aromen | EQ17: Anwendbare Personen × Aromen | ER17: Aromen × Artikel | ES17: Aromen × Farbe | ET17: Aromen × Gewicht | EU17: Aromen × Größe | EV17: Aromen × Haarlänge | EW17: Aromen × Kapazität | EX17: Aromen × Komposition | EY17: Aromen × Material | EZ17: Aromen × Menge | FA17: Aromen × Modell | FB17: Aromen × Stil
A18: t_4_Anwendbare Personen | B18: condition_D2A70D56696C3080902D19A458636473 | C18: Anwendbare Personen | D18: Anwendbare Personen × Aromen | E18: Anwendbare Personen × Artikel | F18: Anwendbare Personen × Farbe | G18: Anwendbare Personen × Gewicht | H18: Anwendbare Personen × Größe | I18: Anwendbare Personen × Haarlänge | J18: Anwendbare Personen × Kapazität | K18: Anwendbare Personen × Komposition | L18: Anwendbare Personen × Material | M18: Anwendbare Personen × Menge | N18: Anwendbare Personen × Modell | O18: Anwendbare Personen × Stil | P18: Anwendbare Personen | Q18: Anwendbare Personen × Aromen | R18: Anwendbare Personen × Artikel | S18: Anwendbare Personen × Farbe | T18: Anwendbare Personen × Gewicht | U18: Anwendbare Personen × Größe | V18: Anwendbare Personen × Haarlänge | W18: Anwendbare Personen × Kapazität | X18: Anwendbare Personen × Komposition | Y18: Anwendbare Personen × Material | Z18: Anwendbare Personen × Menge | AA18: Anwendbare Personen × Modell | AB18: Anwendbare Personen × Stil | AC18: Anwendbare Personen | AD18: Anwendbare Personen × Aromen | AE18: Anwendbare Personen × Artikel | AF18: Anwendbare Personen × Farbe | AG18: Anwendbare Personen × Gewicht | AH18: Anwendbare Personen × Größe | AI18: Anwendbare Personen × Haarlänge | AJ18: Anwendbare Personen × Kapazität | AK18: Anwendbare Personen × Komposition | AL18: Anwendbare Personen × Material | AM18: Anwendbare Personen × Menge | AN18: Anwendbare Personen × Modell | AO18: Anwendbare Personen × Stil | AP18: Anwendbare Personen | AQ18: Anwendbare Personen × Aromen | AR18: Anwendbare Personen × Artikel | AS18: Anwendbare Personen × Farbe | AT18: Anwendbare Personen × Gewicht | AU18: Anwendbare Personen × Größe | AV18: Anwendbare Personen × Haarlänge | AW18: Anwendbare Personen × Kapazität | AX18: Anwendbare Personen × Komposition | AY18: Anwendbare Personen × Material | AZ18: Anwendbare Personen × Menge | BA18: Anwendbare Personen × Modell | BB18: Anwendbare Personen × Stil | BC18: Anwendbare Personen | BD18: Anwendbare Personen × Aromen | BE18: Anwendbare Personen × Artikel | BF18: Anwendbare Personen × Farbe | BG18: Anwendbare Personen × Gewicht | BH18: Anwendbare Personen × Größe | BI18: Anwendbare Personen × Haarlänge | BJ18: Anwendbare Personen × Kapazität | BK18: Anwendbare Personen × Komposition | BL18: Anwendbare Personen × Material | BM18: Anwendbare Personen × Menge | BN18: Anwendbare Personen × Modell | BO18: Anwendbare Personen × Stil | BP18: Anwendbare Personen | BQ18: Anwendbare Personen × Aromen | BR18: Anwendbare Personen × Artikel | BS18: Anwendbare Personen × Farbe | BT18: Anwendbare Personen × Gewicht | BU18: Anwendbare Personen × Größe | BV18: Anwendbare Personen × Haarlänge | BW18: Anwendbare Personen × Kapazität | BX18: Anwendbare Personen × Komposition | BY18: Anwendbare Personen × Material | BZ18: Anwendbare Personen × Menge | CA18: Anwendbare Personen × Modell | CB18: Anwendbare Personen × Stil | CC18: Anwendbare Personen | CD18: Anwendbare Personen × Aromen | CE18: Anwendbare Personen × Artikel | CF18: Anwendbare Personen × Farbe | CG18: Anwendbare Personen × Gewicht | CH18: Anwendbare Personen × Größe | CI18: Anwendbare Personen × Haarlänge | CJ18: Anwendbare Personen × Kapazität | CK18: Anwendbare Personen × Komposition | CL18: Anwendbare Personen × Material | CM18: Anwendbare Personen × Menge | CN18: Anwendbare Personen × Modell | CO18: Anwendbare Personen × Stil | CP18: Anwendbare Personen | CQ18: Anwendbare Personen × Aromen | CR18: Anwendbare Personen × Artikel | CS18: Anwendbare Personen × Farbe | CT18: Anwendbare Personen × Gewicht | CU18: Anwendbare Personen × Größe | CV18: Anwendbare Personen × Haarlänge | CW18: Anwendbare Personen × Kapazität | CX18: Anwendbare Personen × Komposition | CY18: Anwendbare Personen × Material | CZ18: Anwendbare Personen × Menge | DA18: Anwendbare Personen × Modell | DB18: Anwendbare Personen × Stil | DC18: Anwendbare Personen | DD18: Anwendbare Personen × Aromen | DE18: Anwendbare Personen × Artikel | DF18: Anwendbare Personen × Farbe | DG18: Anwendbare Personen × Gewicht | DH18: Anwendbare Personen × Größe | DI18: Anwendbare Personen × Haarlänge | DJ18: Anwendbare Personen × Kapazität | DK18: Anwendbare Personen × Komposition | DL18: Anwendbare Personen × Material | DM18: Anwendbare Personen × Menge | DN18: Anwendbare Personen × Modell | DO18: Anwendbare Personen × Stil | DP18: Anwendbare Personen | DQ18: Anwendbare Personen × Aromen | DR18: Anwendbare Personen × Artikel | DS18: Anwendbare Personen × Farbe | DT18: Anwendbare Personen × Gewicht | DU18: Anwendbare Personen × Größe | DV18: Anwendbare Personen × Haarlänge | DW18: Anwendbare Personen × Kapazität | DX18: Anwendbare Personen × Komposition | DY18: Anwendbare Personen × Material | DZ18: Anwendbare Personen × Menge | EA18: Anwendbare Personen × Modell | EB18: Anwendbare Personen × Stil | EC18: Anwendbare Personen | ED18: Anwendbare Personen × Aromen | EE18: Anwendbare Personen × Artikel | EF18: Anwendbare Personen × Farbe | EG18: Anwendbare Personen × Gewicht | EH18: Anwendbare Personen × Größe | EI18: Anwendbare Personen × Haarlänge | EJ18: Anwendbare Personen × Kapazität | EK18: Anwendbare Personen × Komposition | EL18: Anwendbare Personen × Material | EM18: Anwendbare Personen × Menge | EN18: Anwendbare Personen × Modell | EO18: Anwendbare Personen × Stil | EP18: Anwendbare Personen | EQ18: Anwendbare Personen × Aromen | ER18: Anwendbare Personen × Artikel | ES18: Anwendbare Personen × Farbe | ET18: Anwendbare Personen × Gewicht | EU18: Anwendbare Personen × Größe | EV18: Anwendbare Personen × Haarlänge | EW18: Anwendbare Personen × Kapazität | EX18: Anwendbare Personen × Komposition | EY18: Anwendbare Personen × Material | EZ18: Anwendbare Personen × Menge | FA18: Anwendbare Personen × Modell | FB18: Anwendbare Personen × Stil
A19: t_4_Kapazität | B19: condition_F881F62A68A53C61A4A6EB5AF1320904 | C19: Kapazität | D19: Anwendbare Personen × Kapazität | E19: Aromen × Kapazität | F19: Artikel × Kapazität | G19: Farbe × Kapazität | H19: Gewicht × Kapazität | I19: Größe × Kapazität | J19: Haarlänge × Kapazität | K19: Kapazität × Komposition | L19: Kapazität × Material | M19: Kapazität × Menge | N19: Kapazität × Modell | O19: Kapazität × Stil | P19: Kapazität | Q19: Anwendbare Personen × Kapazität | R19: Aromen × Kapazität | S19: Artikel × Kapazität | T19: Farbe × Kapazität | U19: Gewicht × Kapazität | V19: Größe × Kapazität | W19: Haarlänge × Kapazität | X19: Kapazität × Komposition | Y19: Kapazität × Material | Z19: Kapazität × Menge | AA19: Kapazität × Modell | AB19: Kapazität × Stil | AC19: Kapazität | AD19: Anwendbare Personen × Kapazität | AE19: Aromen × Kapazität | AF19: Artikel × Kapazität | AG19: Farbe × Kapazität | AH19: Gewicht × Kapazität | AI19: Größe × Kapazität | AJ19: Haarlänge × Kapazität | AK19: Kapazität × Komposition | AL19: Kapazität × Material | AM19: Kapazität × Menge | AN19: Kapazität × Modell | AO19: Kapazität × Stil | AP19: Kapazität | AQ19: Anwendbare Personen × Kapazität | AR19: Aromen × Kapazität | AS19: Artikel × Kapazität | AT19: Farbe × Kapazität | AU19: Gewicht × Kapazität | AV19: Größe × Kapazität | AW19: Haarlänge × Kapazität | AX19: Kapazität × Komposition | AY19: Kapazität × Material | AZ19: Kapazität × Menge | BA19: Kapazität × Modell | BB19: Kapazität × Stil | BC19: Kapazität | BD19: Anwendbare Personen × Kapazität | BE19: Aromen × Kapazität | BF19: Artikel × Kapazität | BG19: Farbe × Kapazität | BH19: Gewicht × Kapazität | BI19: Größe × Kapazität | BJ19: Haarlänge × Kapazität | BK19: Kapazität × Komposition | BL19: Kapazität × Material | BM19: Kapazität × Menge | BN19: Kapazität × Modell | BO19: Kapazität × Stil | BP19: Kapazität | BQ19: Anwendbare Personen × Kapazität | BR19: Aromen × Kapazität | BS19: Artikel × Kapazität | BT19: Farbe × Kapazität | BU19: Gewicht × Kapazität | BV19: Größe × Kapazität | BW19: Haarlänge × Kapazität | BX19: Kapazität × Komposition | BY19: Kapazität × Material | BZ19: Kapazität × Menge | CA19: Kapazität × Modell | CB19: Kapazität × Stil | CC19: Kapazität | CD19: Anwendbare Personen × Kapazität | CE19: Aromen × Kapazität | CF19: Artikel × Kapazität | CG19: Farbe × Kapazität | CH19: Gewicht × Kapazität | CI19: Größe × Kapazität | CJ19: Haarlänge × Kapazität | CK19: Kapazität × Komposition | CL19: Kapazität × Material | CM19: Kapazität × Menge | CN19: Kapazität × Modell | CO19: Kapazität × Stil | CP19: Kapazität | CQ19: Anwendbare Personen × Kapazität | CR19: Aromen × Kapazität | CS19: Artikel × Kapazität | CT19: Farbe × Kapazität | CU19: Gewicht × Kapazität | CV19: Größe × Kapazität | CW19: Haarlänge × Kapazität | CX19: Kapazität × Komposition | CY19: Kapazität × Material | CZ19: Kapazität × Menge | DA19: Kapazität × Modell | DB19: Kapazität × Stil | DC19: Kapazität | DD19: Anwendbare Personen × Kapazität | DE19: Aromen × Kapazität | DF19: Artikel × Kapazität | DG19: Farbe × Kapazität | DH19: Gewicht × Kapazität | DI19: Größe × Kapazität | DJ19: Haarlänge × Kapazität | DK19: Kapazität × Komposition | DL19: Kapazität × Material | DM19: Kapazität × Menge | DN19: Kapazität × Modell | DO19: Kapazität × Stil | DP19: Kapazität | DQ19: Anwendbare Personen × Kapazität | DR19: Aromen × Kapazität | DS19: Artikel × Kapazität | DT19: Farbe × Kapazität | DU19: Gewicht × Kapazität | DV19: Größe × Kapazität | DW19: Haarlänge × Kapazität | DX19: Kapazität × Komposition | DY19: Kapazität × Material | DZ19: Kapazität × Menge | EA19: Kapazität × Modell | EB19: Kapazität × Stil | EC19: Kapazität | ED19: Anwendbare Personen × Kapazität | EE19: Aromen × Kapazität | EF19: Artikel × Kapazität | EG19: Farbe × Kapazität | EH19: Gewicht × Kapazität | EI19: Größe × Kapazität | EJ19: Haarlänge × Kapazität | EK19: Kapazität × Komposition | EL19: Kapazität × Material | EM19: Kapazität × Menge | EN19: Kapazität × Modell | EO19: Kapazität × Stil | EP19: Kapazität | EQ19: Anwendbare Personen × Kapazität | ER19: Aromen × Kapazität | ES19: Artikel × Kapazität | ET19: Farbe × Kapazität | EU19: Gewicht × Kapazität | EV19: Größe × Kapazität | EW19: Haarlänge × Kapazität | EX19: Kapazität × Komposition | EY19: Kapazität × Material | EZ19: Kapazität × Menge | FA19: Kapazität × Modell | FB19: Kapazität × Stil
